Workbook
Name Slicer_Category_Groups: #N/A
Name Slicer_MMM_YYY: #N/A
Name Slicer_Sales_person: #N/A
Name Slicer_Channel: #N/A
Name Slicer_Country: #N/A

Sheet Brief
A1: Assignment
A2: Excel Mastery Assignment: Sales Operations & Analytics | AD2: {=Region&" 'Brief'!A26 "&Country&" | "&City} -> #NAME?
A4: Overview:
A5: You are an analyst for a multi-regional electronics distributor. The 'Data' sheet contains 632 rows and 15 columns of transactional data with intentional data-quality issues.
A6: Your job is to clean, enrich, analyze, and present insights via a dynamic dashboard.
A8: Part A — Data Cleaning & Preparation:
A9: 1) Create a staging table where you:
A10: • Remove exact duplicate rows (define and document your duplicate criteria).
A11: • Fix data types (dates as Dates, numeric fields as numbers).
A12: • Handle missing values for City, Salesperson, and Channel using reasonable business logic (document your approach).
A13: • Flag and correct suspicious UnitPrice values (e.g., negative prices) and discounts (e.g., > 30%).
A14: • Ensure RequiredDate is not earlier than OrderDate; where it is, impute a corrected RequiredDate (explain your rule).
A15: • Add a derived 'LeadTimeDays' = RequiredDate − OrderDate (in days).
A17: 2) Create calculated columns (do these in Excel, not by formula in the data source):
... A67: 15) Ensure your dashboard responds to slicers without broken references.

Sheet READ ME
A1: READ ME : SALES ANALYSIS PROJECT
A3: Project Overview
A4: This project analyzes transactional sales data from a multi-regional electronics distributor. The dataset contains 632 rows and 15 columns, with intentional data quality issues.
A5: The objective was to:
A6: Clean and prepare the dataset
A7: Perform analytical tasks to generate business insights
A8: Build a scenario model to simulate business decisions
A9: Present findings in a structured and interpretable format
A12: Data issues identified
A13: The dataset contained several inconsistencies and quality issues:
A14: Duplicate records within the dataset
A15: Missing values in City, Salesperson, and Channel fields
... A130: Capability to present findings in a structured format

Sheet Data
A1: OrderID | B1: OrderDate | C1: RequiredDate | D1: Region | E1: Country | F1: City | G1: CustomerSegment | H1: Channel | I1: Salesperson | J1: ProductCategory | K1: SKU | L1: UnitCost | M1: UnitPrice | N1: DiscountPct | O1: Quantity
A2: ORD-2024-275203 | B2: 45362 | C2: 45388 | D2: Africa | E2: Kenya | F2: Kisumu | G2: Corporate | H2: Retail | I2: C. Otieno | J2: Components | K2: CMP-8270 | L2: 279.24 | M2: 608.9 | N2: 0.112 | O2: 9
A3: ORD-2024-358795 | B3: 45588 | C3: 45587 | D3: Africa | E3: Nigeria | F3: Port Harcourt | G3: Education | H3: Online | I3: J. Njeri | J3: Printers | K3: PRN-9322 | L3: 1084.39 | M3: 759.33 | N3: 0.237 | O3: 31
A4: ORD-2023-373538 | B4: 44985 | C4: 45010 | D4: Africa | E4: Kenya | F4: Nairobi | G4: Corporate | H4: Retail | I4: I. Johnson | J4: Networking | K4: NET-9666 | L4: 1460.76 | M4: -30.66 | N4: 0.131 | O4: 12
A5: ORD-2025-168148 | B5: 45745 | C5: 45749 | D5: Africa | E5: Nigeria | F5: Lagos | G5: Non-Profit | H5: Marketplace | I5: G. Dubois | J5: Phones | K5: PHN-4556 | L5: 259.93 | M5: 255.94 | N5: 0.072 | O5: 22
A6: ORD-2023-824839 | B6: 45266 | C6: 45291 | D6: Asia | E6: Japan | F6: Osaka | G6: Consumer | H6: Retail | I6: L. Okafor | J6: Printers | K6: PRN-8041 | L6: 663.03 | M6: 813.51 | N6: 0.102 | O6: 15
A7: ORD-2023-723587 | B7: 44928 | C7: 44931 | D7: Americas | E7: Canada | F7: Toronto | G7: Corporate | H7: Distributor | I7: B. Chen | J7: Laptops | K7: LAP-8555 | L7: 315.87 | M7: 591.68 | N7: 0 | O7: 7
A8: ORD-2024-336584 | B8: 45653 | C8: 45671 | D8: Asia | E8: India | F8: Bengaluru | G8: Small Business | H8: Marketplace | I8: E. Garcia | J8: Monitors | K8: MON-8629 | L8: 586.07 | M8: 845.97 | N8: 0.147 | O8: 4
A9: ORD-2023-112666 | B9: 44941 | C9: 44939 | D9: Africa | E9: Nigeria | F9: Abuja | G9: Education | H9: Online | I9: O. Wang | J9: Printers | K9: PRN-6276 | L9: 28.38 | M9: 47.22 | N9: 0.194 | O9: 18
A10: ORD-2024-589570 | B10: 45416 | C10: 45441 | D10: Africa | E10: Nigeria | F10: Abuja | G10: Non-Profit | H10: Marketplace | I10: O. Wang | J10: Monitors | K10: MON-6892 | L10: 1295.34 | M10: 2530.81 | N10: 0.031 | O10: 6
A11: ORD-2025-997421 | B11: 45798 | C11: 45817 | D11: Americas | E11: Brazil | F11: São Paulo | G11: Non-Profit | H11: Online | I11: A. Patel | J11: Components | K11: CMP-3731 | L11: 1331.38 | M11: 2309.56 | N11: 0.149 | O11: 31
A12: ORD-2024-210687 | B12: 45319 | C12: 45331 | D12: Europe | E12: Germany | F12: Berlin | G12: Corporate | H12: Online | I12: G. Dubois | J12: Accessories | K12: ACC-7938 | L12: 644.17 | M12: 700.12 | N12: 0.006 | O12: 23
A13: ORD-2025-515515 | B13: 45660 | C13: 45680 | D13: Asia | E13: Japan | F13: Osaka | G13: Corporate | H13: Distributor | I13: F. Müller | J13: Phones | K13: PHN-7019 | L13: 908.6 | M13: 691.37 | N13: 0.25 | O13: 20
... A34: ORD-2025-474710 | B34: 45862 | C34: 45875 | D34: Africa | E34: South Africa | F34: Johannesburg | G34: Education | H34: Marketplace | I34: D. Smith | J34: Networking | K34: NET-7966 | L34: 1463.9 | M34: 2633.02 | N34: 0.084 | O34: 4
A35: ORD-2024-629525 | B35: 45400 | C35: 45420 | D35: Europe | E35: United Kingdom | F35: London | G35: Non-Profit | I35: D. Smith | J35: Laptops | K35: LAP-9932 | L35: 645.33 | M35: 1321.85 | N35: 0 | O35: 10
A36: ORD-2024-167215 | B36: 45527 | C36: 45525 | D36: Africa | E36: South Africa | F36: Johannesburg | G36: Education | H36: Retail | I36: E. Garcia | J36: Components | K36: CMP-1559 | L36: 1432.52 | M36: 3036.87 | N36: 0 | O36: 9
A37: ORD-2023-864121 | B37: 45012 | C37: 45038 | D37: Asia | E37: India | F37: Delhi | G37: Non-Profit | H37: Marketplace | I37: J. Njeri | J37: Printers | K37: PRN-4506 | L37: 178.53 | M37: 199.37 | N37: 0.101 | O37: 37
A38: ORD-2024-692673 | B38: 45358 | C38: 45376 | D38: Europe | E38: Germany | F38: Munich | G38: Corporate | H38: Online | I38: B. Chen | J38: Components | K38: CMP-7617 | L38: 712.84 | M38: 927.51 | N38: 0.243 | O38: 27
A39: ORD-2025-718992 | B39: 45832 | C39: 45848 | D39: Asia | E39: China | F39: Shanghai | G39: Enterprise | H39: Direct | I39: N. Brown | J39: Components | K39: CMP-8390 | L39: 757.19 | M39: 1735.41 | N39: 0.136 | O39: 8
A40: ORD-2024-599522 | B40: 45401 | C40: 45418 | D40: Africa | E40: Nigeria | F40: Port Harcourt | G40: Non-Profit | H40: Online | I40: A. Patel | J40: Printers | K40: PRN-7303 | L40: 865.33 | M40: 1395.64 | N40: 0.175 | O40: 13
A41: ORD-2023-651638 | B41: 45094 | C41: 45101 | D41: Americas | E41: USA | F41: San Francisco | G41: Corporate | H41: Retail | I41: I. Johnson | J41: Printers | K41: PRN-6536 | L41: 313.99 | M41: 454.42 | N41: 0.129 | O41: 9
A42: ORD-2024-635626 | B42: 45531 | C42: 45554 | D42: Europe | E42: Germany | F42: Berlin | G42: Small Business | H42: Direct | I42: D. Smith | J42: Monitors | K42: MON-9967 | L42: 1024.01 | M42: 1580.97 | N42: 0.037 | O42: 27
A43: ORD-2024-296582 | B43: 45302 | C43: 45324 | D43: Africa | E43: South Africa | F43: Durban | G43: Consumer | H43: Online | I43: K. Singh | J43: Networking | K43: NET-1412 | L43: 1206.2 | M43: 1759.79 | N43: 0 | O43: 6
A44: ORD-2024-998320 | B44: 45590 | C44: 45610 | D44: Africa | E44: Kenya | F44: Mombasa | G44: Corporate | H44: Direct | I44: H. Kim | J44: Printers | K44: PRN-3143 | L44: 1396.48 | M44: 3204.5 | N44: 0.318 | O44: 14
A45: ORD-2025-820255 | B45: 45806 | C45: 45828 | D45: Europe | E45: Germany | F45: Berlin | G45: Corporate | H45: Direct | I45: A. Patel | J45: Printers | K45: PRN-9787 | L45: 483.47 | M45: 1135.43 | N45: 0.146 | O45: 11
A46: ORD-2024-389336 | B46: 45432 | C46: 45445 | D46: Americas | E46: Canada | F46: Vancouver | G46: Enterprise | H46: Marketplace | I46: K. Singh | J46: Components | K46: CMP-5946 | L46: 675.43 | M46: 996.36 | N46: 0.182 | O46: 22
A47: ORD-2023-308124 | B47: 45035 | C47: 45046 | D47: Asia | E47: India | F47: Delhi | G47: Small Business | H47: Retail | I47: A. Patel | J47: Networking | K47: NET-2062 | L47: 826.55 | M47: 1397.05 | N47: 0.169 | O47: 28
... A77: ORD-2023-722117 | B77: 45187 | C77: 45207 | D77: Asia | E77: India | F77: Delhi | G77: Small Business | H77: Direct | I77: B. Chen | J77: Components | K77: CMP-1009 | L77: 825.64 | M77: 1108.43 | N77: 0.114 | O77: 7
A78: ORD-2024-446699 | B78: 45532 | C78: 45560 | D78: Americas | E78: Brazil | F78: Rio de Janeiro | G78: Non-Profit | H78: Online | J78: Accessories | K78: ACC-4490 | L78: 1394.65 | M78: 3144.1 | N78: 0.134 | O78: 13
A79: ORD-2024-451005 | B79: 45473 | C79: 45471 | D79: Americas | E79: Brazil | F79: Rio de Janeiro | G79: Small Business | H79: Direct | I79: L. Okafor | J79: Accessories | K79: ACC-9162 | L79: 1112.98 | M79: 2095.73 | N79: 0.072 | O79: 17
A80: ORD-2023-290279 | B80: 45091 | C80: 45093 | D80: Europe | E80: United Kingdom | F80: Manchester | G80: Non-Profit | H80: Direct | I80: K. Singh | J80: Components | K80: CMP-5820 | L80: 357.36 | M80: 703.62 | N80: 0.257 | O80: 20
A81: ORD-2024-192263 | B81: 45617 | C81: 45647 | D81: Europe | E81: France | F81: Marseille | G81: Small Business | H81: Direct | I81: I. Johnson | J81: Monitors | K81: MON-7943 | L81: 1122.68 | M81: 1997.19 | N81: 0.186 | O81: 3
A82: ORD-2023-159379 | B82: 44965 | C82: 44968 | D82: Africa | E82: South Africa | F82: Cape Town | G82: Corporate | H82: Direct | I82: M. Rossi | J82: Networking | K82: NET-5018 | L82: 1410.05 | M82: 2763.95 | N82: 0.161 | O82: 26
A83: ORD-2023-343322 | B83: 45157 | C83: 45181 | D83: Americas | E83: Canada | F83: Vancouver | G83: Enterprise | H83: Retail | I83: I. Johnson | J83: Printers | K83: PRN-9669 | L83: 1183.95 | M83: 1503.53 | N83: 0.241 | O83: 16
A84: ORD-2025-114382 | B84: 45791 | C84: 45801 | D84: Europe | E84: France | F84: Paris | G84: Small Business | H84: Marketplace | I84: K. Singh | J84: Components | K84: CMP-2865 | L84: 170.39 | M84: 388.04 | N84: 0.084 | O84: 15
A85: ORD-2025-488349 | B85: 45770 | C85: 45769 | D85: Americas | E85: USA | F85: San Francisco | G85: Non-Profit | H85: Distributor | I85: D. Smith | J85: Monitors | K85: MON-3371 | L85: 23.24 | M85: 44.57 | N85: 0.215 | O85: 15
A86: ORD-2025-330203 | B86: 45741 | C86: 45764 | D86: Europe | E86: United Kingdom | F86: London | G86: Consumer | H86: Retail | I86: H. Kim | J86: Networking | K86: NET-7166 | L86: 1421.19 | M86: 1808.26 | N86: 0.104 | O86: 13
A87: ORD-2023-841426 | B87: 45282 | C87: 45283 | D87: Africa | E87: South Africa | F87: Cape Town | G87: Non-Profit | H87: Marketplace | I87: D. Smith | J87: Components | K87: CMP-4531 | L87: 1186.18 | M87: 1285.09 | N87: 0.07 | O87: 11
A88: ORD-2024-594592 | B88: 45388 | C88: 45407 | D88: Asia | E88: China | F88: Shanghai | G88: Corporate | H88: Retail | I88: K. Singh | J88: Components | K88: CMP-8196 | L88: 1366.48 | M88: 1678.14 | N88: 0.154 | O88: 10
A89: ORD-2025-863978 | B89: 45876 | C89: 45888 | D89: Africa | E89: Kenya | F89: Nakuru | G89: Corporate | I89: M. Rossi | J89: Components | K89: CMP-2854 | L89: 601.51 | M89: 679.35 | N89: 0.188 | O89: 3
A90: ORD-2024-604471 | B90: 45312 | C90: 45316 | D90: Asia | E90: India | F90: Delhi | G90: Consumer | H90: Direct | I90: C. Otieno | J90: Monitors | K90: MON-8973 | L90: 523.7 | M90: 1109.92 | N90: 0.03 | O90: 11
A91: ORD-2023-258768 | B91: 45106 | C91: 45109 | D91: Asia | E91: Japan | F91: Nagoya | G91: Education | H91: Marketplace | I91: F. Müller | J91: Monitors | K91: MON-2990 | L91: 55.65 | M91: 83.57 | N91: 0.066 | O91: 8
A92: ORD-2025-626047 | B92: 45775 | C92: 45792 | D92: Asia | E92: Japan | F92: Nagoya | G92: Education | H92: Direct | I92: N. Brown | J92: Networking | K92: NET-1966 | L92: 691.19 | M92: 1284.3 | N92: 0.074 | O92: 7
A93: ORD-2025-526752 | B93: 45817 | C93: 45833 | D93: Asia | E93: India | F93: Hyderabad | G93: Enterprise | H93: Distributor | I93: M. Rossi | J93: Phones | K93: PHN-3482 | L93: 527.33 | M93: 911.72 | N93: 0.144 | O93: 25
A94: ORD-2023-374486 | B94: 45101 | C94: 45100 | D94: Americas | E94: Brazil | F94: Rio de Janeiro | G94: Non-Profit | H94: Retail | I94: E. Garcia | J94: Printers | K94: PRN-6490 | L94: 804.01 | M94: 1405.07 | N94: 0.096 | O94: 8
A95: ORD-2024-997336 | B95: 45569 | C95: 45598 | D95: Africa | E95: Nigeria | F95: Abuja | G95: Corporate | H95: Distributor | I95: F. Müller | J95: Accessories | K95: ACC-9038 | L95: 412.09 | M95: 968.94 | N95: 0.099 | O95: 23
A96: ORD-2025-725646 | B96: 45910 | C96: 45930 | D96: Africa | E96: Kenya | F96: Mombasa | G96: Corporate | H96: Direct | I96: L. Okafor | J96: Phones | K96: PHN-6954 | L96: 1009.48 | M96: 1088.81 | N96: 0.16 | O96: 6
A97: ORD-2023-868734 | B97: 45022 | C97: 45043 | D97: Europe | E97: United Kingdom | F97: Manchester | G97: Enterprise | H97: Distributor | I97: I. Johnson | J97: Printers | K97: PRN-8970 | L97: 1084.79 | M97: 2484.99 | N97: 0.034 | O97: 18
A98: ORD-2025-262491 | B98: 45870 | C98: 45885 | D98: Asia | E98: India | G98: Enterprise | H98: Direct | I98: O. Wang | J98: Monitors | K98: MON-1822 | L98: 24.44 | M98: 28.69 | N98: 0.146 | O98: 6
A99: ORD-2024-638884 | B99: 45440 | C99: 45438 | D99: Africa | E99: Nigeria | F99: Abuja | G99: Enterprise | H99: Online | I99: F. Müller | J99: Accessories | K99: ACC-5177 | L99: 1227.08 | M99: 1896.62 | N99: 0 | O99: 18
A100: ORD-2025-541501 | B100: 45860 | C100: 45887 | D100: Asia | E100: China | F100: Shenzhen | G100: Non-Profit | H100: Marketplace | I100: M. Rossi | J100: Networking | K100: NET-1804 | L100: 547.32 | M100: 419.17 | N100: 0.092 | O100: 14
A101: ORD-2023-422918 | B101: 44985 | C101: 45005 | D101: Europe | E101: Germany | F101: Berlin | G101: Small Business | H101: Direct | I101: H. Kim | J101: Laptops | K101: LAP-3679 | L101: 1200.78 | M101: 2001.17 | N101: 0.292 | O101: 18
A102: ORD-2025-328504 | B102: 45684 | C102: 45703 | D102: Asia | E102: China | F102: Shenzhen | G102: Non-Profit | H102: Direct | I102: L. Okafor | J102: Phones | K102: PHN-8368 | L102: 1253.22 | M102: 3104.71 | N102: 0 | O102: 17
A103: ORD-2024-851883 | B103: 45304 | C103: 45313 | D103: Asia | E103: India | F103: Mumbai | G103: Enterprise | H103: Marketplace | I103: J. Njeri | J103: Components | K103: CMP-8141 | L103: 313.6 | M103: 334.28 | N103: 0.14 | O103: 22
A104: ORD-2025-662997 | B104: 45747 | C104: 45751 | D104: Africa | E104: Kenya | F104: Nakuru | G104: Corporate | H104: Direct | I104: C. Otieno | J104: Laptops | K104: LAP-7136 | L104: 862.08 | M104: 1952.83 | N104: 0 | O104: 7
A105: ORD-2024-478165 | B105: 45631 | C105: 45654 | D105: Americas | E105: Canada | F105: Vancouver | G105: Corporate | H105: Direct | I105: F. Müller | J105: Accessories | K105: ACC-2386 | L105: 107.03 | M105: 242.29 | N105: 0.18 | O105: 30
A106: ORD-2024-771210 | B106: 45549 | C106: 45570 | D106: Asia | E106: China | F106: Shanghai | G106: Small Business | H106: Online | I106: H. Kim | J106: Laptops | K106: LAP-5150 | L106: 1405.56 | M106: 2968.87 | N106: 0.169 | O106: 5
A107: ORD-2024-155337 | B107: 45433 | C107: 45439 | D107: Africa | E107: South Africa | F107: Johannesburg | G107: Non-Profit | H107: Online | I107: M. Rossi | J107: Components | K107: CMP-8101 | L107: 1157.51 | M107: 1394.3 | N107: 0.278 | O107: 12
A108: ORD-2023-251563 | B108: 45057 | C108: 45084 | D108: Africa | E108: Kenya | F108: Mombasa | G108: Corporate | H108: Online | I108: J. Njeri | J108: Phones | K108: PHN-8970 | L108: 12.85 | M108: 15.41 | N108: 0.137 | O108: 39
A109: ORD-2024-286833 | B109: 45518 | C109: 45539 | D109: Europe | E109: United Kingdom | F109: Manchester | G109: Non-Profit | H109: Online | I109: J. Njeri | J109: Phones | K109: PHN-2341 | L109: 1138.8 | M109: 2250.81 | N109: 0.123 | O109: 12
A110: ORD-2024-792558 | B110: 45581 | C110: 45604 | D110: Asia | E110: Japan | F110: Osaka | G110: Small Business | H110: Retail | I110: J. Njeri | J110: Networking | K110: NET-6387 | L110: 82.14 | M110: 166.04 | N110: 0 | O110: 10
... A121: ORD-2025-956101 | B121: 45847 | C121: 45856 | D121: Americas | E121: Canada | F121: Vancouver | G121: Education | H121: Distributor | I121: I. Johnson | J121: Laptops | K121: LAP-2218 | L121: 57.96 | M121: 88.51 | N121: 0.043 | O121: 7
A122: ORD-2025-184082 | B122: 45827 | C122: 45850 | D122: Europe | E122: United Kingdom | G122: Non-Profit | H122: Direct | J122: Networking | K122: NET-6370 | L122: 801.24 | M122: 1959.09 | N122: 0.123 | O122: 23
A123: ORD-2023-576840 | B123: 45249 | C123: 45273 | D123: Europe | E123: France | F123: Lyon | G123: Non-Profit | H123: Direct | I123: H. Kim | J123: Monitors | K123: MON-3745 | L123: 1297.42 | M123: 2742.97 | N123: 0.069 | O123: 9
A124: ORD-2023-178249 | B124: 45289 | C124: 45311 | D124: Africa | E124: Kenya | F124: Kisumu | G124: Corporate | H124: Direct | I124: L. Okafor | J124: Phones | K124: PHN-7924 | L124: 1395.49 | M124: 1679.42 | N124: 0.203 | O124: 12
A125: ORD-2024-588972 | B125: 45598 | C125: 45625 | D125: Americas | E125: Brazil | F125: Brasília | G125: Small Business | H125: Direct | I125: I. Johnson | J125: Networking | K125: NET-8561 | L125: 1363.51 | M125: 1433.9 | N125: 0.057 | O125: 8
A126: ORD-2023-603238 | B126: 45159 | C126: 45173 | D126: Americas | E126: Canada | F126: Montreal | G126: Education | H126: Distributor | I126: F. Müller | J126: Components | K126: CMP-2136 | L126: 178.19 | M126: 284.43 | N126: 0.089 | O126: 8
A127: ORD-2023-883066 | B127: 45150 | C127: 45175 | D127: Asia | E127: China | F127: Shanghai | G127: Small Business | H127: Retail | I127: B. Chen | J127: Components | K127: CMP-6352 | L127: 950.77 | M127: 694.78 | N127: 0.084 | O127: 14
A128: ORD-2024-584090 | B128: 45450 | C128: 45469 | D128: Europe | E128: Germany | F128: Berlin | G128: Non-Profit | H128: Marketplace | I128: M. Rossi | J128: Components | K128: CMP-2040 | L128: 1064.32 | M128: 1848.39 | N128: 0.073 | O128: 38
A129: ORD-2025-537785 | B129: 45874 | C129: 45883 | D129: Europe | E129: United Kingdom | F129: London | G129: Non-Profit | H129: Direct | I129: E. Garcia | J129: Components | K129: CMP-6346 | L129: 41.76 | M129: 45.19 | N129: 0.179 | O129: 23
A130: ORD-2024-605518 | B130: 45442 | C130: 45456 | D130: Americas | E130: USA | F130: San Francisco | G130: Small Business | H130: Retail | I130: F. Müller | J130: Phones | K130: PHN-4356 | L130: 157.78 | M130: 361.1 | N130: 0.187 | O130: 9
A131: ORD-2023-521818 | B131: 44948 | C131: 44956 | D131: Americas | E131: USA | F131: San Francisco | G131: Small Business | H131: Online | I131: A. Patel | J131: Networking | K131: NET-4155 | L131: 413.52 | M131: 1004.34 | N131: 0.111 | O131: 18
A132: ORD-2025-650719 | B132: 45700 | C132: 45716 | D132: Americas | E132: Brazil | F132: São Paulo | G132: Non-Profit | H132: Direct | I132: B. Chen | J132: Monitors | K132: MON-5179 | L132: 414.95 | M132: 1027.73 | N132: 0.063 | O132: 8
A133: ORD-2025-501927 | B133: 45719 | C133: 45740 | D133: Africa | E133: Nigeria | F133: Abuja | G133: Enterprise | H133: Direct | I133: H. Kim | J133: Accessories | K133: ACC-4056 | L133: 555.95 | M133: 468.09 | N133: 0.142 | O133: 11
A134: ORD-2023-430904 | B134: 44953 | C134: 44957 | D134: Europe | E134: United Kingdom | F134: Manchester | G134: Enterprise | H134: Online | I134: N. Brown | J134: Laptops | K134: LAP-9782 | L134: 941.2 | M134: 668.02 | N134: 0.22 | O134: 16
... A187: ORD-2023-399631 | B187: 45099 | C187: 45128 | D187: Europe | E187: France | F187: Lyon | G187: Corporate | H187: Retail | I187: J. Njeri | J187: Accessories | K187: ACC-3385 | L187: 734.34 | M187: 887.9 | N187: 0.025 | O187: 12
A188: ORD-2025-542939 | B188: 45670 | C188: 45696 | D188: Europe | E188: France | F188: Paris | G188: Non-Profit | I188: E. Garcia | J188: Monitors | K188: MON-1593 | L188: 594.74 | M188: 1020.69 | N188: 0.211 | O188: 6
A189: ORD-2023-521818 | B189: 44955 | C189: 44985 | D189: Asia | E189: India | F189: Bengaluru | G189: Non-Profit | H189: Retail | I189: B. Chen | J189: Accessories | K189: ACC-4631 | L189: 1262.1 | M189: 1395.53 | N189: 0.233 | O189: 25
A190: ORD-2023-825836 | B190: 45126 | C190: 45138 | D190: Americas | E190: Brazil | F190: Rio de Janeiro | G190: Corporate | H190: Retail | I190: C. Otieno | J190: Monitors | K190: MON-7869 | L190: 1334.64 | M190: 2273.42 | N190: 0.118 | O190: 14
A191: ORD-2024-503082 | B191: 45431 | C191: 45451 | D191: Americas | E191: Brazil | F191: Brasília | G191: Small Business | H191: Retail | I191: E. Garcia | J191: Monitors | K191: MON-4271 | L191: 1075.9 | M191: 1242.15 | N191: 0.012 | O191: 7
A192: ORD-2024-760799 | B192: 45325 | C192: 45341 | D192: Asia | E192: China | F192: Shenzhen | G192: Small Business | H192: Online | I192: H. Kim | J192: Laptops | K192: LAP-5531 | L192: 993.75 | M192: 1310.29 | N192: 0.215 | O192: 19
A193: ORD-2023-197661 | B193: 45146 | C193: 45160 | D193: Europe | E193: United Kingdom | F193: Birmingham | G193: Non-Profit | H193: Direct | I193: N. Brown | J193: Monitors | K193: MON-7511 | L193: 446.69 | M193: 967.25 | N193: 0.094 | O193: 10
A194: ORD-2024-212990 | B194: 45516 | C194: 45538 | D194: Americas | E194: USA | F194: Austin | G194: Consumer | H194: Distributor | I194: I. Johnson | J194: Laptops | K194: LAP-7979 | L194: 797.8 | M194: 886.22 | N194: 0.236 | O194: 36
A195: ORD-2023-925146 | B195: 45214 | C195: 45243 | D195: Asia | E195: China | F195: Shenzhen | G195: Non-Profit | H195: Distributor | I195: J. Njeri | J195: Printers | K195: PRN-4983 | L195: 986.44 | M195: 790.61 | N195: 0.072 | O195: 6
A196: ORD-2023-177794 | B196: 45050 | C196: 45072 | D196: Americas | E196: USA | F196: San Francisco | G196: Enterprise | H196: Online | I196: J. Njeri | J196: Networking | K196: NET-5941 | L196: 249.71 | M196: 361.33 | N196: 0.094 | O196: 12
A197: ORD-2024-444710 | B197: 45557 | C197: 45566 | D197: Americas | E197: Brazil | F197: São Paulo | G197: Non-Profit | H197: Online | I197: K. Singh | J197: Monitors | K197: MON-6341 | L197: 1378.8 | M197: 1952.04 | N197: 0.159 | O197: 19
A198: ORD-2024-668926 | B198: 45588 | C198: 45610 | D198: Asia | E198: Japan | F198: Osaka | G198: Non-Profit | H198: Direct | I198: B. Chen | J198: Phones | K198: PHN-9789 | L198: 1406.4 | M198: 1564.76 | N198: 0.185 | O198: 17
A199: ORD-2024-968374 | B199: 45333 | C199: 45354 | D199: Africa | E199: Kenya | F199: Kisumu | G199: Enterprise | H199: Online | I199: B. Chen | J199: Phones | K199: PHN-5082 | L199: 516.86 | M199: 852.54 | N199: 0.051 | O199: 14
A200: ORD-2023-575584 | B200: 44956 | C200: 44978 | D200: Europe | E200: Germany | F200: Munich | G200: Small Business | H200: Marketplace | I200: G. Dubois | J200: Networking | K200: NET-3460 | L200: 1142.88 | M200: 1465.29 | N200: 0.186 | O200: 7
... A236: ORD-2023-946143 | B236: 44999 | C236: 45015 | D236: Africa | E236: South Africa | F236: Cape Town | G236: Consumer | H236: Distributor | I236: K. Singh | J236: Components | K236: CMP-8230 | L236: 1309.77 | M236: 1589.07 | N236: 0.102 | O236: 10
A237: ORD-2024-281211 | B237: 45302 | C237: 45324 | D237: Asia | E237: Japan | F237: Nagoya | G237: Small Business | H237: Online | J237: Printers | K237: PRN-7816 | L237: 1237.68 | M237: 1432.8 | N237: 0.068 | O237: 13
A238: ORD-2024-805860 | B238: 45548 | C238: 45567 | D238: Africa | E238: Kenya | F238: Mombasa | G238: Small Business | H238: Retail | I238: M. Rossi | J238: Phones | K238: PHN-8804 | L238: 1338.99 | M238: 1765.76 | N238: 0.126 | O238: 24
A239: ORD-2025-132174 | B239: 45855 | C239: 45861 | D239: Americas | E239: Canada | F239: Vancouver | G239: Consumer | H239: Online | I239: H. Kim | J239: Components | K239: CMP-8851 | L239: 1364.89 | M239: 2757.54 | N239: 0.172 | O239: 61
A240: ORD-2023-964434 | B240: 45258 | C240: 45267 | D240: Asia | E240: India | F240: Delhi | G240: Enterprise | H240: Marketplace | I240: L. Okafor | J240: Phones | K240: PHN-2447 | L240: 699.33 | M240: 873.75 | N240: 0.235 | O240: 10
A241: ORD-2024-897622 | B241: 45381 | C241: 45406 | D241: Americas | E241: USA | F241: Austin | G241: Non-Profit | H241: Online | I241: G. Dubois | J241: Laptops | K241: LAP-2846 | L241: 160.82 | M241: 258.52 | N241: 0.13 | O241: 17
A242: ORD-2023-517216 | B242: 45188 | C242: 45207 | D242: Asia | E242: India | F242: Bengaluru | G242: Education | H242: Direct | I242: J. Njeri | J242: Printers | K242: PRN-5005 | L242: 385.32 | M242: 606.76 | N242: 0.086 | O242: 8
A243: ORD-2025-509940 | B243: 45793 | C243: 45804 | D243: Asia | E243: China | F243: Beijing | G243: Enterprise | H243: Online | I243: F. Müller | J243: Phones | K243: PHN-3800 | L243: 918.12 | M243: 1337.69 | N243: 0.095 | O243: 8
A244: ORD-2025-646342 | B244: 45871 | C244: 45877 | D244: Asia | E244: Japan | F244: Osaka | G244: Consumer | H244: Direct | I244: N. Brown | J244: Laptops | K244: LAP-4828 | L244: 1225.94 | M244: 1793.08 | N244: 0.136 | O244: 22
A245: ORD-2024-866535 | B245: 45630 | C245: 45638 | D245: Europe | E245: Germany | F245: Frankfurt | G245: Enterprise | H245: Marketplace | I245: B. Chen | J245: Printers | K245: PRN-5492 | L245: 72.06 | M245: 122.74 | N245: 0.238 | O245: 8
A246: ORD-2023-747341 | B246: 45035 | C246: 45044 | D246: Americas | E246: Brazil | F246: Rio de Janeiro | G246: Corporate | H246: Distributor | I246: M. Rossi | J246: Phones | K246: PHN-7132 | L246: 1013.54 | M246: 927.93 | N246: 0.175 | O246: 16
...

Sheet Staging Data
A1: Order ID | B1: Order Date | C1: Required Date | D1: Region | E1: Country | F1: City | G1: Customer Segment | H1: Channel | I1: Sales person | J1: Product Category | K1: SKU | L1: UnitCost | M1: Unit Price | N1: Discount % | O1: Quantity | P1: Negative prices | Q1: Clean Unit Prices | R1: Discounts >30% | S1: Clean discounts | T1: Date Diff | U1: Validated Required date | V1: Lead Time days | W1: Gross Revenue | X1: Cost of Goods | Y1: Gross Profit | Z1: Margin % | AA1: MMM-YYY | AB1: Quarters | AC1: Region Hierarchy | AD1: Category Groups | AE1: Price Band | AF1: Clean country | AG1: Country start Date | AH1: Country Start Month | AI1: Order Month date | AJ1: On Time Flag | AK1: Flagged Discount % | AL1: What-if Discount | AM1: What if Cost | AN1: What If Quantity | AO1: What if Revenue | AP1: What if Profit
A2: ORD-2024-275203 | B2: 45362 | C2: 45388 | D2: Africa | E2: Kenya | F2: Kisumu | G2: Corporate | H2: Retail | I2: C. Otieno | J2: Components | K2: CMP-8270 | L2: 279.24 | M2: 608.9 | N2: 0.112 | O2: 9 | P2: =IF(M2>0,"Valid") -> Valid | Q2: =ABS(M2) -> 608.9 | R2: =IF(N2>30%,"Excess") -> FALSE | S2: =IF(R2="Excess",30%,N2) -> 0.112 | T2: =(C2-B2) -> 26 | U2: =IF(C2<B2,B2+7,C2) -> 45388 | V2: =(U2-B2) -> 26 | W2: =(Q2*O2*(100-S2)) -> 547396.23 | X2: =(Q2*O2) -> 5480.1 | Y2: =W2-X2 -> 541916.13 | Z2: =Y2/W2 -> 0.98998879 | AA2: Mar-2024 | AB2: ="Q"&ROUNDUP(MONTH(B2)/3,0)&"-"&YEAR(B2) -> Q1-2024 | AC2: =D2&" → "&E2&" → "&F2 -> Africa → Kenya → Kisumu | AD2: =IF(OR(J2="Laptops",J2="Phones"),"Devices",IF(OR(J2="Monitors",J2="Printers"),"Peripherals","Support")) -> Support | AE2: =IF(B2<=PERCENTILE($B$2:$B$632,0.33),"Low",IF(B2<=PERCENTILE($B$2:$B$632,0.66),"Medium","High")) -> Medium | AF2: =UPPER(TRIM(CLEAN(SUBSTITUTE(E2,CHAR(160),"")))) -> KENYA | AG2: =_xlfn.MINIFS($B$2:$B$633,$AF$2:$AF$633,AF2) -> 44946 | AH2: =TEXT(AG2,"MMM-YYYY") -> Jan-2023 | AI2: =EOMONTH(B2,0) -> 45382 | AJ2: =IF(V2<=7,1,0) -> 0 | AK2: =IF(N2>20%,1,0) -> 0 | AL2: =MIN(N2,'Scenario Modelling'!$B$2) -> 0.112 | AM2: =L2*(1+'Scenario Modelling'!$B$3) -> 321.126 | AN2: =O2*(1+'Scenario Modelling'!$B$4) -> 10.8 | AO2: =AN2*M2*(1-AL2) -> 5839.5946 | AP2: =(M2*(1-AL2)-AM2)*AN2 -> 2371.4338
A3: ORD-2024-358795 | B3: 45588 | C3: 45587 | D3: Africa | E3: Nigeria | F3: Port Harcourt | G3: Education | H3: Online | I3: J. Njeri | J3: Printers | K3: PRN-9322 | L3: 1084.39 | M3: 759.33 | N3: 0.237 | O3: 31 | P3: =IF(M3>0,"Valid") -> Valid | Q3: =ABS(M3) -> 759.33 | R3: =IF(N3>30%,"Excess") -> FALSE | S3: =IF(R3="Excess",30%,N3) -> 0.237 | T3: =(C3-B3) -> -1 | U3: =IF(C3<B3,B3+7,C3) -> 45595 | V3: =(U3-B3) -> 7 | W3: =(Q3*O3*(100-S3)) -> 2348344.2 | X3: =(Q3*O3) -> 23539.23 | Y3: =W3-X3 -> 2324805 | Z3: =Y3/W3 -> 0.98997624 | AA3: Oct-2024 | AB3: ="Q"&ROUNDUP(MONTH(B3)/3,0)&"-"&YEAR(B3) -> Q4-2024 | AC3: =D3&" → "&E3&" → "&F3 -> Africa → Nigeria → Port Harcourt | AD3: =IF(OR(J3="Laptops",J3="Phones"),"Devices",IF(OR(J3="Monitors",J3="Printers"),"Peripherals","Support")) -> Peripherals | AE3: =IF(B3<=PERCENTILE($B$2:$B$632,0.33),"Low",IF(B3<=PERCENTILE($B$2:$B$632,0.66),"Medium","High")) -> Medium | AF3: =UPPER(TRIM(CLEAN(SUBSTITUTE(E3,CHAR(160),"")))) -> NIGERIA | AG3: =_xlfn.MINIFS($B$2:$B$633,$AF$2:$AF$633,AF3) -> 44941 | AH3: =TEXT(AG3,"MMM-YYYY") -> Jan-2023 | AI3: =EOMONTH(B3,0) -> 45596 | AJ3: =IF(V3<=7,1,0) -> 1 | AK3: =IF(N3>20%,1,0) -> 1 | AL3: =MIN(N3,'Scenario Modelling'!$B$2) -> 0.237 | AM3: =L3*(1+'Scenario Modelling'!$B$3) -> 1247.0485 | AN3: =O3*(1+'Scenario Modelling'!$B$4) -> 37.2 | AO3: =AN3*M3*(1-AL3) -> 21552.519 | AP3: =(M3*(1-AL3)-AM3)*AN3 -> -24837.685
A4: ORD-2023-373538 | B4: 44985 | C4: 45010 | D4: Africa | E4: Kenya | F4: Nairobi | G4: Corporate | H4: Retail | I4: I. Johnson | J4: Networking | K4: NET-9666 | L4: 1460.76 | M4: -30.66 | N4: 0.131 | O4: 12 | P4: =IF(M4>0,"Valid") -> FALSE | Q4: =ABS(M4) -> 30.66 | R4: =IF(N4>30%,"Excess") -> FALSE | S4: =IF(R4="Excess",30%,N4) -> 0.131 | T4: =(C4-B4) -> 25 | U4: =IF(C4<B4,B4+7,C4) -> 45010 | V4: =(U4-B4) -> 25 | W4: =(Q4*O4*(100-S4)) -> 36743.802 | X4: =(Q4*O4) -> 367.92 | Y4: =W4-X4 -> 36375.882 | Z4: =Y4/W4 -> 0.98998688 | AA4: Feb-2023 | AB4: ="Q"&ROUNDUP(MONTH(B4)/3,0)&"-"&YEAR(B4) -> Q1-2023 | AC4: =D4&" → "&E4&" → "&F4 -> Africa → Kenya → Nairobi | AD4: =IF(OR(J4="Laptops",J4="Phones"),"Devices",IF(OR(J4="Monitors",J4="Printers"),"Peripherals","Support")) -> Support | AE4: =IF(B4<=PERCENTILE($B$2:$B$632,0.33),"Low",IF(B4<=PERCENTILE($B$2:$B$632,0.66),"Medium","High")) -> Low | AF4: =UPPER(TRIM(CLEAN(SUBSTITUTE(E4,CHAR(160),"")))) -> KENYA | AG4: 44946 | AH4: =TEXT(AG4,"MMM-YYYY") -> Jan-2023 | AI4: =EOMONTH(B4,0) -> 44985 | AJ4: =IF(V4<=7,1,0) -> 0 | AK4: =IF(N4>20%,1,0) -> 0 | AL4: =MIN(N4,'Scenario Modelling'!$B$2) -> 0.131 | AM4: =L4*(1+'Scenario Modelling'!$B$3) -> 1679.874 | AN4: =O4*(1+'Scenario Modelling'!$B$4) -> 14.4 | AO4: =AN4*M4*(1-AL4) -> -383.66698 | AP4: =(M4*(1-AL4)-AM4)*AN4 -> -24573.853
A5: ORD-2025-168148 | B5: 45745 | C5: 45749 | D5: Africa | E5: Nigeria | F5: Lagos | G5: Non-Profit | H5: Marketplace | I5: G. Dubois | J5: Phones | K5: PHN-4556 | L5: 259.93 | M5: 255.94 | N5: 0.072 | O5: 22 | P5: =IF(M5>0,"Valid") -> Valid | Q5: =ABS(M5) -> 255.94 | R5: =IF(N5>30%,"Excess") -> FALSE | S5: =IF(R5="Excess",30%,N5) -> 0.072 | T5: =(C5-B5) -> 4 | U5: =IF(C5<B5,B5+7,C5) -> 45749 | V5: =(U5-B5) -> 4 | W5: =(Q5*O5*(100-S5)) -> 562662.59 | X5: =(Q5*O5) -> 5630.68 | Y5: =W5-X5 -> 557031.91 | Z5: =Y5/W5 -> 0.98999279 | AA5: Mar-2025 | AB5: ="Q"&ROUNDUP(MONTH(B5)/3,0)&"-"&YEAR(B5) -> Q1-2025 | AC5: =D5&" → "&E5&" → "&F5 -> Africa → Nigeria → Lagos | AD5: =IF(OR(J5="Laptops",J5="Phones"),"Devices",IF(OR(J5="Monitors",J5="Printers"),"Peripherals","Support")) -> Devices | AE5: =IF(B5<=PERCENTILE($B$2:$B$632,0.33),"Low",IF(B5<=PERCENTILE($B$2:$B$632,0.66),"Medium","High")) -> High | AF5: =UPPER(TRIM(CLEAN(SUBSTITUTE(E5,CHAR(160),"")))) -> NIGERIA | AG5: =_xlfn.MINIFS($B$2:$B$633,$AF$2:$AF$633,AF5) -> 44941 | AH5: =TEXT(AG5,"MMM-YYYY") -> Jan-2023 | AI5: =EOMONTH(B5,0) -> 45747 | AJ5: =IF(V5<=7,1,0) -> 1 | AK5: =IF(N5>20%,1,0) -> 0 | AL5: =MIN(N5,'Scenario Modelling'!$B$2) -> 0.072 | AM5: =L5*(1+'Scenario Modelling'!$B$3) -> 298.9195 | AN5: =O5*(1+'Scenario Modelling'!$B$4) -> 26.4 | AO5: =AN5*M5*(1-AL5) -> 6270.3252 | AP5: =(M5*(1-AL5)-AM5)*AN5 -> -1621.1496
A6: ORD-2023-723587 | B6: 44928 | C6: 44931 | D6: Americas | E6: Canada | F6: Toronto | G6: Corporate | H6: Distributor | I6: B. Chen | J6: Laptops | K6: LAP-8555 | L6: 315.87 | M6: 591.68 | N6: 0 | O6: 7 | P6: =IF(M6>0,"Valid") -> Valid | Q6: =ABS(M6) -> 591.68 | R6: =IF(N6>30%,"Excess") -> FALSE | S6: =IF(R6="Excess",30%,N6) -> 0 | T6: =(C6-B6) -> 3 | U6: =IF(C6<B6,B6+7,C6) -> 44931 | V6: =(U6-B6) -> 3 | W6: =(Q6*O6*(100-S6)) -> 414176 | X6: =(Q6*O6) -> 4141.76 | Y6: =W6-X6 -> 410034.24 | Z6: =Y6/W6 -> 0.99 | AA6: Jan-2023 | AB6: ="Q"&ROUNDUP(MONTH(B6)/3,0)&"-"&YEAR(B6) -> Q1-2023 | AC6: =D6&" → "&E6&" → "&F6 -> Americas → Canada → Toronto | AD6: =IF(OR(J6="Laptops",J6="Phones"),"Devices",IF(OR(J6="Monitors",J6="Printers"),"Peripherals","Support")) -> Devices | AE6: =IF(B6<=PERCENTILE($B$2:$B$632,0.33),"Low",IF(B6<=PERCENTILE($B$2:$B$632,0.66),"Medium","High")) -> Low | AF6: =UPPER(TRIM(CLEAN(SUBSTITUTE(E6,CHAR(160),"")))) -> CANADA | AG6: =_xlfn.MINIFS($B$2:$B$633,$AF$2:$AF$633,AF6) -> 44928 | AH6: =TEXT(AG6,"MMM-YYYY") -> Jan-2023 | AI6: =EOMONTH(B6,0) -> 44957 | AJ6: =IF(V6<=7,1,0) -> 1 | AK6: =IF(N6>20%,1,0) -> 0 | AL6: =MIN(N6,'Scenario Modelling'!$B$2) -> 0 | AM6: =L6*(1+'Scenario Modelling'!$B$3) -> 363.2505 | AN6: =O6*(1+'Scenario Modelling'!$B$4) -> 8.4 | AO6: =AN6*M6*(1-AL6) -> 4970.112 | AP6: =(M6*(1-AL6)-AM6)*AN6 -> 1918.8078
A7: ORD-2024-336584 | B7: 45653 | C7: 45671 | D7: Asia | E7: India | F7: Bengaluru | G7: Small Business | H7: Marketplace | I7: E. Garcia | J7: Monitors | K7: MON-8629 | L7: 586.07 | M7: 845.97 | N7: 0.147 | O7: 4 | P7: =IF(M7>0,"Valid") -> Valid | Q7: =ABS(M7) -> 845.97 | R7: =IF(N7>30%,"Excess") -> FALSE | S7: =IF(R7="Excess",30%,N7) -> 0.147 | T7: =(C7-B7) -> 18 | U7: =IF(C7<B7,B7+7,C7) -> 45671 | V7: =(U7-B7) -> 18 | W7: =(Q7*O7*(100-S7)) -> 337890.57 | X7: =(Q7*O7) -> 3383.88 | Y7: =W7-X7 -> 334506.69 | Z7: =Y7/W7 -> 0.98998528 | AA7: Dec-2024 | AB7: ="Q"&ROUNDUP(MONTH(B7)/3,0)&"-"&YEAR(B7) -> Q4-2024 | AC7: =D7&" → "&E7&" → "&F7 -> Asia → India → Bengaluru | AD7: =IF(OR(J7="Laptops",J7="Phones"),"Devices",IF(OR(J7="Monitors",J7="Printers"),"Peripherals","Support")) -> Peripherals | AE7: =IF(B7<=PERCENTILE($B$2:$B$632,0.33),"Low",IF(B7<=PERCENTILE($B$2:$B$632,0.66),"Medium","High")) -> High | AF7: =UPPER(TRIM(CLEAN(SUBSTITUTE(E7,CHAR(160),"")))) -> INDIA | AG7: 44955 | AH7: =TEXT(AG7,"MMM-YYYY") -> Jan-2023 | AI7: =EOMONTH(B7,0) -> 45657 | AJ7: =IF(V7<=7,1,0) -> 0 | AK7: =IF(N7>20%,1,0) -> 0 | AL7: =MIN(N7,'Scenario Modelling'!$B$2) -> 0.147 | AM7: =L7*(1+'Scenario Modelling'!$B$3) -> 673.9805 | AN7: =O7*(1+'Scenario Modelling'!$B$4) -> 4.8 | AO7: =AN7*M7*(1-AL7) -> 3463.7396 | AP7: =(M7*(1-AL7)-AM7)*AN7 -> 228.63317
A8: ORD-2023-112666 | B8: 44941 | C8: 44939 | D8: Africa | E8: Nigeria | F8: Abuja | G8: Education | H8: Online | I8: O. Wang | J8: Printers | K8: PRN-6276 | L8: 28.38 | M8: 47.22 | N8: 0.194 | O8: 18 | P8: =IF(M8>0,"Valid") -> Valid | Q8: =ABS(M8) -> 47.22 | R8: =IF(N8>30%,"Excess") -> FALSE | S8: =IF(R8="Excess",30%,N8) -> 0.194 | T8: =(C8-B8) -> -2 | U8: =IF(C8<B8,B8+7,C8) -> 44948 | V8: =(U8-B8) -> 7 | W8: =(Q8*O8*(100-S8)) -> 84831.108 | X8: =(Q8*O8) -> 849.96 | Y8: =W8-X8 -> 83981.148 | Z8: =Y8/W8 -> 0.98998056 | AA8: Jan-2023 | AB8: ="Q"&ROUNDUP(MONTH(B8)/3,0)&"-"&YEAR(B8) -> Q1-2023 | AC8: =D8&" → "&E8&" → "&F8 -> Africa → Nigeria → Abuja | AD8: =IF(OR(J8="Laptops",J8="Phones"),"Devices",IF(OR(J8="Monitors",J8="Printers"),"Peripherals","Support")) -> Peripherals | AE8: =IF(B8<=PERCENTILE($B$2:$B$632,0.33),"Low",IF(B8<=PERCENTILE($B$2:$B$632,0.66),"Medium","High")) -> Low | AF8: =UPPER(TRIM(CLEAN(SUBSTITUTE(E8,CHAR(160),"")))) -> NIGERIA | AG8: =_xlfn.MINIFS($B$2:$B$633,$AF$2:$AF$633,AF8) -> 44941 | AH8: =TEXT(AG8,"MMM-YYYY") -> Jan-2023 | AI8: =EOMONTH(B8,0) -> 44957 | AJ8: =IF(V8<=7,1,0) -> 1 | AK8: =IF(N8>20%,1,0) -> 0 | AL8: =MIN(N8,'Scenario Modelling'!$B$2) -> 0.194 | AM8: =L8*(1+'Scenario Modelling'!$B$3) -> 32.637 | AN8: =O8*(1+'Scenario Modelling'!$B$4) -> 21.6 | AO8: =AN8*M8*(1-AL8) -> 822.08131 | AP8: =(M8*(1-AL8)-AM8)*AN8 -> 117.12211
A9: ORD-2024-589570 | B9: 45416 | C9: 45441 | D9: Africa | E9: Nigeria | F9: Abuja | G9: Non-Profit | H9: Marketplace | I9: O. Wang | J9: Monitors | K9: MON-6892 | L9: 1295.34 | M9: 2530.81 | N9: 0.031 | O9: 6 | P9: =IF(M9>0,"Valid") -> Valid | Q9: =ABS(M9) -> 2530.81 | R9: =IF(N9>30%,"Excess") -> FALSE | S9: =IF(R9="Excess",30%,N9) -> 0.031 | T9: =(C9-B9) -> 25 | U9: =IF(C9<B9,B9+7,C9) -> 45441 | V9: =(U9-B9) -> 25 | W9: =(Q9*O9*(100-S9)) -> 1518015.3 | X9: =(Q9*O9) -> 15184.86 | Y9: =W9-X9 -> 1502830.4 | Z9: =Y9/W9 -> 0.9899969 | AA9: May-2024 | AB9: ="Q"&ROUNDUP(MONTH(B9)/3,0)&"-"&YEAR(B9) -> Q2-2024 | AC9: =D9&" → "&E9&" → "&F9 -> Africa → Nigeria → Abuja | AD9: =IF(OR(J9="Laptops",J9="Phones"),"Devices",IF(OR(J9="Monitors",J9="Printers"),"Peripherals","Support")) -> Peripherals | AE9: =IF(B9<=PERCENTILE($B$2:$B$632,0.33),"Low",IF(B9<=PERCENTILE($B$2:$B$632,0.66),"Medium","High")) -> Medium | AF9: =UPPER(TRIM(CLEAN(SUBSTITUTE(E9,CHAR(160),"")))) -> NIGERIA | AG9: =_xlfn.MINIFS($B$2:$B$633,$AF$2:$AF$633,AF9) -> 44941 | AH9: =TEXT(AG9,"MMM-YYYY") -> Jan-2023 | AI9: =EOMONTH(B9,0) -> 45443 | AJ9: =IF(V9<=7,1,0) -> 0 | AK9: =IF(N9>20%,1,0) -> 0 | AL9: =MIN(N9,'Scenario Modelling'!$B$2) -> 0.031 | AM9: =L9*(1+'Scenario Modelling'!$B$3) -> 1489.641 | AN9: =O9*(1+'Scenario Modelling'!$B$4) -> 7.2 | AO9: =AN9*M9*(1-AL9) -> 17656.955 | AP9: =(M9*(1-AL9)-AM9)*AN9 -> 6931.54
A10: ORD-2025-997421 | B10: 45798 | C10: 45817 | D10: Americas | E10: Brazil | F10: São Paulo | G10: Non-Profit | H10: Online | I10: A. Patel | J10: Components | K10: CMP-3731 | L10: 1331.38 | M10: 2309.56 | N10: 0.149 | O10: 31 | P10: =IF(M10>0,"Valid") -> Valid | Q10: =ABS(M10) -> 2309.56 | R10: =IF(N10>30%,"Excess") -> FALSE | S10: =IF(R10="Excess",30%,N10) -> 0.149 | T10: =(C10-B10) -> 19 | U10: =IF(C10<B10,B10+7,C10) -> 45817 | V10: =(U10-B10) -> 19 | W10: =(Q10*O10*(100-S10)) -> 7148968.1 | X10: =(Q10*O10) -> 71596.36 | Y10: =W10-X10 -> 7077371.8 | Z10: =Y10/W10 -> 0.98998508 | AA10: May-2025 | AB10: ="Q"&ROUNDUP(MONTH(B10)/3,0)&"-"&YEAR(B10) -> Q2-2025 | AC10: =D10&" → "&E10&" → "&F10 -> Americas → Brazil → São Paulo | AD10: =IF(OR(J10="Laptops",J10="Phones"),"Devices",IF(OR(J10="Monitors",J10="Printers"),"Peripherals","Support")) -> Support | AE10: =IF(B10<=PERCENTILE($B$2:$B$632,0.33),"Low",IF(B10<=PERCENTILE($B$2:$B$632,0.66),"Medium","High")) -> High | AF10: =UPPER(TRIM(CLEAN(SUBSTITUTE(E10,CHAR(160),"")))) -> BRAZIL | AG10: =_xlfn.MINIFS($B$2:$B$633,$AF$2:$AF$633,AF10) -> 44955 | AH10: =TEXT(AG10,"MMM-YYYY") -> Jan-2023 | AI10: =EOMONTH(B10,0) -> 45808 | AJ10: =IF(V10<=7,1,0) -> 0 | AK10: =IF(N10>20%,1,0) -> 0 | AL10: =MIN(N10,'Scenario Modelling'!$B$2) -> 0.149 | AM10: =L10*(1+'Scenario Modelling'!$B$3) -> 1531.087 | AN10: =O10*(1+'Scenario Modelling'!$B$4) -> 37.2 | AO10: =AN10*M10*(1-AL10) -> 73114.203 | AP10: =(M10*(1-AL10)-AM10)*AN10 -> 16157.766
A11: ORD-2024-210687 | B11: 45319 | C11: 45331 | D11: Europe | E11: Germany | F11: Berlin | G11: Corporate | H11: Online | I11: G. Dubois | J11: Accessories | K11: ACC-7938 | L11: 644.17 | M11: 700.12 | N11: 0.006 | O11: 23 | P11: =IF(M11>0,"Valid") -> Valid | Q11: =ABS(M11) -> 700.12 | R11: =IF(N11>30%,"Excess") -> FALSE | S11: =IF(R11="Excess",30%,N11) -> 0.006 | T11: =(C11-B11) -> 12 | U11: =IF(C11<B11,B11+7,C11) -> 45331 | V11: =(U11-B11) -> 12 | W11: =(Q11*O11*(100-S11)) -> 1610179.4 | X11: =(Q11*O11) -> 16102.76 | Y11: =W11-X11 -> 1594076.6 | Z11: =Y11/W11 -> 0.9899994 | AA11: Jan-2024 | AB11: ="Q"&ROUNDUP(MONTH(B11)/3,0)&"-"&YEAR(B11) -> Q1-2024 | AC11: =D11&" → "&E11&" → "&F11 -> Europe → Germany → Berlin | AD11: =IF(OR(J11="Laptops",J11="Phones"),"Devices",IF(OR(J11="Monitors",J11="Printers"),"Peripherals","Support")) -> Support | AE11: =IF(B11<=PERCENTILE($B$2:$B$632,0.33),"Low",IF(B11<=PERCENTILE($B$2:$B$632,0.66),"Medium","High")) -> Medium | AF11: =UPPER(TRIM(CLEAN(SUBSTITUTE(E11,CHAR(160),"")))) -> GERMANY | AG11: 44948 | AH11: =TEXT(AG11,"MMM-YYYY") -> Jan-2023 | AI11: =EOMONTH(B11,0) -> 45322 | AJ11: =IF(V11<=7,1,0) -> 0 | AK11: =IF(N11>20%,1,0) -> 0 | AL11: =MIN(N11,'Scenario Modelling'!$B$2) -> 0.006 | AM11: =L11*(1+'Scenario Modelling'!$B$3) -> 740.7955 | AN11: =O11*(1+'Scenario Modelling'!$B$4) -> 27.6 | AO11: =AN11*M11*(1-AL11) -> 19207.372 | AP11: =(M11*(1-AL11)-AM11)*AN11 -> -1238.5837
A12: ORD-2025-515515 | B12: 45660 | C12: 45680 | D12: Asia | E12: Japan | F12: Osaka | G12: Corporate | H12: Distributor | I12: F. Müller | J12: Phones | K12: PHN-7019 | L12: 908.6 | M12: 691.37 | N12: 0.25 | O12: 20 | P12: =IF(M12>0,"Valid") -> Valid | Q12: =ABS(M12) -> 691.37 | R12: =IF(N12>30%,"Excess") -> FALSE | S12: =IF(R12="Excess",30%,N12) -> 0.25 | T12: =(C12-B12) -> 20 | U12: =IF(C12<B12,B12+7,C12) -> 45680 | V12: =(U12-B12) -> 20 | W12: =(Q12*O12*(100-S12)) -> 1379283.1 | X12: =(Q12*O12) -> 13827.4 | Y12: =W12-X12 -> 1365455.8 | Z12: =Y12/W12 -> 0.98997494 | AA12: Jan-2025 | AB12: ="Q"&ROUNDUP(MONTH(B12)/3,0)&"-"&YEAR(B12) -> Q1-2025 | AC12: =D12&" → "&E12&" → "&F12 -> Asia → Japan → Osaka | AD12: =IF(OR(J12="Laptops",J12="Phones"),"Devices",IF(OR(J12="Monitors",J12="Printers"),"Peripherals","Support")) -> Devices | AE12: =IF(B12<=PERCENTILE($B$2:$B$632,0.33),"Low",IF(B12<=PERCENTILE($B$2:$B$632,0.66),"Medium","High")) -> High | AF12: =UPPER(TRIM(CLEAN(SUBSTITUTE(E12,CHAR(160),"")))) -> JAPAN | AG12: 44988 | AH12: =TEXT(AG12,"MMM-YYYY") -> Mar-2023 | AI12: =EOMONTH(B12,0) -> 45688 | AJ12: =IF(V12<=7,1,0) -> 0 | AK12: =IF(N12>20%,1,0) -> 1 | AL12: =MIN(N12,'Scenario Modelling'!$B$2) -> 0.25 | AM12: =L12*(1+'Scenario Modelling'!$B$3) -> 1044.89 | AN12: =O12*(1+'Scenario Modelling'!$B$4) -> 24 | AO12: =AN12*M12*(1-AL12) -> 12444.66 | AP12: =(M12*(1-AL12)-AM12)*AN12 -> -12632.7
A13: ORD-2025-487261 | B13: 45722 | C13: 45747 | D13: Americas | E13: Brazil | F13: Brasília | G13: Non-Profit | H13: Online | I13: J. Njeri | J13: Components | K13: CMP-3693 | L13: 331.57 | M13: 548.4 | N13: 0.094 | O13: 10 | P13: =IF(M13>0,"Valid") -> Valid | Q13: =ABS(M13) -> 548.4 | R13: =IF(N13>30%,"Excess") -> FALSE | S13: =IF(R13="Excess",30%,N13) -> 0.094 | T13: =(C13-B13) -> 25 | U13: =IF(C13<B13,B13+7,C13) -> 45747 | V13: =(U13-B13) -> 25 | W13: =(Q13*O13*(100-S13)) -> 547884.5 | X13: =(Q13*O13) -> 5484 | Y13: =W13-X13 -> 542400.5 | Z13: =Y13/W13 -> 0.98999059 | AA13: Mar-2025 | AB13: ="Q"&ROUNDUP(MONTH(B13)/3,0)&"-"&YEAR(B13) -> Q1-2025 | AC13: =D13&" → "&E13&" → "&F13 -> Americas → Brazil → Brasília | AD13: =IF(OR(J13="Laptops",J13="Phones"),"Devices",IF(OR(J13="Monitors",J13="Printers"),"Peripherals","Support")) -> Support | AE13: =IF(B13<=PERCENTILE($B$2:$B$632,0.33),"Low",IF(B13<=PERCENTILE($B$2:$B$632,0.66),"Medium","High")) -> High | AF13: =UPPER(TRIM(CLEAN(SUBSTITUTE(E13,CHAR(160),"")))) -> BRAZIL | AG13: =_xlfn.MINIFS($B$2:$B$633,$AF$2:$AF$633,AF13) -> 44955 | AH13: =TEXT(AG13,"MMM-YYYY") -> Jan-2023 | AI13: =EOMONTH(B13,0) -> 45747 | AJ13: =IF(V13<=7,1,0) -> 0 | AK13: =IF(N13>20%,1,0) -> 0 | AL13: =MIN(N13,'Scenario Modelling'!$B$2) -> 0.094 | AM13: =L13*(1+'Scenario Modelling'!$B$3) -> 381.3055 | AN13: =O13*(1+'Scenario Modelling'!$B$4) -> 12 | AO13: =AN13*M13*(1-AL13) -> 5962.2048 | AP13: =(M13*(1-AL13)-AM13)*AN13 -> 1386.5388
A14: ORD-2024-890180 | B14: 45311 | C14: 45335 | D14: Europe | E14: France | F14: Marseille | G14: Corporate | H14: Retail | I14: H. Kim | J14: Printers | K14: PRN-8392 | L14: 643.53 | M14: 1439.01 | N14: 0 | O14: 15 | P14: =IF(M14>0,"Valid") -> Valid | Q14: =ABS(M14) -> 1439.01 | R14: =IF(N14>30%,"Excess") -> FALSE | S14: =IF(R14="Excess",30%,N14) -> 0 | T14: =(C14-B14) -> 24 | U14: =IF(C14<B14,B14+7,C14) -> 45335 | V14: =(U14-B14) -> 24 | W14: =(Q14*O14*(100-S14)) -> 2158515 | X14: =(Q14*O14) -> 21585.15 | Y14: =W14-X14 -> 2136929.9 | Z14: =Y14/W14 -> 0.99 | AA14: Jan-2024 | AB14: ="Q"&ROUNDUP(MONTH(B14)/3,0)&"-"&YEAR(B14) -> Q1-2024 | AC14: =D14&" → "&E14&" → "&F14 -> Europe → France → Marseille | AD14: =IF(OR(J14="Laptops",J14="Phones"),"Devices",IF(OR(J14="Monitors",J14="Printers"),"Peripherals","Support")) -> Peripherals | AE14: =IF(B14<=PERCENTILE($B$2:$B$632,0.33),"Low",IF(B14<=PERCENTILE($B$2:$B$632,0.66),"Medium","High")) -> Medium | AF14: =UPPER(TRIM(CLEAN(SUBSTITUTE(E14,CHAR(160),"")))) -> FRANCE | AG14: =_xlfn.MINIFS($B$2:$B$633,$AF$2:$AF$633,AF14) -> 44936 | AH14: =TEXT(AG14,"MMM-YYYY") -> Jan-2023 | AI14: =EOMONTH(B14,0) -> 45322 | AJ14: =IF(V14<=7,1,0) -> 0 | AK14: =IF(N14>20%,1,0) -> 0 | AL14: =MIN(N14,'Scenario Modelling'!$B$2) -> 0 | AM14: =L14*(1+'Scenario Modelling'!$B$3) -> 740.0595 | AN14: =O14*(1+'Scenario Modelling'!$B$4) -> 18 | AO14: =AN14*M14*(1-AL14) -> 25902.18 | AP14: =(M14*(1-AL14)-AM14)*AN14 -> 12581.109
A15: ORD-2025-840976 | B15: 45901 | C15: 45930 | D15: Americas | E15: Brazil | F15: Brasília | G15: Education | H15: Retail | I15: K. Singh | J15: Accessories | K15: ACC-1663 | L15: 780.59 | M15: 631.57 | N15: 0 | O15: 12 | P15: =IF(M15>0,"Valid") -> Valid | Q15: =ABS(M15) -> 631.57 | R15: =IF(N15>30%,"Excess") -> FALSE | S15: =IF(R15="Excess",30%,N15) -> 0 | T15: =(C15-B15) -> 29 | U15: =IF(C15<B15,B15+7,C15) -> 45930 | V15: =(U15-B15) -> 29 | W15: =(Q15*O15*(100-S15)) -> 757884 | X15: =(Q15*O15) -> 7578.84 | Y15: =W15-X15 -> 750305.16 | Z15: =Y15/W15 -> 0.99 | AA15: Sep-2025 | AB15: ="Q"&ROUNDUP(MONTH(B15)/3,0)&"-"&YEAR(B15) -> Q3-2025 | AC15: =D15&" → "&E15&" → "&F15 -> Americas → Brazil → Brasília | AD15: =IF(OR(J15="Laptops",J15="Phones"),"Devices",IF(OR(J15="Monitors",J15="Printers"),"Peripherals","Support")) -> Support | AE15: =IF(B15<=PERCENTILE($B$2:$B$632,0.33),"Low",IF(B15<=PERCENTILE($B$2:$B$632,0.66),"Medium","High")) -> High | AF15: =UPPER(TRIM(CLEAN(SUBSTITUTE(E15,CHAR(160),"")))) -> BRAZIL | AG15: =_xlfn.MINIFS($B$2:$B$633,$AF$2:$AF$633,AF15) -> 44955 | AH15: =TEXT(AG15,"MMM-YYYY") -> Jan-2023 | AI15: =EOMONTH(B15,0) -> 45930 | AJ15: =IF(V15<=7,1,0) -> 0 | AK15: =IF(N15>20%,1,0) -> 0 | AL15: =MIN(N15,'Scenario Modelling'!$B$2) -> 0 | AM15: =L15*(1+'Scenario Modelling'!$B$3) -> 897.6785 | AN15: =O15*(1+'Scenario Modelling'!$B$4) -> 14.4 | AO15: =AN15*M15*(1-AL15) -> 9094.608 | AP15: =(M15*(1-AL15)-AM15)*AN15 -> -3831.9624
A16: ORD-2023-937291 | B16: 45039 | C16: 45038 | D16: Africa | E16: Kenya | F16: Nairobi | G16: Small Business | H16: Direct | I16: E. Garcia | J16: Laptops | K16: LAP-1698 | L16: 756.51 | M16: 850.8 | N16: 0.074 | O16: 9 | P16: =IF(M16>0,"Valid") -> Valid | Q16: =ABS(M16) -> 850.8 | R16: =IF(N16>30%,"Excess") -> FALSE | S16: =IF(R16="Excess",30%,N16) -> 0.074 | T16: =(C16-B16) -> -1 | U16: =IF(C16<B16,B16+7,C16) -> 45046 | V16: =(U16-B16) -> 7 | W16: =(Q16*O16*(100-S16)) -> 765153.37 | X16: =(Q16*O16) -> 7657.2 | Y16: =W16-X16 -> 757496.17 | Z16: =Y16/W16 -> 0.98999259 | AA16: Apr-2023 | AB16: ="Q"&ROUNDUP(MONTH(B16)/3,0)&"-"&YEAR(B16) -> Q2-2023 | AC16: =D16&" → "&E16&" → "&F16 -> Africa → Kenya → Nairobi | AD16: =IF(OR(J16="Laptops",J16="Phones"),"Devices",IF(OR(J16="Monitors",J16="Printers"),"Peripherals","Support")) -> Devices | AE16: =IF(B16<=PERCENTILE($B$2:$B$632,0.33),"Low",IF(B16<=PERCENTILE($B$2:$B$632,0.66),"Medium","High")) -> Low | AF16: =UPPER(TRIM(CLEAN(SUBSTITUTE(E16,CHAR(160),"")))) -> KENYA | AG16: 44946 | AH16: =TEXT(AG16,"MMM-YYYY") -> Jan-2023 | AI16: =EOMONTH(B16,0) -> 45046 | AJ16: =IF(V16<=7,1,0) -> 1 | AK16: =IF(N16>20%,1,0) -> 0 | AL16: =MIN(N16,'Scenario Modelling'!$B$2) -> 0.074 | AM16: =L16*(1+'Scenario Modelling'!$B$3) -> 869.9865 | AN16: =O16*(1+'Scenario Modelling'!$B$4) -> 10.8 | AO16: =AN16*M16*(1-AL16) -> 8508.6806 | AP16: =(M16*(1-AL16)-AM16)*AN16 -> -887.17356
A17: ORD-2024-206081 | B17: 45636 | C17: 45665 | D17: Europe | E17: France | F17: Marseille | G17: Small Business | H17: Retail | I17: K. Singh | J17: Printers | K17: PRN-6791 | L17: 891.08 | M17: 1040.1 | N17: 0.109 | O17: 28 | P17: =IF(M17>0,"Valid") -> Valid | Q17: =ABS(M17) -> 1040.1 | R17: =IF(N17>30%,"Excess") -> FALSE | S17: =IF(R17="Excess",30%,N17) -> 0.109 | T17: =(C17-B17) -> 29 | U17: =IF(C17<B17,B17+7,C17) -> 45665 | V17: =(U17-B17) -> 29 | W17: =(Q17*O17*(100-S17)) -> 2909105.6 | X17: =(Q17*O17) -> 29122.8 | Y17: =W17-X17 -> 2879982.8 | Z17: =Y17/W17 -> 0.98998909 | AA17: Dec-2024 | AB17: ="Q"&ROUNDUP(MONTH(B17)/3,0)&"-"&YEAR(B17) -> Q4-2024 | AC17: =D17&" → "&E17&" → "&F17 -> Europe → France → Marseille | AD17: =IF(OR(J17="Laptops",J17="Phones"),"Devices",IF(OR(J17="Monitors",J17="Printers"),"Peripherals","Support")) -> Peripherals | AE17: =IF(B17<=PERCENTILE($B$2:$B$632,0.33),"Low",IF(B17<=PERCENTILE($B$2:$B$632,0.66),"Medium","High")) -> High | AF17: =UPPER(TRIM(CLEAN(SUBSTITUTE(E17,CHAR(160),"")))) -> FRANCE | AG17: 44936 | AH17: =TEXT(AG17,"MMM-YYYY") -> Jan-2023 | AI17: =EOMONTH(B17,0) -> 45657 | AJ17: =IF(V17<=7,1,0) -> 0 | AK17: =IF(N17>20%,1,0) -> 0 | AL17: =MIN(N17,'Scenario Modelling'!$B$2) -> 0.109 | AM17: =L17*(1+'Scenario Modelling'!$B$3) -> 1024.742 | AN17: =O17*(1+'Scenario Modelling'!$B$4) -> 33.6 | AO17: =AN17*M17*(1-AL17) -> 31138.098 | AP17: =(M17*(1-AL17)-AM17)*AN17 -> -3293.2334
A18: ORD-2025-233883 | B18: 45908 | C18: 45916 | D18: Asia | E18: Japan | F18: Osaka | G18: Corporate | H18: Distributor | I18: C. Otieno | J18: Phones | K18: PHN-1197 | L18: 1225.57 | M18: 2705.57 | N18: 0.183 | O18: 16 | P18: =IF(M18>0,"Valid") -> Valid | Q18: =ABS(M18) -> 2705.57 | R18: =IF(N18>30%,"Excess") -> FALSE | S18: =IF(R18="Excess",30%,N18) -> 0.183 | T18: =(C18-B18) -> 8 | U18: =IF(C18<B18,B18+7,C18) -> 45916 | V18: =(U18-B18) -> 8 | W18: =(Q18*O18*(100-S18)) -> 4320990.1 | X18: =(Q18*O18) -> 43289.12 | Y18: =W18-X18 -> 4277701 | Z18: =Y18/W18 -> 0.98998167 | AA18: Sep-2025 | AB18: ="Q"&ROUNDUP(MONTH(B18)/3,0)&"-"&YEAR(B18) -> Q3-2025 | AC18: =D18&" → "&E18&" → "&F18 -> Asia → Japan → Osaka | AD18: =IF(OR(J18="Laptops",J18="Phones"),"Devices",IF(OR(J18="Monitors",J18="Printers"),"Peripherals","Support")) -> Devices | AE18: =IF(B18<=PERCENTILE($B$2:$B$632,0.33),"Low",IF(B18<=PERCENTILE($B$2:$B$632,0.66),"Medium","High")) -> High | AF18: =UPPER(TRIM(CLEAN(SUBSTITUTE(E18,CHAR(160),"")))) -> JAPAN | AG18: 44988 | AH18: =TEXT(AG18,"MMM-YYYY") -> Mar-2023 | AI18: =EOMONTH(B18,0) -> 45930 | AJ18: =IF(V18<=7,1,0) -> 0 | AK18: =IF(N18>20%,1,0) -> 0 | AL18: =MIN(N18,'Scenario Modelling'!$B$2) -> 0.183 | AM18: =L18*(1+'Scenario Modelling'!$B$3) -> 1409.4055 | AN18: =O18*(1+'Scenario Modelling'!$B$4) -> 19.2 | AO18: =AN18*M18*(1-AL18) -> 42440.653 | AP18: =(M18*(1-AL18)-AM18)*AN18 -> 15380.068
A19: ORD-2025-843974 | B19: 45858 | C19: 45874 | D19: Americas | E19: Brazil | F19: Brasília | G19: Enterprise | H19: Marketplace | I19: G. Dubois | J19: Accessories | K19: ACC-8098 | L19: 1068.17 | M19: 2375.37 | N19: 0.109 | O19: 18 | P19: =IF(M19>0,"Valid") -> Valid | Q19: =ABS(M19) -> 2375.37 | R19: =IF(N19>30%,"Excess") -> FALSE | S19: =IF(R19="Excess",30%,N19) -> 0.109 | T19: =(C19-B19) -> 16 | U19: =IF(C19<B19,B19+7,C19) -> 45874 | V19: =(U19-B19) -> 16 | W19: =(Q19*O19*(100-S19)) -> 4271005.5 | X19: =(Q19*O19) -> 42756.66 | Y19: =W19-X19 -> 4228248.9 | Z19: =Y19/W19 -> 0.98998909 | AA19: Jul-2025 | AB19: ="Q"&ROUNDUP(MONTH(B19)/3,0)&"-"&YEAR(B19) -> Q3-2025 | AC19: =D19&" → "&E19&" → "&F19 -> Americas → Brazil → Brasília | AD19: =IF(OR(J19="Laptops",J19="Phones"),"Devices",IF(OR(J19="Monitors",J19="Printers"),"Peripherals","Support")) -> Support | AE19: =IF(B19<=PERCENTILE($B$2:$B$632,0.33),"Low",IF(B19<=PERCENTILE($B$2:$B$632,0.66),"Medium","High")) -> High | AF19: =UPPER(TRIM(CLEAN(SUBSTITUTE(E19,CHAR(160),"")))) -> BRAZIL | AG19: =_xlfn.MINIFS($B$2:$B$633,$AF$2:$AF$633,AF19) -> 44955 | AH19: =TEXT(AG19,"MMM-YYYY") -> Jan-2023 | AI19: =EOMONTH(B19,0) -> 45869 | AJ19: =IF(V19<=7,1,0) -> 0 | AK19: =IF(N19>20%,1,0) -> 0 | AL19: =MIN(N19,'Scenario Modelling'!$B$2) -> 0.109 | AM19: =L19*(1+'Scenario Modelling'!$B$3) -> 1228.3955 | AN19: =O19*(1+'Scenario Modelling'!$B$4) -> 21.6 | AO19: =AN19*M19*(1-AL19) -> 45715.421 | AP19: =(M19*(1-AL19)-AM19)*AN19 -> 19182.078
A20: ORD-2025-745263 | B20: 45798 | C20: 45796 | D20: Europe | E20: United Kingdom | F20: Birmingham | G20: Enterprise | H20: Online | I20: M. Rossi | J20: Laptops | K20: LAP-3385 | L20: 1015.16 | M20: 2148.14 | N20: 0.038 | O20: 19 | P20: =IF(M20>0,"Valid") -> Valid | Q20: =ABS(M20) -> 2148.14 | R20: =IF(N20>30%,"Excess") -> FALSE | S20: =IF(R20="Excess",30%,N20) -> 0.038 | T20: =(C20-B20) -> -2 | U20: =IF(C20<B20,B20+7,C20) -> 45805 | V20: =(U20-B20) -> 7 | W20: =(Q20*O20*(100-S20)) -> 4079915 | X20: =(Q20*O20) -> 40814.66 | Y20: =W20-X20 -> 4039100.4 | Z20: =Y20/W20 -> 0.9899962 | AA20: May-2025 | AB20: ="Q"&ROUNDUP(MONTH(B20)/3,0)&"-"&YEAR(B20) -> Q2-2025 | AC20: =D20&" → "&E20&" → "&F20 -> Europe → United Kingdom → Birmingham | AD20: =IF(OR(J20="Laptops",J20="Phones"),"Devices",IF(OR(J20="Monitors",J20="Printers"),"Peripherals","Support")) -> Devices | AE20: =IF(B20<=PERCENTILE($B$2:$B$632,0.33),"Low",IF(B20<=PERCENTILE($B$2:$B$632,0.66),"Medium","High")) -> High | AF20: =UPPER(TRIM(CLEAN(SUBSTITUTE(E20,CHAR(160),"")))) -> UNITED KINGDOM | AG20: 44945 | AH20: =TEXT(AG20,"MMM-YYYY") -> Jan-2023 | AI20: =EOMONTH(B20,0) -> 45808 | AJ20: =IF(V20<=7,1,0) -> 1 | AK20: =IF(N20>20%,1,0) -> 0 | AL20: =MIN(N20,'Scenario Modelling'!$B$2) -> 0.038 | AM20: =L20*(1+'Scenario Modelling'!$B$3) -> 1167.434 | AN20: =O20*(1+'Scenario Modelling'!$B$4) -> 22.8 | AO20: =AN20*M20*(1-AL20) -> 47116.444 | AP20: =(M20*(1-AL20)-AM20)*AN20 -> 20498.948
A21: ORD-2024-798002 | B21: 45498 | C21: 45497 | D21: Africa | E21: Kenya | F21: Mombasa | G21: Non-Profit | H21: Direct | I21: J. Njeri | J21: Laptops | K21: LAP-9815 | L21: 1494.4 | M21: 3661.07 | N21: 0.072 | O21: 7 | P21: =IF(M21>0,"Valid") -> Valid | Q21: =ABS(M21) -> 3661.07 | R21: =IF(N21>30%,"Excess") -> FALSE | S21: =IF(R21="Excess",30%,N21) -> 0.072 | T21: =(C21-B21) -> -1 | U21: =IF(C21<B21,B21+7,C21) -> 45505 | V21: =(U21-B21) -> 7 | W21: =(Q21*O21*(100-S21)) -> 2560903.8 | X21: =(Q21*O21) -> 25627.49 | Y21: =W21-X21 -> 2535276.3 | Z21: =Y21/W21 -> 0.98999279 | AA21: Jul-2024 | AB21: ="Q"&ROUNDUP(MONTH(B21)/3,0)&"-"&YEAR(B21) -> Q3-2024 | AC21: =D21&" → "&E21&" → "&F21 -> Africa → Kenya → Mombasa | AD21: =IF(OR(J21="Laptops",J21="Phones"),"Devices",IF(OR(J21="Monitors",J21="Printers"),"Peripherals","Support")) -> Devices | AE21: =IF(B21<=PERCENTILE($B$2:$B$632,0.33),"Low",IF(B21<=PERCENTILE($B$2:$B$632,0.66),"Medium","High")) -> Medium | AF21: =UPPER(TRIM(CLEAN(SUBSTITUTE(E21,CHAR(160),"")))) -> KENYA | AG21: 44946 | AH21: =TEXT(AG21,"MMM-YYYY") -> Jan-2023 | AI21: =EOMONTH(B21,0) -> 45504 | AJ21: =IF(V21<=7,1,0) -> 1 | AK21: =IF(N21>20%,1,0) -> 0 | AL21: =MIN(N21,'Scenario Modelling'!$B$2) -> 0.072 | AM21: =L21*(1+'Scenario Modelling'!$B$3) -> 1718.56 | AN21: =O21*(1+'Scenario Modelling'!$B$4) -> 8.4 | AO21: =AN21*M21*(1-AL21) -> 28538.773 | AP21: =(M21*(1-AL21)-AM21)*AN21 -> 14102.869
A22: ORD-2023-867836 | B22: 45057 | C22: 45074 | D22: Asia | E22: China | F22: Shenzhen | G22: Enterprise | H22: Marketplace | I22: E. Garcia | J22: Networking | K22: NET-3255 | L22: 1331.19 | M22: 2903.09 | N22: 0.143 | O22: 8 | P22: =IF(M22>0,"Valid") -> Valid | Q22: =ABS(M22) -> 2903.09 | R22: =IF(N22>30%,"Excess") -> FALSE | S22: =IF(R22="Excess",30%,N22) -> 0.143 | T22: =(C22-B22) -> 17 | U22: =IF(C22<B22,B22+7,C22) -> 45074 | V22: =(U22-B22) -> 17 | W22: =(Q22*O22*(100-S22)) -> 2319150.9 | X22: =(Q22*O22) -> 23224.72 | Y22: =W22-X22 -> 2295926.1 | Z22: =Y22/W22 -> 0.98998568 | AA22: May-2023 | AB22: ="Q"&ROUNDUP(MONTH(B22)/3,0)&"-"&YEAR(B22) -> Q2-2023 | AC22: =D22&" → "&E22&" → "&F22 -> Asia → China → Shenzhen | AD22: =IF(OR(J22="Laptops",J22="Phones"),"Devices",IF(OR(J22="Monitors",J22="Printers"),"Peripherals","Support")) -> Support | AE22: =IF(B22<=PERCENTILE($B$2:$B$632,0.33),"Low",IF(B22<=PERCENTILE($B$2:$B$632,0.66),"Medium","High")) -> Low | AF22: =UPPER(TRIM(CLEAN(SUBSTITUTE(E22,CHAR(160),"")))) -> CHINA | AG22: =_xlfn.MINIFS($B$2:$B$633,$AF$2:$AF$633,AF22) -> 44938 | AH22: =TEXT(AG22,"MMM-YYYY") -> Jan-2023 | AI22: =EOMONTH(B22,0) -> 45077 | AJ22: =IF(V22<=7,1,0) -> 0 | AK22: =IF(N22>20%,1,0) -> 0 | AL22: =MIN(N22,'Scenario Modelling'!$B$2) -> 0.143 | AM22: =L22*(1+'Scenario Modelling'!$B$3) -> 1530.8685 | AN22: =O22*(1+'Scenario Modelling'!$B$4) -> 9.6 | AO22: =AN22*M22*(1-AL22) -> 23884.302 | AP22: =(M22*(1-AL22)-AM22)*AN22 -> 9187.9644
A23: ORD-2025-580047 | B23: 45822 | C23: 45837 | D23: Africa | E23: Nigeria | F23: Port Harcourt | G23: Consumer | H23: Marketplace | I23: M. Rossi | J23: Accessories | K23: ACC-3961 | L23: 730.99 | M23: 1242.84 | N23: 0.12 | O23: 10 | P23: =IF(M23>0,"Valid") -> Valid | Q23: =ABS(M23) -> 1242.84 | R23: =IF(N23>30%,"Excess") -> FALSE | S23: =IF(R23="Excess",30%,N23) -> 0.12 | T23: =(C23-B23) -> 15 | U23: =IF(C23<B23,B23+7,C23) -> 45837 | V23: =(U23-B23) -> 15 | W23: =(Q23*O23*(100-S23)) -> 1241348.6 | X23: =(Q23*O23) -> 12428.4 | Y23: =W23-X23 -> 1228920.2 | Z23: =Y23/W23 -> 0.98998799 | AA23: Jun-2025 | AB23: ="Q"&ROUNDUP(MONTH(B23)/3,0)&"-"&YEAR(B23) -> Q2-2025 | AC23: =D23&" → "&E23&" → "&F23 -> Africa → Nigeria → Port Harcourt | AD23: =IF(OR(J23="Laptops",J23="Phones"),"Devices",IF(OR(J23="Monitors",J23="Printers"),"Peripherals","Support")) -> Support | AE23: =IF(B23<=PERCENTILE($B$2:$B$632,0.33),"Low",IF(B23<=PERCENTILE($B$2:$B$632,0.66),"Medium","High")) -> High | AF23: =UPPER(TRIM(CLEAN(SUBSTITUTE(E23,CHAR(160),"")))) -> NIGERIA | AG23: =_xlfn.MINIFS($B$2:$B$633,$AF$2:$AF$633,AF23) -> 44941 | AH23: =TEXT(AG23,"MMM-YYYY") -> Jan-2023 | AI23: =EOMONTH(B23,0) -> 45838 | AJ23: =IF(V23<=7,1,0) -> 0 | AK23: =IF(N23>20%,1,0) -> 0 | AL23: =MIN(N23,'Scenario Modelling'!$B$2) -> 0.12 | AM23: =L23*(1+'Scenario Modelling'!$B$3) -> 840.6385 | AN23: =O23*(1+'Scenario Modelling'!$B$4) -> 12 | AO23: =AN23*M23*(1-AL23) -> 13124.39 | AP23: =(M23*(1-AL23)-AM23)*AN23 -> 3036.7284
A24: ORD-2024-500109 | B24: 45430 | C24: 45435 | D24: Americas | E24: USA | F24: Chicago | G24: Enterprise | H24: Retail | I24: H. Kim | J24: Laptops | K24: LAP-4987 | L24: 1274.59 | M24: 2553.69 | N24: 0.01 | O24: 8 | P24: =IF(M24>0,"Valid") -> Valid | Q24: =ABS(M24) -> 2553.69 | R24: =IF(N24>30%,"Excess") -> FALSE | S24: =IF(R24="Excess",30%,N24) -> 0.01 | T24: =(C24-B24) -> 5 | U24: =IF(C24<B24,B24+7,C24) -> 45435 | V24: =(U24-B24) -> 5 | W24: =(Q24*O24*(100-S24)) -> 2042747.7 | X24: =(Q24*O24) -> 20429.52 | Y24: =W24-X24 -> 2022318.2 | Z24: =Y24/W24 -> 0.989999 | AA24: May-2024 | AB24: ="Q"&ROUNDUP(MONTH(B24)/3,0)&"-"&YEAR(B24) -> Q2-2024 | AC24: =D24&" → "&E24&" → "&F24 -> Americas → USA → Chicago | AD24: =IF(OR(J24="Laptops",J24="Phones"),"Devices",IF(OR(J24="Monitors",J24="Printers"),"Peripherals","Support")) -> Devices | AE24: =IF(B24<=PERCENTILE($B$2:$B$632,0.33),"Low",IF(B24<=PERCENTILE($B$2:$B$632,0.66),"Medium","High")) -> Medium | AF24: =UPPER(TRIM(CLEAN(SUBSTITUTE(E24,CHAR(160),"")))) -> USA | AG24: 44939 | AH24: =TEXT(AG24,"MMM-YYYY") -> Jan-2023 | AI24: =EOMONTH(B24,0) -> 45443 | AJ24: =IF(V24<=7,1,0) -> 1 | AK24: =IF(N24>20%,1,0) -> 0 | AL24: =MIN(N24,'Scenario Modelling'!$B$2) -> 0.01 | AM24: =L24*(1+'Scenario Modelling'!$B$3) -> 1465.7785 | AN24: =O24*(1+'Scenario Modelling'!$B$4) -> 9.6 | AO24: =AN24*M24*(1-AL24) -> 24270.27 | AP24: =(M24*(1-AL24)-AM24)*AN24 -> 10198.796
A25: ORD-2023-271836 | B25: 44964 | C25: 44969 | D25: Americas | E25: Brazil | F25: São Paulo | G25: Education | H25: Online | I25: N. Brown | J25: Components | K25: CMP-2693 | L25: 948.55 | M25: 2089.16 | N25: 0.007 | O25: 12 | P25: =IF(M25>0,"Valid") -> Valid | Q25: =ABS(M25) -> 2089.16 | R25: =IF(N25>30%,"Excess") -> FALSE | S25: =IF(R25="Excess",30%,N25) -> 0.007 | T25: =(C25-B25) -> 5 | U25: =IF(C25<B25,B25+7,C25) -> 44969 | V25: =(U25-B25) -> 5 | W25: =(Q25*O25*(100-S25)) -> 2506816.5 | X25: =(Q25*O25) -> 25069.92 | Y25: =W25-X25 -> 2481746.6 | Z25: =Y25/W25 -> 0.9899993 | AA25: Feb-2023 | AB25: ="Q"&ROUNDUP(MONTH(B25)/3,0)&"-"&YEAR(B25) -> Q1-2023 | AC25: =D25&" → "&E25&" → "&F25 -> Americas → Brazil → São Paulo | AD25: =IF(OR(J25="Laptops",J25="Phones"),"Devices",IF(OR(J25="Monitors",J25="Printers"),"Peripherals","Support")) -> Support | AE25: =IF(B25<=PERCENTILE($B$2:$B$632,0.33),"Low",IF(B25<=PERCENTILE($B$2:$B$632,0.66),"Medium","High")) -> Low | AF25: =UPPER(TRIM(CLEAN(SUBSTITUTE(E25,CHAR(160),"")))) -> BRAZIL | AG25: =_xlfn.MINIFS($B$2:$B$633,$AF$2:$AF$633,AF25) -> 44955 | AH25: =TEXT(AG25,"MMM-YYYY") -> Jan-2023 | AI25: =EOMONTH(B25,0) -> 44985 | AJ25: =IF(V25<=7,1,0) -> 1 | AK25: =IF(N25>20%,1,0) -> 0 | AL25: =MIN(N25,'Scenario Modelling'!$B$2) -> 0.007 | AM25: =L25*(1+'Scenario Modelling'!$B$3) -> 1090.8325 | AN25: =O25*(1+'Scenario Modelling'!$B$4) -> 14.4 | AO25: =AN25*M25*(1-AL25) -> 29873.317 | AP25: =(M25*(1-AL25)-AM25)*AN25 -> 14165.329
A26: ORD-2024-215294 | B26: 45473 | C26: 45487 | D26: Americas | E26: Brazil | F26: Brasília | G26: Education | H26: Retail | I26: C. Otieno | J26: Accessories | K26: ACC-8683 | L26: 1491.85 | M26: 2583.02 | N26: 0.168 | O26: 4 | P26: =IF(M26>0,"Valid") -> Valid | Q26: =ABS(M26) -> 2583.02 | R26: =IF(N26>30%,"Excess") -> FALSE | S26: =IF(R26="Excess",30%,N26) -> 0.168 | T26: =(C26-B26) -> 14 | U26: =IF(C26<B26,B26+7,C26) -> 45487 | V26: =(U26-B26) -> 14 | W26: =(Q26*O26*(100-S26)) -> 1031472.2 | X26: =(Q26*O26) -> 10332.08 | Y26: =W26-X26 -> 1021140.1 | Z26: =Y26/W26 -> 0.98998317 | AA26: Jun-2024 | AB26: ="Q"&ROUNDUP(MONTH(B26)/3,0)&"-"&YEAR(B26) -> Q2-2024 | AC26: =D26&" → "&E26&" → "&F26 -> Americas → Brazil → Brasília | AD26: =IF(OR(J26="Laptops",J26="Phones"),"Devices",IF(OR(J26="Monitors",J26="Printers"),"Peripherals","Support")) -> Support | AE26: =IF(B26<=PERCENTILE($B$2:$B$632,0.33),"Low",IF(B26<=PERCENTILE($B$2:$B$632,0.66),"Medium","High")) -> Medium | AF26: =UPPER(TRIM(CLEAN(SUBSTITUTE(E26,CHAR(160),"")))) -> BRAZIL | AG26: =_xlfn.MINIFS($B$2:$B$633,$AF$2:$AF$633,AF26) -> 44955 | AH26: =TEXT(AG26,"MMM-YYYY") -> Jan-2023 | AI26: =EOMONTH(B26,0) -> 45473 | AJ26: =IF(V26<=7,1,0) -> 0 | AK26: =IF(N26>20%,1,0) -> 0 | AL26: =MIN(N26,'Scenario Modelling'!$B$2) -> 0.168 | AM26: =L26*(1+'Scenario Modelling'!$B$3) -> 1715.6275 | AN26: =O26*(1+'Scenario Modelling'!$B$4) -> 4.8 | AO26: =AN26*M26*(1-AL26) -> 10315.549 | AP26: =(M26*(1-AL26)-AM26)*AN26 -> 2080.5367
A27: ORD-2024-788105 | B27: 45626 | C27: 45656 | D27: Europe | E27: France | F27: Marseille | G27: Consumer | H27: Marketplace | I27: F. Müller | J27: Printers | K27: PRN-4170 | L27: 117.64 | M27: 175.67 | N27: 0 | O27: 10 | P27: =IF(M27>0,"Valid") -> Valid | Q27: =ABS(M27) -> 175.67 | R27: =IF(N27>30%,"Excess") -> FALSE | S27: =IF(R27="Excess",30%,N27) -> 0 | T27: =(C27-B27) -> 30 | U27: =IF(C27<B27,B27+7,C27) -> 45656 | V27: =(U27-B27) -> 30 | W27: =(Q27*O27*(100-S27)) -> 175670 | X27: =(Q27*O27) -> 1756.7 | Y27: =W27-X27 -> 173913.3 | Z27: =Y27/W27 -> 0.99 | AA27: Nov-2024 | AB27: ="Q"&ROUNDUP(MONTH(B27)/3,0)&"-"&YEAR(B27) -> Q4-2024 | AC27: =D27&" → "&E27&" → "&F27 -> Europe → France → Marseille | AD27: =IF(OR(J27="Laptops",J27="Phones"),"Devices",IF(OR(J27="Monitors",J27="Printers"),"Peripherals","Support")) -> Peripherals | AE27: =IF(B27<=PERCENTILE($B$2:$B$632,0.33),"Low",IF(B27<=PERCENTILE($B$2:$B$632,0.66),"Medium","High")) -> High | AF27: =UPPER(TRIM(CLEAN(SUBSTITUTE(E27,CHAR(160),"")))) -> FRANCE | AG27: 44936 | AH27: =TEXT(AG27,"MMM-YYYY") -> Jan-2023 | AI27: =EOMONTH(B27,0) -> 45626 | AJ27: =IF(V27<=7,1,0) -> 0 | AK27: =IF(N27>20%,1,0) -> 0 | AL27: =MIN(N27,'Scenario Modelling'!$B$2) -> 0 | AM27: =L27*(1+'Scenario Modelling'!$B$3) -> 135.286 | AN27: =O27*(1+'Scenario Modelling'!$B$4) -> 12 | AO27: =AN27*M27*(1-AL27) -> 2108.04 | AP27: =(M27*(1-AL27)-AM27)*AN27 -> 484.608
A28: ORD-2024-855073 | B28: 45492 | C28: 45492 | D28: Africa | E28: Kenya | F28: Kisumu | G28: Small Business | H28: Retail | I28: A. Patel | J28: Phones | K28: PHN-6854 | L28: 857.24 | M28: 758.23 | N28: 0.125 | O28: 6 | P28: =IF(M28>0,"Valid") -> Valid | Q28: =ABS(M28) -> 758.23 | R28: =IF(N28>30%,"Excess") -> FALSE | S28: =IF(R28="Excess",30%,N28) -> 0.125 | T28: =(C28-B28) -> 0 | U28: =IF(C28<B28,B28+7,C28) -> 45492 | V28: =(U28-B28) -> 0 | W28: =(Q28*O28*(100-S28)) -> 454369.33 | X28: =(Q28*O28) -> 4549.38 | Y28: =W28-X28 -> 449819.95 | Z28: =Y28/W28 -> 0.98998748 | AA28: Jul-2024 | AB28: ="Q"&ROUNDUP(MONTH(B28)/3,0)&"-"&YEAR(B28) -> Q3-2024 | AC28: =D28&" → "&E28&" → "&F28 -> Africa → Kenya → Kisumu | AD28: =IF(OR(J28="Laptops",J28="Phones"),"Devices",IF(OR(J28="Monitors",J28="Printers"),"Peripherals","Support")) -> Devices | AE28: =IF(B28<=PERCENTILE($B$2:$B$632,0.33),"Low",IF(B28<=PERCENTILE($B$2:$B$632,0.66),"Medium","High")) -> Medium | AF28: =UPPER(TRIM(CLEAN(SUBSTITUTE(E28,CHAR(160),"")))) -> KENYA | AG28: 44946 | AH28: =TEXT(AG28,"MMM-YYYY") -> Jan-2023 | AI28: =EOMONTH(B28,0) -> 45504 | AJ28: =IF(V28<=7,1,0) -> 1 | AK28: =IF(N28>20%,1,0) -> 0 | AL28: =MIN(N28,'Scenario Modelling'!$B$2) -> 0.125 | AM28: =L28*(1+'Scenario Modelling'!$B$3) -> 985.826 | AN28: =O28*(1+'Scenario Modelling'!$B$4) -> 7.2 | AO28: =AN28*M28*(1-AL28) -> 4776.849 | AP28: =(M28*(1-AL28)-AM28)*AN28 -> -2321.0982
A29: ORD-2023-897079 | B29: 45030 | C29: 45060 | D29: Africa | E29: Kenya | F29: Nakuru | G29: Consumer | H29: Marketplace | I29: M. Rossi | J29: Phones | K29: PHN-1784 | L29: 209.25 | M29: 434.8 | N29: 0 | O29: 9 | P29: =IF(M29>0,"Valid") -> Valid | Q29: =ABS(M29) -> 434.8 | R29: =IF(N29>30%,"Excess") -> FALSE | S29: =IF(R29="Excess",30%,N29) -> 0 | T29: =(C29-B29) -> 30 | U29: =IF(C29<B29,B29+7,C29) -> 45060 | V29: =(U29-B29) -> 30 | W29: =(Q29*O29*(100-S29)) -> 391320 | X29: =(Q29*O29) -> 3913.2 | Y29: =W29-X29 -> 387406.8 | Z29: =Y29/W29 -> 0.99 | AA29: Apr-2023 | AB29: ="Q"&ROUNDUP(MONTH(B29)/3,0)&"-"&YEAR(B29) -> Q2-2023 | AC29: =D29&" → "&E29&" → "&F29 -> Africa → Kenya → Nakuru | AD29: =IF(OR(J29="Laptops",J29="Phones"),"Devices",IF(OR(J29="Monitors",J29="Printers"),"Peripherals","Support")) -> Devices | AE29: =IF(B29<=PERCENTILE($B$2:$B$632,0.33),"Low",IF(B29<=PERCENTILE($B$2:$B$632,0.66),"Medium","High")) -> Low | AF29: =UPPER(TRIM(CLEAN(SUBSTITUTE(E29,CHAR(160),"")))) -> KENYA | AG29: 44946 | AH29: =TEXT(AG29,"MMM-YYYY") -> Jan-2023 | AI29: =EOMONTH(B29,0) -> 45046 | AJ29: =IF(V29<=7,1,0) -> 0 | AK29: =IF(N29>20%,1,0) -> 0 | AL29: =MIN(N29,'Scenario Modelling'!$B$2) -> 0 | AM29: =L29*(1+'Scenario Modelling'!$B$3) -> 240.6375 | AN29: =O29*(1+'Scenario Modelling'!$B$4) -> 10.8 | AO29: =AN29*M29*(1-AL29) -> 4695.84 | AP29: =(M29*(1-AL29)-AM29)*AN29 -> 2096.955
A30: ORD-2025-548982 | B30: 45754 | C30: 45758 | D30: Europe | E30: France | F30: Lyon | G30: Education | H30: Retail | I30: E. Garcia | J30: Networking | K30: NET-9716 | L30: 754.77 | M30: 1666.18 | N30: 0.139 | O30: 14 | P30: =IF(M30>0,"Valid") -> Valid | Q30: =ABS(M30) -> 1666.18 | R30: =IF(N30>30%,"Excess") -> FALSE | S30: =IF(R30="Excess",30%,N30) -> 0.139 | T30: =(C30-B30) -> 4 | U30: =IF(C30<B30,B30+7,C30) -> 45758 | V30: =(U30-B30) -> 4 | W30: =(Q30*O30*(100-S30)) -> 2329409.6 | X30: =(Q30*O30) -> 23326.52 | Y30: =W30-X30 -> 2306083.1 | Z30: =Y30/W30 -> 0.98998608 | AA30: Apr-2025 | AB30: ="Q"&ROUNDUP(MONTH(B30)/3,0)&"-"&YEAR(B30) -> Q2-2025 | AC30: =D30&" → "&E30&" → "&F30 -> Europe → France → Lyon | AD30: =IF(OR(J30="Laptops",J30="Phones"),"Devices",IF(OR(J30="Monitors",J30="Printers"),"Peripherals","Support")) -> Support | AE30: =IF(B30<=PERCENTILE($B$2:$B$632,0.33),"Low",IF(B30<=PERCENTILE($B$2:$B$632,0.66),"Medium","High")) -> High | AF30: =UPPER(TRIM(CLEAN(SUBSTITUTE(E30,CHAR(160),"")))) -> FRANCE | AG30: 44936 | AH30: =TEXT(AG30,"MMM-YYYY") -> Jan-2023 | AI30: =EOMONTH(B30,0) -> 45777 | AJ30: =IF(V30<=7,1,0) -> 1 | AK30: =IF(N30>20%,1,0) -> 0 | AL30: =MIN(N30,'Scenario Modelling'!$B$2) -> 0.139 | AM30: =L30*(1+'Scenario Modelling'!$B$3) -> 867.9855 | AN30: =O30*(1+'Scenario Modelling'!$B$4) -> 16.8 | AO30: =AN30*M30*(1-AL30) -> 24100.96 | AP30: =(M30*(1-AL30)-AM30)*AN30 -> 9518.8041
A31: ORD-2024-170313 | B31: 45653 | C31: 45672 | D31: Asia | E31: India | F31: Delhi | G31: Non-Profit | H31: Distributor | I31: G. Dubois | J31: Components | K31: CMP-6919 | L31: 495.59 | M31: 631.78 | N31: 0.087 | O31: 17 | P31: =IF(M31>0,"Valid") -> Valid | Q31: =ABS(M31) -> 631.78 | R31: =IF(N31>30%,"Excess") -> FALSE | S31: =IF(R31="Excess",30%,N31) -> 0.087 | T31: =(C31-B31) -> 19 | U31: =IF(C31<B31,B31+7,C31) -> 45672 | V31: =(U31-B31) -> 19 | W31: =(Q31*O31*(100-S31)) -> 1073091.6 | X31: =(Q31*O31) -> 10740.26 | Y31: =W31-X31 -> 1062351.3 | Z31: =Y31/W31 -> 0.98999129 | AA31: Dec-2024 | AB31: ="Q"&ROUNDUP(MONTH(B31)/3,0)&"-"&YEAR(B31) -> Q4-2024 | AC31: =D31&" → "&E31&" → "&F31 -> Asia → India → Delhi | AD31: =IF(OR(J31="Laptops",J31="Phones"),"Devices",IF(OR(J31="Monitors",J31="Printers"),"Peripherals","Support")) -> Support | AE31: =IF(B31<=PERCENTILE($B$2:$B$632,0.33),"Low",IF(B31<=PERCENTILE($B$2:$B$632,0.66),"Medium","High")) -> High | AF31: =UPPER(TRIM(CLEAN(SUBSTITUTE(E31,CHAR(160),"")))) -> INDIA | AG31: 44955 | AH31: =TEXT(AG31,"MMM-YYYY") -> Jan-2023 | AI31: =EOMONTH(B31,0) -> 45657 | AJ31: =IF(V31<=7,1,0) -> 0 | AK31: =IF(N31>20%,1,0) -> 0 | AL31: =MIN(N31,'Scenario Modelling'!$B$2) -> 0.087 | AM31: =L31*(1+'Scenario Modelling'!$B$3) -> 569.9285 | AN31: =O31*(1+'Scenario Modelling'!$B$4) -> 20.4 | AO31: =AN31*M31*(1-AL31) -> 11767.029 | AP31: =(M31*(1-AL31)-AM31)*AN31 -> 140.48746
A32: ORD-2023-562894 | B32: 44980 | C32: 45010 | D32: Americas | E32: Canada | F32: Montreal | G32: Enterprise | H32: Online | I32: D. Smith | J32: Phones | K32: PHN-4854 | L32: 1242.66 | M32: 1794.07 | N32: 0.089 | O32: 16 | P32: =IF(M32>0,"Valid") -> Valid | Q32: =ABS(M32) -> 1794.07 | R32: =IF(N32>30%,"Excess") -> FALSE | S32: =IF(R32="Excess",30%,N32) -> 0.089 | T32: =(C32-B32) -> 30 | U32: =IF(C32<B32,B32+7,C32) -> 45010 | V32: =(U32-B32) -> 30 | W32: =(Q32*O32*(100-S32)) -> 2867957.2 | X32: =(Q32*O32) -> 28705.12 | Y32: =W32-X32 -> 2839252.1 | Z32: =Y32/W32 -> 0.98999109 | AA32: Feb-2023 | AB32: ="Q"&ROUNDUP(MONTH(B32)/3,0)&"-"&YEAR(B32) -> Q1-2023 | AC32: =D32&" → "&E32&" → "&F32 -> Americas → Canada → Montreal | AD32: =IF(OR(J32="Laptops",J32="Phones"),"Devices",IF(OR(J32="Monitors",J32="Printers"),"Peripherals","Support")) -> Devices | AE32: =IF(B32<=PERCENTILE($B$2:$B$632,0.33),"Low",IF(B32<=PERCENTILE($B$2:$B$632,0.66),"Medium","High")) -> Low | AF32: =UPPER(TRIM(CLEAN(SUBSTITUTE(E32,CHAR(160),"")))) -> CANADA | AG32: =_xlfn.MINIFS($B$2:$B$633,$AF$2:$AF$633,AF32) -> 44928 | AH32: =TEXT(AG32,"MMM-YYYY") -> Jan-2023 | AI32: =EOMONTH(B32,0) -> 44985 | AJ32: =IF(V32<=7,1,0) -> 0 | AK32: =IF(N32>20%,1,0) -> 0 | AL32: =MIN(N32,'Scenario Modelling'!$B$2) -> 0.089 | AM32: =L32*(1+'Scenario Modelling'!$B$3) -> 1429.059 | AN32: =O32*(1+'Scenario Modelling'!$B$4) -> 19.2 | AO32: =AN32*M32*(1-AL32) -> 31380.437 | AP32: =(M32*(1-AL32)-AM32)*AN32 -> 3942.5044
A33: ORD-2025-474710 | B33: 45862 | C33: 45875 | D33: Africa | E33: South Africa | F33: Johannesburg | G33: Education | H33: Marketplace | I33: D. Smith | J33: Networking | K33: NET-7966 | L33: 1463.9 | M33: 2633.02 | N33: 0.084 | O33: 4 | P33: =IF(M33>0,"Valid") -> Valid | Q33: =ABS(M33) -> 2633.02 | R33: =IF(N33>30%,"Excess") -> FALSE | S33: =IF(R33="Excess",30%,N33) -> 0.084 | T33: =(C33-B33) -> 13 | U33: =IF(C33<B33,B33+7,C33) -> 45875 | V33: =(U33-B33) -> 13 | W33: =(Q33*O33*(100-S33)) -> 1052323.3 | X33: =(Q33*O33) -> 10532.08 | Y33: =W33-X33 -> 1041791.2 | Z33: =Y33/W33 -> 0.98999159 | AA33: Jul-2025 | AB33: ="Q"&ROUNDUP(MONTH(B33)/3,0)&"-"&YEAR(B33) -> Q3-2025 | AC33: =D33&" → "&E33&" → "&F33 -> Africa → South Africa → Johannesburg | AD33: =IF(OR(J33="Laptops",J33="Phones"),"Devices",IF(OR(J33="Monitors",J33="Printers"),"Peripherals","Support")) -> Support | AE33: =IF(B33<=PERCENTILE($B$2:$B$632,0.33),"Low",IF(B33<=PERCENTILE($B$2:$B$632,0.66),"Medium","High")) -> High | AF33: =UPPER(TRIM(CLEAN(SUBSTITUTE(E33,CHAR(160),"")))) -> SOUTH AFRICA | AG33: =_xlfn.MINIFS($B$2:$B$633,$AF$2:$AF$633,AF33) -> 44933 | AH33: =TEXT(AG33,"MMM-YYYY") -> Jan-2023 | AI33: =EOMONTH(B33,0) -> 45869 | AJ33: =IF(V33<=7,1,0) -> 0 | AK33: =IF(N33>20%,1,0) -> 0 | AL33: =MIN(N33,'Scenario Modelling'!$B$2) -> 0.084 | AM33: =L33*(1+'Scenario Modelling'!$B$3) -> 1683.485 | AN33: =O33*(1+'Scenario Modelling'!$B$4) -> 4.8 | AO33: =AN33*M33*(1-AL33) -> 11576.862 | AP33: =(M33*(1-AL33)-AM33)*AN33 -> 3496.1343
A34: ORD-2024-629525 | B34: 45400 | C34: 45420 | D34: Europe | E34: United Kingdom | F34: London | G34: Non-Profit | H34: Unknown Channel | I34: D. Smith | J34: Laptops | K34: LAP-9932 | L34: 645.33 | M34: 1321.85 | N34: 0 | O34: 10 | P34: =IF(M34>0,"Valid") -> Valid | Q34: =ABS(M34) -> 1321.85 | R34: =IF(N34>30%,"Excess") -> FALSE | S34: =IF(R34="Excess",30%,N34) -> 0 | T34: =(C34-B34) -> 20 | U34: =IF(C34<B34,B34+7,C34) -> 45420 | V34: =(U34-B34) -> 20 | W34: =(Q34*O34*(100-S34)) -> 1321850 | X34: =(Q34*O34) -> 13218.5 | Y34: =W34-X34 -> 1308631.5 | Z34: =Y34/W34 -> 0.99 | AA34: Apr-2024 | AB34: ="Q"&ROUNDUP(MONTH(B34)/3,0)&"-"&YEAR(B34) -> Q2-2024 | AC34: =D34&" → "&E34&" → "&F34 -> Europe → United Kingdom → London | AD34: =IF(OR(J34="Laptops",J34="Phones"),"Devices",IF(OR(J34="Monitors",J34="Printers"),"Peripherals","Support")) -> Devices | AE34: =IF(B34<=PERCENTILE($B$2:$B$632,0.33),"Low",IF(B34<=PERCENTILE($B$2:$B$632,0.66),"Medium","High")) -> Medium | AF34: =UPPER(TRIM(CLEAN(SUBSTITUTE(E34,CHAR(160),"")))) -> UNITED KINGDOM | AG34: 44945 | AH34: =TEXT(AG34,"MMM-YYYY") -> Jan-2023 | AI34: =EOMONTH(B34,0) -> 45412 | AJ34: =IF(V34<=7,1,0) -> 0 | AK34: =IF(N34>20%,1,0) -> 0 | AL34: =MIN(N34,'Scenario Modelling'!$B$2) -> 0 | AM34: =L34*(1+'Scenario Modelling'!$B$3) -> 742.1295 | AN34: =O34*(1+'Scenario Modelling'!$B$4) -> 12 | AO34: =AN34*M34*(1-AL34) -> 15862.2 | AP34: =(M34*(1-AL34)-AM34)*AN34 -> 6956.646
A35: ORD-2024-167215 | B35: 45527 | C35: 45525 | D35: Africa | E35: South Africa | F35: Johannesburg | G35: Education | H35: Retail | I35: E. Garcia | J35: Components | K35: CMP-1559 | L35: 1432.52 | M35: 3036.87 | N35: 0 | O35: 9 | P35: =IF(M35>0,"Valid") -> Valid | Q35: =ABS(M35) -> 3036.87 | R35: =IF(N35>30%,"Excess") -> FALSE | S35: =IF(R35="Excess",30%,N35) -> 0 | T35: =(C35-B35) -> -2 | U35: =IF(C35<B35,B35+7,C35) -> 45534 | V35: =(U35-B35) -> 7 | W35: =(Q35*O35*(100-S35)) -> 2733183 | X35: =(Q35*O35) -> 27331.83 | Y35: =W35-X35 -> 2705851.2 | Z35: =Y35/W35 -> 0.99 | AA35: Aug-2024 | AB35: ="Q"&ROUNDUP(MONTH(B35)/3,0)&"-"&YEAR(B35) -> Q3-2024 | AC35: =D35&" → "&E35&" → "&F35 -> Africa → South Africa → Johannesburg | AD35: =IF(OR(J35="Laptops",J35="Phones"),"Devices",IF(OR(J35="Monitors",J35="Printers"),"Peripherals","Support")) -> Support | AE35: =IF(B35<=PERCENTILE($B$2:$B$632,0.33),"Low",IF(B35<=PERCENTILE($B$2:$B$632,0.66),"Medium","High")) -> Medium | AF35: =UPPER(TRIM(CLEAN(SUBSTITUTE(E35,CHAR(160),"")))) -> SOUTH AFRICA | AG35: =_xlfn.MINIFS($B$2:$B$633,$AF$2:$AF$633,AF35) -> 44933 | AH35: =TEXT(AG35,"MMM-YYYY") -> Jan-2023 | AI35: =EOMONTH(B35,0) -> 45535 | AJ35: =IF(V35<=7,1,0) -> 1 | AK35: =IF(N35>20%,1,0) -> 0 | AL35: =MIN(N35,'Scenario Modelling'!$B$2) -> 0 | AM35: =L35*(1+'Scenario Modelling'!$B$3) -> 1647.398 | AN35: =O35*(1+'Scenario Modelling'!$B$4) -> 10.8 | AO35: =AN35*M35*(1-AL35) -> 32798.196 | AP35: =(M35*(1-AL35)-AM35)*AN35 -> 15006.298
A36: ORD-2023-864121 | B36: 45012 | C36: 45038 | D36: Asia | E36: India | F36: Delhi | G36: Non-Profit | H36: Marketplace | I36: J. Njeri | J36: Printers | K36: PRN-4506 | L36: 178.53 | M36: 199.37 | N36: 0.101 | O36: 37 | P36: =IF(M36>0,"Valid") -> Valid | Q36: =ABS(M36) -> 199.37 | R36: =IF(N36>30%,"Excess") -> FALSE | S36: =IF(R36="Excess",30%,N36) -> 0.101 | T36: =(C36-B36) -> 26 | U36: =IF(C36<B36,B36+7,C36) -> 45038 | V36: =(U36-B36) -> 26 | W36: =(Q36*O36*(100-S36)) -> 736923.95 | X36: =(Q36*O36) -> 7376.69 | Y36: =W36-X36 -> 729547.26 | Z36: =Y36/W36 -> 0.98998989 | AA36: Mar-2023 | AB36: ="Q"&ROUNDUP(MONTH(B36)/3,0)&"-"&YEAR(B36) -> Q1-2023 | AC36: =D36&" → "&E36&" → "&F36 -> Asia → India → Delhi | AD36: =IF(OR(J36="Laptops",J36="Phones"),"Devices",IF(OR(J36="Monitors",J36="Printers"),"Peripherals","Support")) -> Peripherals | AE36: =IF(B36<=PERCENTILE($B$2:$B$632,0.33),"Low",IF(B36<=PERCENTILE($B$2:$B$632,0.66),"Medium","High")) -> Low | AF36: =UPPER(TRIM(CLEAN(SUBSTITUTE(E36,CHAR(160),"")))) -> INDIA | AG36: 44955 | AH36: =TEXT(AG36,"MMM-YYYY") -> Jan-2023 | AI36: =EOMONTH(B36,0) -> 45016 | AJ36: =IF(V36<=7,1,0) -> 0 | AK36: =IF(N36>20%,1,0) -> 0 | AL36: =MIN(N36,'Scenario Modelling'!$B$2) -> 0.101 | AM36: =L36*(1+'Scenario Modelling'!$B$3) -> 205.3095 | AN36: =O36*(1+'Scenario Modelling'!$B$4) -> 44.4 | AO36: =AN36*M36*(1-AL36) -> 7957.9732 | AP36: =(M36*(1-AL36)-AM36)*AN36 -> -1157.7686
A37: ORD-2024-692673 | B37: 45358 | C37: 45376 | D37: Europe | E37: Germany | F37: Munich | G37: Corporate | H37: Online | I37: B. Chen | J37: Components | K37: CMP-7617 | L37: 712.84 | M37: 927.51 | N37: 0.243 | O37: 27 | P37: =IF(M37>0,"Valid") -> Valid | Q37: =ABS(M37) -> 927.51 | R37: =IF(N37>30%,"Excess") -> FALSE | S37: =IF(R37="Excess",30%,N37) -> 0.243 | T37: =(C37-B37) -> 18 | U37: =IF(C37<B37,B37+7,C37) -> 45376 | V37: =(U37-B37) -> 18 | W37: =(Q37*O37*(100-S37)) -> 2498191.6 | X37: =(Q37*O37) -> 25042.77 | Y37: =W37-X37 -> 2473148.8 | Z37: =Y37/W37 -> 0.98997564 | AA37: Mar-2024 | AB37: ="Q"&ROUNDUP(MONTH(B37)/3,0)&"-"&YEAR(B37) -> Q1-2024 | AC37: =D37&" → "&E37&" → "&F37 -> Europe → Germany → Munich | AD37: =IF(OR(J37="Laptops",J37="Phones"),"Devices",IF(OR(J37="Monitors",J37="Printers"),"Peripherals","Support")) -> Support | AE37: =IF(B37<=PERCENTILE($B$2:$B$632,0.33),"Low",IF(B37<=PERCENTILE($B$2:$B$632,0.66),"Medium","High")) -> Medium | AF37: =UPPER(TRIM(CLEAN(SUBSTITUTE(E37,CHAR(160),"")))) -> GERMANY | AG37: 44948 | AH37: =TEXT(AG37,"MMM-YYYY") -> Jan-2023 | AI37: =EOMONTH(B37,0) -> 45382 | AJ37: =IF(V37<=7,1,0) -> 0 | AK37: =IF(N37>20%,1,0) -> 1 | AL37: =MIN(N37,'Scenario Modelling'!$B$2) -> 0.243 | AM37: =L37*(1+'Scenario Modelling'!$B$3) -> 819.766 | AN37: =O37*(1+'Scenario Modelling'!$B$4) -> 32.4 | AO37: =AN37*M37*(1-AL37) -> 22748.852 | AP37: =(M37*(1-AL37)-AM37)*AN37 -> -3811.5661
A38: ORD-2025-718992 | B38: 45832 | C38: 45848 | D38: Asia | E38: China | F38: Shanghai | G38: Enterprise | H38: Direct | I38: N. Brown | J38: Components | K38: CMP-8390 | L38: 757.19 | M38: 1735.41 | N38: 0.136 | O38: 8 | P38: =IF(M38>0,"Valid") -> Valid | Q38: =ABS(M38) -> 1735.41 | R38: =IF(N38>30%,"Excess") -> FALSE | S38: =IF(R38="Excess",30%,N38) -> 0.136 | T38: =(C38-B38) -> 16 | U38: =IF(C38<B38,B38+7,C38) -> 45848 | V38: =(U38-B38) -> 16 | W38: =(Q38*O38*(100-S38)) -> 1386439.9 | X38: =(Q38*O38) -> 13883.28 | Y38: =W38-X38 -> 1372556.6 | Z38: =Y38/W38 -> 0.98998638 | AA38: Jun-2025 | AB38: ="Q"&ROUNDUP(MONTH(B38)/3,0)&"-"&YEAR(B38) -> Q2-2025 | AC38: =D38&" → "&E38&" → "&F38 -> Asia → China → Shanghai | AD38: =IF(OR(J38="Laptops",J38="Phones"),"Devices",IF(OR(J38="Monitors",J38="Printers"),"Peripherals","Support")) -> Support | AE38: =IF(B38<=PERCENTILE($B$2:$B$632,0.33),"Low",IF(B38<=PERCENTILE($B$2:$B$632,0.66),"Medium","High")) -> High | AF38: =UPPER(TRIM(CLEAN(SUBSTITUTE(E38,CHAR(160),"")))) -> CHINA | AG38: =_xlfn.MINIFS($B$2:$B$633,$AF$2:$AF$633,AF38) -> 44938 | AH38: =TEXT(AG38,"MMM-YYYY") -> Jan-2023 | AI38: =EOMONTH(B38,0) -> 45838 | AJ38: =IF(V38<=7,1,0) -> 0 | AK38: =IF(N38>20%,1,0) -> 0 | AL38: =MIN(N38,'Scenario Modelling'!$B$2) -> 0.136 | AM38: =L38*(1+'Scenario Modelling'!$B$3) -> 870.7685 | AN38: =O38*(1+'Scenario Modelling'!$B$4) -> 9.6 | AO38: =AN38*M38*(1-AL38) -> 14394.185 | AP38: =(M38*(1-AL38)-AM38)*AN38 -> 6034.8071
A39: ORD-2024-599522 | B39: 45401 | C39: 45418 | D39: Africa | E39: Nigeria | F39: Port Harcourt | G39: Non-Profit | H39: Online | I39: A. Patel | J39: Printers | K39: PRN-7303 | L39: 865.33 | M39: 1395.64 | N39: 0.175 | O39: 13 | P39: =IF(M39>0,"Valid") -> Valid | Q39: =ABS(M39) -> 1395.64 | R39: =IF(N39>30%,"Excess") -> FALSE | S39: =IF(R39="Excess",30%,N39) -> 0.175 | T39: =(C39-B39) -> 17 | U39: =IF(C39<B39,B39+7,C39) -> 45418 | V39: =(U39-B39) -> 17 | W39: =(Q39*O39*(100-S39)) -> 1811156.9 | X39: =(Q39*O39) -> 18143.32 | Y39: =W39-X39 -> 1793013.6 | Z39: =Y39/W39 -> 0.98998247 | AA39: Apr-2024 | AB39: ="Q"&ROUNDUP(MONTH(B39)/3,0)&"-"&YEAR(B39) -> Q2-2024 | AC39: =D39&" → "&E39&" → "&F39 -> Africa → Nigeria → Port Harcourt | AD39: =IF(OR(J39="Laptops",J39="Phones"),"Devices",IF(OR(J39="Monitors",J39="Printers"),"Peripherals","Support")) -> Peripherals | AE39: =IF(B39<=PERCENTILE($B$2:$B$632,0.33),"Low",IF(B39<=PERCENTILE($B$2:$B$632,0.66),"Medium","High")) -> Medium | AF39: =UPPER(TRIM(CLEAN(SUBSTITUTE(E39,CHAR(160),"")))) -> NIGERIA | AG39: =_xlfn.MINIFS($B$2:$B$633,$AF$2:$AF$633,AF39) -> 44941 | AH39: =TEXT(AG39,"MMM-YYYY") -> Jan-2023 | AI39: =EOMONTH(B39,0) -> 45412 | AJ39: =IF(V39<=7,1,0) -> 0 | AK39: =IF(N39>20%,1,0) -> 0 | AL39: =MIN(N39,'Scenario Modelling'!$B$2) -> 0.175 | AM39: =L39*(1+'Scenario Modelling'!$B$3) -> 995.1295 | AN39: =O39*(1+'Scenario Modelling'!$B$4) -> 15.6 | AO39: =AN39*M39*(1-AL39) -> 17961.887 | AP39: =(M39*(1-AL39)-AM39)*AN39 -> 2437.8666
A40: ORD-2023-651638 | B40: 45094 | C40: 45101 | D40: Americas | E40: USA | F40: San Francisco | G40: Corporate | H40: Retail | I40: I. Johnson | J40: Printers | K40: PRN-6536 | L40: 313.99 | M40: 454.42 | N40: 0.129 | O40: 9 | P40: =IF(M40>0,"Valid") -> Valid | Q40: =ABS(M40) -> 454.42 | R40: =IF(N40>30%,"Excess") -> FALSE | S40: =IF(R40="Excess",30%,N40) -> 0.129 | T40: =(C40-B40) -> 7 | U40: =IF(C40<B40,B40+7,C40) -> 45101 | V40: =(U40-B40) -> 7 | W40: =(Q40*O40*(100-S40)) -> 408450.42 | X40: =(Q40*O40) -> 4089.78 | Y40: =W40-X40 -> 404360.64 | Z40: =Y40/W40 -> 0.98998708 | AA40: Jun-2023 | AB40: ="Q"&ROUNDUP(MONTH(B40)/3,0)&"-"&YEAR(B40) -> Q2-2023 | AC40: =D40&" → "&E40&" → "&F40 -> Americas → USA → San Francisco | AD40: =IF(OR(J40="Laptops",J40="Phones"),"Devices",IF(OR(J40="Monitors",J40="Printers"),"Peripherals","Support")) -> Peripherals | AE40: =IF(B40<=PERCENTILE($B$2:$B$632,0.33),"Low",IF(B40<=PERCENTILE($B$2:$B$632,0.66),"Medium","High")) -> Low | AF40: =UPPER(TRIM(CLEAN(SUBSTITUTE(E40,CHAR(160),"")))) -> USA | AG40: 44939 | AH40: =TEXT(AG40,"MMM-YYYY") -> Jan-2023 | AI40: =EOMONTH(B40,0) -> 45107 | AJ40: =IF(V40<=7,1,0) -> 1 | AK40: =IF(N40>20%,1,0) -> 0 | AL40: =MIN(N40,'Scenario Modelling'!$B$2) -> 0.129 | AM40: =L40*(1+'Scenario Modelling'!$B$3) -> 361.0885 | AN40: =O40*(1+'Scenario Modelling'!$B$4) -> 10.8 | AO40: =AN40*M40*(1-AL40) -> 4274.6381 | AP40: =(M40*(1-AL40)-AM40)*AN40 -> 374.88226
A41: ORD-2024-635626 | B41: 45531 | C41: 45554 | D41: Europe | E41: Germany | F41: Berlin | G41: Small Business | H41: Direct | I41: D. Smith | J41: Monitors | K41: MON-9967 | L41: 1024.01 | M41: 1580.97 | N41: 0.037 | O41: 27 | P41: =IF(M41>0,"Valid") -> Valid | Q41: =ABS(M41) -> 1580.97 | R41: =IF(N41>30%,"Excess") -> FALSE | S41: =IF(R41="Excess",30%,N41) -> 0.037 | T41: =(C41-B41) -> 23 | U41: =IF(C41<B41,B41+7,C41) -> 45554 | V41: =(U41-B41) -> 23 | W41: =(Q41*O41*(100-S41)) -> 4267039.6 | X41: =(Q41*O41) -> 42686.19 | Y41: =W41-X41 -> 4224353.4 | Z41: =Y41/W41 -> 0.9899963 | AA41: Aug-2024 | AB41: ="Q"&ROUNDUP(MONTH(B41)/3,0)&"-"&YEAR(B41) -> Q3-2024 | AC41: =D41&" → "&E41&" → "&F41 -> Europe → Germany → Berlin | AD41: =IF(OR(J41="Laptops",J41="Phones"),"Devices",IF(OR(J41="Monitors",J41="Printers"),"Peripherals","Support")) -> Peripherals | AE41: =IF(B41<=PERCENTILE($B$2:$B$632,0.33),"Low",IF(B41<=PERCENTILE($B$2:$B$632,0.66),"Medium","High")) -> Medium | AF41: =UPPER(TRIM(CLEAN(SUBSTITUTE(E41,CHAR(160),"")))) -> GERMANY | AG41: 44948 | AH41: =TEXT(AG41,"MMM-YYYY") -> Jan-2023 | AI41: =EOMONTH(B41,0) -> 45535 | AJ41: =IF(V41<=7,1,0) -> 0 | AK41: =IF(N41>20%,1,0) -> 0 | AL41: =MIN(N41,'Scenario Modelling'!$B$2) -> 0.037 | AM41: =L41*(1+'Scenario Modelling'!$B$3) -> 1177.6115 | AN41: =O41*(1+'Scenario Modelling'!$B$4) -> 32.4 | AO41: =AN41*M41*(1-AL41) -> 49328.161 | AP41: =(M41*(1-AL41)-AM41)*AN41 -> 11173.549
A42: ORD-2024-296582 | B42: 45302 | C42: 45324 | D42: Africa | E42: South Africa | F42: Durban | G42: Consumer | H42: Online | I42: K. Singh | J42: Networking | K42: NET-1412 | L42: 1206.2 | M42: 1759.79 | N42: 0 | O42: 6 | P42: =IF(M42>0,"Valid") -> Valid | Q42: =ABS(M42) -> 1759.79 | R42: =IF(N42>30%,"Excess") -> FALSE | S42: =IF(R42="Excess",30%,N42) -> 0 | T42: =(C42-B42) -> 22 | U42: =IF(C42<B42,B42+7,C42) -> 45324 | V42: =(U42-B42) -> 22 | W42: =(Q42*O42*(100-S42)) -> 1055874 | X42: =(Q42*O42) -> 10558.74 | Y42: =W42-X42 -> 1045315.3 | Z42: =Y42/W42 -> 0.99 | AA42: Jan-2024 | AB42: ="Q"&ROUNDUP(MONTH(B42)/3,0)&"-"&YEAR(B42) -> Q1-2024 | AC42: =D42&" → "&E42&" → "&F42 -> Africa → South Africa → Durban | AD42: =IF(OR(J42="Laptops",J42="Phones"),"Devices",IF(OR(J42="Monitors",J42="Printers"),"Peripherals","Support")) -> Support | AE42: =IF(B42<=PERCENTILE($B$2:$B$632,0.33),"Low",IF(B42<=PERCENTILE($B$2:$B$632,0.66),"Medium","High")) -> Medium | AF42: =UPPER(TRIM(CLEAN(SUBSTITUTE(E42,CHAR(160),"")))) -> SOUTH AFRICA | AG42: =_xlfn.MINIFS($B$2:$B$633,$AF$2:$AF$633,AF42) -> 44933 | AH42: =TEXT(AG42,"MMM-YYYY") -> Jan-2023 | AI42: =EOMONTH(B42,0) -> 45322 | AJ42: =IF(V42<=7,1,0) -> 0 | AK42: =IF(N42>20%,1,0) -> 0 | AL42: =MIN(N42,'Scenario Modelling'!$B$2) -> 0 | AM42: =L42*(1+'Scenario Modelling'!$B$3) -> 1387.13 | AN42: =O42*(1+'Scenario Modelling'!$B$4) -> 7.2 | AO42: =AN42*M42*(1-AL42) -> 12670.488 | AP42: =(M42*(1-AL42)-AM42)*AN42 -> 2683.152
A43: ORD-2024-998320 | B43: 45590 | C43: 45610 | D43: Africa | E43: Kenya | F43: Mombasa | G43: Corporate | H43: Direct | I43: H. Kim | J43: Printers | K43: PRN-3143 | L43: 1396.48 | M43: 3204.5 | N43: 0.318 | O43: 14 | P43: =IF(M43>0,"Valid") -> Valid | Q43: =ABS(M43) -> 3204.5 | R43: =IF(N43>30%,"Excess") -> Excess | S43: =IF(R43="Excess",30%,N43) -> 0.3 | T43: =(C43-B43) -> 20 | U43: =IF(C43<B43,B43+7,C43) -> 45610 | V43: =(U43-B43) -> 20 | W43: =(Q43*O43*(100-S43)) -> 4472841.1 | X43: =(Q43*O43) -> 44863 | Y43: =W43-X43 -> 4427978.1 | Z43: =Y43/W43 -> 0.98996991 | AA43: Oct-2024 | AB43: ="Q"&ROUNDUP(MONTH(B43)/3,0)&"-"&YEAR(B43) -> Q4-2024 | AC43: =D43&" → "&E43&" → "&F43 -> Africa → Kenya → Mombasa | AD43: =IF(OR(J43="Laptops",J43="Phones"),"Devices",IF(OR(J43="Monitors",J43="Printers"),"Peripherals","Support")) -> Peripherals | AE43: =IF(B43<=PERCENTILE($B$2:$B$632,0.33),"Low",IF(B43<=PERCENTILE($B$2:$B$632,0.66),"Medium","High")) -> High | AF43: =UPPER(TRIM(CLEAN(SUBSTITUTE(E43,CHAR(160),"")))) -> KENYA | AG43: 44946 | AH43: =TEXT(AG43,"MMM-YYYY") -> Jan-2023 | AI43: =EOMONTH(B43,0) -> 45596 | AJ43: =IF(V43<=7,1,0) -> 0 | AK43: =IF(N43>20%,1,0) -> 1 | AL43: =MIN(N43,'Scenario Modelling'!$B$2) -> 0.25 | AM43: =L43*(1+'Scenario Modelling'!$B$3) -> 1605.952 | AN43: =O43*(1+'Scenario Modelling'!$B$4) -> 16.8 | AO43: =AN43*M43*(1-AL43) -> 40376.7 | AP43: =(M43*(1-AL43)-AM43)*AN43 -> 13396.706
A44: ORD-2025-820255 | B44: 45806 | C44: 45828 | D44: Europe | E44: Germany | F44: Berlin | G44: Corporate | H44: Direct | I44: A. Patel | J44: Printers | K44: PRN-9787 | L44: 483.47 | M44: 1135.43 | N44: 0.146 | O44: 11 | P44: =IF(M44>0,"Valid") -> Valid | Q44: =ABS(M44) -> 1135.43 | R44: =IF(N44>30%,"Excess") -> FALSE | S44: =IF(R44="Excess",30%,N44) -> 0.146 | T44: =(C44-B44) -> 22 | U44: =IF(C44<B44,B44+7,C44) -> 45828 | V44: =(U44-B44) -> 22 | W44: =(Q44*O44*(100-S44)) -> 1247149.5 | X44: =(Q44*O44) -> 12489.73 | Y44: =W44-X44 -> 1234659.8 | Z44: =Y44/W44 -> 0.98998538 | AA44: May-2025 | AB44: ="Q"&ROUNDUP(MONTH(B44)/3,0)&"-"&YEAR(B44) -> Q2-2025 | AC44: =D44&" → "&E44&" → "&F44 -> Europe → Germany → Berlin | AD44: =IF(OR(J44="Laptops",J44="Phones"),"Devices",IF(OR(J44="Monitors",J44="Printers"),"Peripherals","Support")) -> Peripherals | AE44: =IF(B44<=PERCENTILE($B$2:$B$632,0.33),"Low",IF(B44<=PERCENTILE($B$2:$B$632,0.66),"Medium","High")) -> High | AF44: =UPPER(TRIM(CLEAN(SUBSTITUTE(E44,CHAR(160),"")))) -> GERMANY | AG44: 44948 | AH44: =TEXT(AG44,"MMM-YYYY") -> Jan-2023 | AI44: =EOMONTH(B44,0) -> 45808 | AJ44: =IF(V44<=7,1,0) -> 0 | AK44: =IF(N44>20%,1,0) -> 0 | AL44: =MIN(N44,'Scenario Modelling'!$B$2) -> 0.146 | AM44: =L44*(1+'Scenario Modelling'!$B$3) -> 555.9905 | AN44: =O44*(1+'Scenario Modelling'!$B$4) -> 13.2 | AO44: =AN44*M44*(1-AL44) -> 12799.475 | AP44: =(M44*(1-AL44)-AM44)*AN44 -> 5460.4007
A45: ORD-2024-389336 | B45: 45432 | C45: 45445 | D45: Americas | E45: Canada | F45: Vancouver | G45: Enterprise | H45: Marketplace | I45: K. Singh | J45: Components | K45: CMP-5946 | L45: 675.43 | M45: 996.36 | N45: 0.182 | O45: 22 | P45: =IF(M45>0,"Valid") -> Valid | Q45: =ABS(M45) -> 996.36 | R45: =IF(N45>30%,"Excess") -> FALSE | S45: =IF(R45="Excess",30%,N45) -> 0.182 | T45: =(C45-B45) -> 13 | U45: =IF(C45<B45,B45+7,C45) -> 45445 | V45: =(U45-B45) -> 13 | W45: =(Q45*O45*(100-S45)) -> 2188002.6 | X45: =(Q45*O45) -> 21919.92 | Y45: =W45-X45 -> 2166082.7 | Z45: =Y45/W45 -> 0.98998177 | AA45: May-2024 | AB45: ="Q"&ROUNDUP(MONTH(B45)/3,0)&"-"&YEAR(B45) -> Q2-2024 | AC45: =D45&" → "&E45&" → "&F45 -> Americas → Canada → Vancouver | AD45: =IF(OR(J45="Laptops",J45="Phones"),"Devices",IF(OR(J45="Monitors",J45="Printers"),"Peripherals","Support")) -> Support | AE45: =IF(B45<=PERCENTILE($B$2:$B$632,0.33),"Low",IF(B45<=PERCENTILE($B$2:$B$632,0.66),"Medium","High")) -> Medium | AF45: =UPPER(TRIM(CLEAN(SUBSTITUTE(E45,CHAR(160),"")))) -> CANADA | AG45: =_xlfn.MINIFS($B$2:$B$633,$AF$2:$AF$633,AF45) -> 44928 | AH45: =TEXT(AG45,"MMM-YYYY") -> Jan-2023 | AI45: =EOMONTH(B45,0) -> 45443 | AJ45: =IF(V45<=7,1,0) -> 0 | AK45: =IF(N45>20%,1,0) -> 0 | AL45: =MIN(N45,'Scenario Modelling'!$B$2) -> 0.182 | AM45: =L45*(1+'Scenario Modelling'!$B$3) -> 776.7445 | AN45: =O45*(1+'Scenario Modelling'!$B$4) -> 26.4 | AO45: =AN45*M45*(1-AL45) -> 21516.593 | AP45: =(M45*(1-AL45)-AM45)*AN45 -> 1010.5387
A46: ORD-2023-308124 | B46: 45035 | C46: 45046 | D46: Asia | E46: India | F46: Delhi | G46: Small Business | H46: Retail | I46: A. Patel | J46: Networking | K46: NET-2062 | L46: 826.55 | M46: 1397.05 | N46: 0.169 | O46: 28 | P46: =IF(M46>0,"Valid") -> Valid | Q46: =ABS(M46) -> 1397.05 | R46: =IF(N46>30%,"Excess") -> FALSE | S46: =IF(R46="Excess",30%,N46) -> 0.169 | T46: =(C46-B46) -> 11 | U46: =IF(C46<B46,B46+7,C46) -> 45046 | V46: =(U46-B46) -> 11 | W46: =(Q46*O46*(100-S46)) -> 3905129.2 | X46: =(Q46*O46) -> 39117.4 | Y46: =W46-X46 -> 3866011.8 | Z46: =Y46/W46 -> 0.98998307 | AA46: Apr-2023 | AB46: ="Q"&ROUNDUP(MONTH(B46)/3,0)&"-"&YEAR(B46) -> Q2-2023 | AC46: =D46&" → "&E46&" → "&F46 -> Asia → India → Delhi | AD46: =IF(OR(J46="Laptops",J46="Phones"),"Devices",IF(OR(J46="Monitors",J46="Printers"),"Peripherals","Support")) -> Support | AE46: =IF(B46<=PERCENTILE($B$2:$B$632,0.33),"Low",IF(B46<=PERCENTILE($B$2:$B$632,0.66),"Medium","High")) -> Low | AF46: =UPPER(TRIM(CLEAN(SUBSTITUTE(E46,CHAR(160),"")))) -> INDIA | AG46: 44955 | AH46: =TEXT(AG46,"MMM-YYYY") -> Jan-2023 | AI46: =EOMONTH(B46,0) -> 45046 | AJ46: =IF(V46<=7,1,0) -> 0 | AK46: =IF(N46>20%,1,0) -> 0 | AL46: =MIN(N46,'Scenario Modelling'!$B$2) -> 0.169 | AM46: =L46*(1+'Scenario Modelling'!$B$3) -> 950.5325 | AN46: =O46*(1+'Scenario Modelling'!$B$4) -> 33.6 | AO46: =AN46*M46*(1-AL46) -> 39007.871 | AP46: =(M46*(1-AL46)-AM46)*AN46 -> 7069.9793
A47: ORD-2023-128295 | B47: 45100 | C47: 45110 | D47: Africa | E47: Nigeria | F47: Abuja | G47: Consumer | H47: Online | I47: J. Njeri | J47: Printers | K47: PRN-2542 | L47: 337.75 | M47: 548.89 | N47: 0 | O47: 13 | P47: =IF(M47>0,"Valid") -> Valid | Q47: =ABS(M47) -> 548.89 | R47: =IF(N47>30%,"Excess") -> FALSE | S47: =IF(R47="Excess",30%,N47) -> 0 | T47: =(C47-B47) -> 10 | U47: =IF(C47<B47,B47+7,C47) -> 45110 | V47: =(U47-B47) -> 10 | W47: =(Q47*O47*(100-S47)) -> 713557 | X47: =(Q47*O47) -> 7135.57 | Y47: =W47-X47 -> 706421.43 | Z47: =Y47/W47 -> 0.99 | AA47: Jun-2023 | AB47: ="Q"&ROUNDUP(MONTH(B47)/3,0)&"-"&YEAR(B47) -> Q2-2023 | AC47: =D47&" → "&E47&" → "&F47 -> Africa → Nigeria → Abuja | AD47: =IF(OR(J47="Laptops",J47="Phones"),"Devices",IF(OR(J47="Monitors",J47="Printers"),"Peripherals","Support")) -> Peripherals | AE47: =IF(B47<=PERCENTILE($B$2:$B$632,0.33),"Low",IF(B47<=PERCENTILE($B$2:$B$632,0.66),"Medium","High")) -> Low | AF47: =UPPER(TRIM(CLEAN(SUBSTITUTE(E47,CHAR(160),"")))) -> NIGERIA | AG47: =_xlfn.MINIFS($B$2:$B$633,$AF$2:$AF$633,AF47) -> 44941 | AH47: =TEXT(AG47,"MMM-YYYY") -> Jan-2023 | AI47: =EOMONTH(B47,0) -> 45107 | AJ47: =IF(V47<=7,1,0) -> 0 | AK47: =IF(N47>20%,1,0) -> 0 | AL47: =MIN(N47,'Scenario Modelling'!$B$2) -> 0 | AM47: =L47*(1+'Scenario Modelling'!$B$3) -> 388.4125 | AN47: =O47*(1+'Scenario Modelling'!$B$4) -> 15.6 | AO47: =AN47*M47*(1-AL47) -> 8562.684 | AP47: =(M47*(1-AL47)-AM47)*AN47 -> 2503.449
A48: ORD-2024-548345 | B48: 45426 | C48: 45440 | D48: Europe | E48: United Kingdom | F48: Birmingham | G48: Consumer | H48: Retail | I48: B. Chen | J48: Networking | K48: NET-2365 | L48: 1421.14 | M48: 3524 | N48: 0 | O48: 31 | P48: =IF(M48>0,"Valid") -> Valid | Q48: =ABS(M48) -> 3524 | R48: =IF(N48>30%,"Excess") -> FALSE | S48: =IF(R48="Excess",30%,N48) -> 0 | T48: =(C48-B48) -> 14 | U48: =IF(C48<B48,B48+7,C48) -> 45440 | V48: =(U48-B48) -> 14 | W48: =(Q48*O48*(100-S48)) -> 10924400 | X48: =(Q48*O48) -> 109244 | Y48: =W48-X48 -> 10815156 | Z48: =Y48/W48 -> 0.99 | AA48: May-2024 | AB48: ="Q"&ROUNDUP(MONTH(B48)/3,0)&"-"&YEAR(B48) -> Q2-2024 | AC48: =D48&" → "&E48&" → "&F48 -> Europe → United Kingdom → Birmingham | AD48: =IF(OR(J48="Laptops",J48="Phones"),"Devices",IF(OR(J48="Monitors",J48="Printers"),"Peripherals","Support")) -> Support | AE48: =IF(B48<=PERCENTILE($B$2:$B$632,0.33),"Low",IF(B48<=PERCENTILE($B$2:$B$632,0.66),"Medium","High")) -> Medium | AF48: =UPPER(TRIM(CLEAN(SUBSTITUTE(E48,CHAR(160),"")))) -> UNITED KINGDOM | AG48: 44945 | AH48: =TEXT(AG48,"MMM-YYYY") -> Jan-2023 | AI48: =EOMONTH(B48,0) -> 45443 | AJ48: =IF(V48<=7,1,0) -> 0 | AK48: =IF(N48>20%,1,0) -> 0 | AL48: =MIN(N48,'Scenario Modelling'!$B$2) -> 0 | AM48: =L48*(1+'Scenario Modelling'!$B$3) -> 1634.311 | AN48: =O48*(1+'Scenario Modelling'!$B$4) -> 37.2 | AO48: =AN48*M48*(1-AL48) -> 131092.8 | AP48: =(M48*(1-AL48)-AM48)*AN48 -> 70296.431
A49: ORD-2024-966651 | B49: 45579 | C49: 45604 | D49: Africa | E49: Nigeria | F49: Lagos | G49: Enterprise | H49: Online | I49: O. Wang | J49: Networking | K49: NET-5268 | L49: 859.35 | M49: 1825.61 | N49: 0.187 | O49: 24 | P49: =IF(M49>0,"Valid") -> Valid | Q49: =ABS(M49) -> 1825.61 | R49: =IF(N49>30%,"Excess") -> FALSE | S49: =IF(R49="Excess",30%,N49) -> 0.187 | T49: =(C49-B49) -> 25 | U49: =IF(C49<B49,B49+7,C49) -> 45604 | V49: =(U49-B49) -> 25 | W49: =(Q49*O49*(100-S49)) -> 4373270.7 | X49: =(Q49*O49) -> 43814.64 | Y49: =W49-X49 -> 4329456 | Z49: =Y49/W49 -> 0.98998126 | AA49: Oct-2024 | AB49: ="Q"&ROUNDUP(MONTH(B49)/3,0)&"-"&YEAR(B49) -> Q4-2024 | AC49: =D49&" → "&E49&" → "&F49 -> Africa → Nigeria → Lagos | AD49: =IF(OR(J49="Laptops",J49="Phones"),"Devices",IF(OR(J49="Monitors",J49="Printers"),"Peripherals","Support")) -> Support | AE49: =IF(B49<=PERCENTILE($B$2:$B$632,0.33),"Low",IF(B49<=PERCENTILE($B$2:$B$632,0.66),"Medium","High")) -> Medium | AF49: =UPPER(TRIM(CLEAN(SUBSTITUTE(E49,CHAR(160),"")))) -> NIGERIA | AG49: =_xlfn.MINIFS($B$2:$B$633,$AF$2:$AF$633,AF49) -> 44941 | AH49: =TEXT(AG49,"MMM-YYYY") -> Jan-2023 | AI49: =EOMONTH(B49,0) -> 45596 | AJ49: =IF(V49<=7,1,0) -> 0 | AK49: =IF(N49>20%,1,0) -> 0 | AL49: =MIN(N49,'Scenario Modelling'!$B$2) -> 0.187 | AM49: =L49*(1+'Scenario Modelling'!$B$3) -> 988.2525 | AN49: =O49*(1+'Scenario Modelling'!$B$4) -> 28.8 | AO49: =AN49*M49*(1-AL49) -> 42745.563 | AP49: =(M49*(1-AL49)-AM49)*AN49 -> 14283.891
A50: ORD-2023-292714 | B50: 45117 | C50: 45139 | D50: Europe | E50: France | F50: Marseille | G50: Consumer | H50: Marketplace | I50: B. Chen | J50: Printers | K50: PRN-1504 | L50: 1303.56 | M50: 1791.37 | N50: 0.126 | O50: 22 | P50: =IF(M50>0,"Valid") -> Valid | Q50: =ABS(M50) -> 1791.37 | R50: =IF(N50>30%,"Excess") -> FALSE | S50: =IF(R50="Excess",30%,N50) -> 0.126 | T50: =(C50-B50) -> 22 | U50: =IF(C50<B50,B50+7,C50) -> 45139 | V50: =(U50-B50) -> 22 | W50: =(Q50*O50*(100-S50)) -> 3936048.3 | X50: =(Q50*O50) -> 39410.14 | Y50: =W50-X50 -> 3896638.2 | Z50: =Y50/W50 -> 0.98998738 | AA50: Jul-2023 | AB50: ="Q"&ROUNDUP(MONTH(B50)/3,0)&"-"&YEAR(B50) -> Q3-2023 | AC50: =D50&" → "&E50&" → "&F50 -> Europe → France → Marseille | AD50: =IF(OR(J50="Laptops",J50="Phones"),"Devices",IF(OR(J50="Monitors",J50="Printers"),"Peripherals","Support")) -> Peripherals | AE50: =IF(B50<=PERCENTILE($B$2:$B$632,0.33),"Low",IF(B50<=PERCENTILE($B$2:$B$632,0.66),"Medium","High")) -> Low | AF50: =UPPER(TRIM(CLEAN(SUBSTITUTE(E50,CHAR(160),"")))) -> FRANCE | AG50: 44936 | AH50: =TEXT(AG50,"MMM-YYYY") -> Jan-2023 | AI50: =EOMONTH(B50,0) -> 45138 | AJ50: =IF(V50<=7,1,0) -> 0 | AK50: =IF(N50>20%,1,0) -> 0 | AL50: =MIN(N50,'Scenario Modelling'!$B$2) -> 0.126 | AM50: =L50*(1+'Scenario Modelling'!$B$3) -> 1499.094 | AN50: =O50*(1+'Scenario Modelling'!$B$4) -> 26.4 | AO50: =AN50*M50*(1-AL50) -> 41333.355 | AP50: =(M50*(1-AL50)-AM50)*AN50 -> 1757.2732
A51: ORD-2024-468501 | B51: 45602 | C51: 45618 | D51: Americas | E51: Canada | F51: Toronto | G51: Non-Profit | H51: Distributor | I51: D. Smith | J51: Accessories | K51: ACC-6348 | L51: 1454.11 | M51: 2629.75 | N51: 0.292 | O51: 8 | P51: =IF(M51>0,"Valid") -> Valid | Q51: =ABS(M51) -> 2629.75 | R51: =IF(N51>30%,"Excess") -> FALSE | S51: =IF(R51="Excess",30%,N51) -> 0.292 | T51: =(C51-B51) -> 16 | U51: =IF(C51<B51,B51+7,C51) -> 45618 | V51: =(U51-B51) -> 16 | W51: =(Q51*O51*(100-S51)) -> 2097656.9 | X51: =(Q51*O51) -> 21038 | Y51: =W51-X51 -> 2076618.9 | Z51: =Y51/W51 -> 0.98997071 | AA51: Nov-2024 | AB51: ="Q"&ROUNDUP(MONTH(B51)/3,0)&"-"&YEAR(B51) -> Q4-2024 | AC51: =D51&" → "&E51&" → "&F51 -> Americas → Canada → Toronto | AD51: =IF(OR(J51="Laptops",J51="Phones"),"Devices",IF(OR(J51="Monitors",J51="Printers"),"Peripherals","Support")) -> Support | AE51: =IF(B51<=PERCENTILE($B$2:$B$632,0.33),"Low",IF(B51<=PERCENTILE($B$2:$B$632,0.66),"Medium","High")) -> High | AF51: =UPPER(TRIM(CLEAN(SUBSTITUTE(E51,CHAR(160),"")))) -> CANADA | AG51: =_xlfn.MINIFS($B$2:$B$633,$AF$2:$AF$633,AF51) -> 44928 | AH51: =TEXT(AG51,"MMM-YYYY") -> Jan-2023 | AI51: =EOMONTH(B51,0) -> 45626 | AJ51: =IF(V51<=7,1,0) -> 0 | AK51: =IF(N51>20%,1,0) -> 1 | AL51: =MIN(N51,'Scenario Modelling'!$B$2) -> 0.25 | AM51: =L51*(1+'Scenario Modelling'!$B$3) -> 1672.2265 | AN51: =O51*(1+'Scenario Modelling'!$B$4) -> 9.6 | AO51: =AN51*M51*(1-AL51) -> 18934.2 | AP51: =(M51*(1-AL51)-AM51)*AN51 -> 2880.8256
A52: ORD-2024-260775 | B52: 45582 | C52: 45602 | D52: Asia | E52: India | F52: Bengaluru | G52: Enterprise | H52: Distributor | I52: O. Wang | J52: Monitors | K52: MON-4330 | L52: 72.94 | M52: 106.3 | N52: 0.295 | O52: 8 | P52: =IF(M52>0,"Valid") -> Valid | Q52: =ABS(M52) -> 106.3 | R52: =IF(N52>30%,"Excess") -> FALSE | S52: =IF(R52="Excess",30%,N52) -> 0.295 | T52: =(C52-B52) -> 20 | U52: =IF(C52<B52,B52+7,C52) -> 45602 | V52: =(U52-B52) -> 20 | W52: =(Q52*O52*(100-S52)) -> 84789.132 | X52: =(Q52*O52) -> 850.4 | Y52: =W52-X52 -> 83938.732 | Z52: =Y52/W52 -> 0.98997041 | AA52: Oct-2024 | AB52: ="Q"&ROUNDUP(MONTH(B52)/3,0)&"-"&YEAR(B52) -> Q4-2024 | AC52: =D52&" → "&E52&" → "&F52 -> Asia → India → Bengaluru | AD52: =IF(OR(J52="Laptops",J52="Phones"),"Devices",IF(OR(J52="Monitors",J52="Printers"),"Peripherals","Support")) -> Peripherals | AE52: =IF(B52<=PERCENTILE($B$2:$B$632,0.33),"Low",IF(B52<=PERCENTILE($B$2:$B$632,0.66),"Medium","High")) -> Medium | AF52: =UPPER(TRIM(CLEAN(SUBSTITUTE(E52,CHAR(160),"")))) -> INDIA | AG52: 44955 | AH52: =TEXT(AG52,"MMM-YYYY") -> Jan-2023 | AI52: =EOMONTH(B52,0) -> 45596 | AJ52: =IF(V52<=7,1,0) -> 0 | AK52: =IF(N52>20%,1,0) -> 1 | AL52: =MIN(N52,'Scenario Modelling'!$B$2) -> 0.25 | AM52: =L52*(1+'Scenario Modelling'!$B$3) -> 83.881 | AN52: =O52*(1+'Scenario Modelling'!$B$4) -> 9.6 | AO52: =AN52*M52*(1-AL52) -> 765.36 | AP52: =(M52*(1-AL52)-AM52)*AN52 -> -39.8976
A53: ORD-2023-419187 | B53: 45016 | C53: 45021 | D53: Africa | E53: Kenya | F53: Nakuru | G53: Education | H53: Marketplace | I53: B. Chen | J53: Laptops | K53: LAP-7819 | L53: 533.26 | M53: 385.72 | N53: 0 | O53: 15 | P53: =IF(M53>0,"Valid") -> Valid | Q53: =ABS(M53) -> 385.72 | R53: =IF(N53>30%,"Excess") -> FALSE | S53: =IF(R53="Excess",30%,N53) -> 0 | T53: =(C53-B53) -> 5 | U53: =IF(C53<B53,B53+7,C53) -> 45021 | V53: =(U53-B53) -> 5 | W53: =(Q53*O53*(100-S53)) -> 578580 | X53: =(Q53*O53) -> 5785.8 | Y53: =W53-X53 -> 572794.2 | Z53: =Y53/W53 -> 0.99 | AA53: Mar-2023 | AB53: ="Q"&ROUNDUP(MONTH(B53)/3,0)&"-"&YEAR(B53) -> Q1-2023 | AC53: =D53&" → "&E53&" → "&F53 -> Africa → Kenya → Nakuru | AD53: =IF(OR(J53="Laptops",J53="Phones"),"Devices",IF(OR(J53="Monitors",J53="Printers"),"Peripherals","Support")) -> Devices | AE53: =IF(B53<=PERCENTILE($B$2:$B$632,0.33),"Low",AF24:AF24 IF(B53<=PERCENTILE($B$2:$B$632,0.66),"Medium","High")) -> Low | AF53: =UPPER(TRIM(CLEAN(SUBSTITUTE(E53,CHAR(160),"")))) -> KENYA | AG53: 44946 | AH53: =TEXT(AG53,"MMM-YYYY") -> Jan-2023 | AI53: =EOMONTH(B53,0) -> 45016 | AJ53: =IF(V53<=7,1,0) -> 1 | AK53: =IF(N53>20%,1,0) -> 0 | AL53: =MIN(N53,'Scenario Modelling'!$B$2) -> 0 | AM53: =L53*(1+'Scenario Modelling'!$B$3) -> 613.249 | AN53: =O53*(1+'Scenario Modelling'!$B$4) -> 18 | AO53: =AN53*M53*(1-AL53) -> 6942.96 | AP53: =(M53*(1-AL53)-AM53)*AN53 -> -4095.522
A54: ORD-2025-578007 | B54: 45678 | C54: 45704 | D54: Europe | E54: France | F54: Lyon | G54: Corporate | H54: Distributor | I54: O. Wang | J54: Laptops | K54: LAP-3779 | L54: 204.11 | M54: 236.87 | N54: 0.182 | O54: 13 | P54: =IF(M54>0,"Valid") -> Valid | Q54: =ABS(M54) -> 236.87 | R54: =IF(N54>30%,"Excess") -> FALSE | S54: =IF(R54="Excess",30%,N54) -> 0.182 | T54: =(C54-B54) -> 26 | U54: =IF(C54<B54,B54+7,C54) -> 45704 | V54: =(U54-B54) -> 26 | W54: =(Q54*O54*(100-S54)) -> 307370.57 | X54: =(Q54*O54) -> 3079.31 | Y54: =W54-X54 -> 304291.26 | Z54: =Y54/W54 -> 0.98998177 | AA54: Jan-2025 | AB54: ="Q"&ROUNDUP(MONTH(B54)/3,0)&"-"&YEAR(B54) -> Q1-2025 | AC54: =D54&" → "&E54&" → "&F54 -> Europe → France → Lyon | AD54: =IF(OR(J54="Laptops",J54="Phones"),"Devices",IF(OR(J54="Monitors",J54="Printers"),"Peripherals","Support")) -> Devices | AE54: =IF(B54<=PERCENTILE($B$2:$B$632,0.33),"Low",IF(B54<=PERCENTILE($B$2:$B$632,0.66),"Medium","High")) -> High | AF54: =UPPER(TRIM(CLEAN(SUBSTITUTE(E54,CHAR(160),"")))) -> FRANCE | AG54: 44936 | AH54: =TEXT(AG54,"MMM-YYYY") -> Jan-2023 | AI54: =EOMONTH(B54,0) -> 45688 | AJ54: =IF(V54<=7,1,0) -> 0 | AK54: =IF(N54>20%,1,0) -> 0 | AL54: =MIN(N54,'Scenario Modelling'!$B$2) -> 0.182 | AM54: =L54*(1+'Scenario Modelling'!$B$3) -> 234.7265 | AN54: =O54*(1+'Scenario Modelling'!$B$4) -> 15.6 | AO54: =AN54*M54*(1-AL54) -> 3022.6507 | AP54: =(M54*(1-AL54)-AM54)*AN54 -> -639.0827
A55: ORD-2023-235230 | B55: 45168 | C55: 45170 | D55: Europe | E55: Germany | F55: Munich | G55: Corporate | H55: Direct | I55: N. Brown | J55: Networking | K55: NET-9989 | L55: 44.42 | M55: 41.9 | N55: 0.144 | O55: 6 | P55: =IF(M55>0,"Valid") -> Valid | Q55: =ABS(M55) -> 41.9 | R55: =IF(N55>30%,"Excess") -> FALSE | S55: =IF(R55="Excess",30%,N55) -> 0.144 | T55: =(C55-B55) -> 2 | U55: =IF(C55<B55,B55+7,C55) -> 45170 | V55: =(U55-B55) -> 2 | W55: =(Q55*O55*(100-S55)) -> 25103.798 | X55: =(Q55*O55) -> 251.4 | Y55: =W55-X55 -> 24852.398 | Z55: =Y55/W55 -> 0.98998558 | AA55: Aug-2023 | AB55: ="Q"&ROUNDUP(MONTH(B55)/3,0)&"-"&YEAR(B55) -> Q3-2023 | AC55: =D55&" → "&E55&" → "&F55 -> Europe → Germany → Munich | AD55: =IF(OR(J55="Laptops",J55="Phones"),"Devices",IF(OR(J55="Monitors",J55="Printers"),"Peripherals","Support")) -> Support | AE55: =IF(B55<=PERCENTILE($B$2:$B$632,0.33),"Low",IF(B55<=PERCENTILE($B$2:$B$632,0.66),"Medium","High")) -> Low | AF55: =UPPER(TRIM(CLEAN(SUBSTITUTE(E55,CHAR(160),"")))) -> GERMANY | AG55: 44948 | AH55: =TEXT(AG55,"MMM-YYYY") -> Jan-2023 | AI55: =EOMONTH(B55,0) -> 45169 | AJ55: =IF(V55<=7,1,0) -> 1 | AK55: =IF(N55>20%,1,0) -> 0 | AL55: =MIN(N55,'Scenario Modelling'!$B$2) -> 0.144 | AM55: =L55*(1+'Scenario Modelling'!$B$3) -> 51.083 | AN55: =O55*(1+'Scenario Modelling'!$B$4) -> 7.2 | AO55: =AN55*M55*(1-AL55) -> 258.23808 | AP55: =(M55*(1-AL55)-AM55)*AN55 -> -109.55952
A56: ORD-2025-765220 | B56: 45753 | C56: 45777 | D56: Americas | E56: Brazil | F56: Brasília | G56: Education | H56: Online | I56: K. Singh | J56: Monitors | K56: MON-4925 | L56: 855.78 | M56: 977.38 | N56: 0.147 | O56: 38 | P56: =IF(M56>0,"Valid") -> Valid | Q56: =ABS(M56) -> 977.38 | R56: =IF(N56>30%,"Excess") -> FALSE | S56: =IF(R56="Excess",30%,N56) -> 0.147 | T56: =(C56-B56) -> 24 | U56: =IF(C56<B56,B56+7,C56) -> 45777 | V56: =(U56-B56) -> 24 | W56: =(Q56*O56*(100-S56)) -> 3708584.4 | X56: =(Q56*O56) -> 37140.44 | Y56: =W56-X56 -> 3671443.9 | Z56: =Y56/W56 -> 0.98998528 | AA56: Apr-2025 | AB56: ="Q"&ROUNDUP(MONTH(B56)/3,0)&"-"&YEAR(B56) -> Q2-2025 | AC56: =D56&" → "&E56&" → "&F56 -> Americas → Brazil → Brasília | AD56: =IF(OR(J56="Laptops",J56="Phones"),"Devices",IF(OR(J56="Monitors",J56="Printers"),"Peripherals","Support")) -> Peripherals | AE56: =IF(B56<=PERCENTILE($B$2:$B$632,0.33),"Low",IF(B56<=PERCENTILE($B$2:$B$632,0.66),"Medium","High")) -> High | AF56: =UPPER(TRIM(CLEAN(SUBSTITUTE(E56,CHAR(160),"")))) -> BRAZIL | AG56: =_xlfn.MINIFS($B$2:$B$633,$AF$2:$AF$633,AF56) -> 44955 | AH56: =TEXT(AG56,"MMM-YYYY") -> Jan-2023 | AI56: =EOMONTH(B56,0) -> 45777 | AJ56: =IF(V56<=7,1,0) -> 0 | AK56: =IF(N56>20%,1,0) -> 0 | AL56: =MIN(N56,'Scenario Modelling'!$B$2) -> 0.147 | AM56: =L56*(1+'Scenario Modelling'!$B$3) -> 984.147 | AN56: =O56*(1+'Scenario Modelling'!$B$4) -> 45.6 | AO56: =AN56*M56*(1-AL56) -> 38016.954 | AP56: =(M56*(1-AL56)-AM56)*AN56 -> -6860.1488
A57: ORD-2025-931538 | B57: 45697 | C57: 45717 | D57: Americas | E57: Brazil | F57: São Paulo | G57: Corporate | H57: Distributor | I57: B. Chen | J57: Laptops | K57: LAP-6989 | L57: 1154.64 | M57: 2794.13 | N57: 0.035 | O57: 11 | P57: =IF(M57>0,"Valid") -> Valid | Q57: =ABS(M57) -> 2794.13 | R57: =IF(N57>30%,"Excess") -> FALSE | S57: =IF(R57="Excess",30%,N57) -> 0.035 | T57: =(C57-B57) -> 20 | U57: =IF(C57<B57,B57+7,C57) -> 45717 | V57: =(U57-B57) -> 20 | W57: =(Q57*O57*(100-S57)) -> 3072467.3 | X57: =(Q57*O57) -> 30735.43 | Y57: =W57-X57 -> 3041731.8 | Z57: =Y57/W57 -> 0.9899965 | AA57: Feb-2025 | AB57: ="Q"&ROUNDUP(MONTH(B57)/3,0)&"-"&YEAR(B57) -> Q1-2025 | AC57: =D57&" → "&E57&" → "&F57 -> Americas → Brazil → São Paulo | AD57: =IF(OR(J57="Laptops",J57="Phones"),"Devices",IF(OR(J57="Monitors",J57="Printers"),"Peripherals","Support")) -> Devices | AE57: =IF(B57<=PERCENTILE($B$2:$B$632,0.33),"Low",IF(B57<=PERCENTILE($B$2:$B$632,0.66),"Medium","High")) -> High | AF57: =UPPER(TRIM(CLEAN(SUBSTITUTE(E57,CHAR(160),"")))) -> BRAZIL | AG57: =_xlfn.MINIFS($B$2:$B$633,$AF$2:$AF$633,AF57) -> 44955 | AH57: =TEXT(AG57,"MMM-YYYY") -> Jan-2023 | AI57: =EOMONTH(B57,0) -> 45716 | AJ57: =IF(V57<=7,1,0) -> 0 | AK57: =IF(N57>20%,1,0) -> 0 | AL57: =MIN(N57,'Scenario Modelling'!$B$2) -> 0.035 | AM57: =L57*(1+'Scenario Modelling'!$B$3) -> 1327.836 | AN57: =O57*(1+'Scenario Modelling'!$B$4) -> 13.2 | AO57: =AN57*M57*(1-AL57) -> 35591.628 | AP57: =(M57*(1-AL57)-AM57)*AN57 -> 18064.193
A58: ORD-2024-289089 | B58: 45643 | C58: 45644 | D58: Europe | E58: Germany | F58: Munich | G58: Education | H58: Retail | I58: L. Okafor | J58: Accessories | K58: ACC-5780 | L58: 346.82 | M58: 701.95 | N58: 0.147 | O58: 8 | P58: =IF(M58>0,"Valid") -> Valid | Q58: =ABS(M58) -> 701.95 | R58: =IF(N58>30%,"Excess") -> FALSE | S58: =IF(R58="Excess",30%,N58) -> 0.147 | T58: =(C58-B58) -> 1 | U58: =IF(C58<B58,B58+7,C58) -> 45644 | V58: =(U58-B58) -> 1 | W58: =(Q58*O58*(100-S58)) -> 560734.51 | X58: =(Q58*O58) -> 5615.6 | Y58: =W58-X58 -> 555118.91 | Z58: =Y58/W58 -> 0.98998528 | AA58: Dec-2024 | AB58: ="Q"&ROUNDUP(MONTH(B58)/3,0)&"-"&YEAR(B58) -> Q4-2024 | AC58: =D58&" → "&E58&" → "&F58 -> Europe → Germany → Munich | AD58: =IF(OR(J58="Laptops",J58="Phones"),"Devices",IF(OR(J58="Monitors",J58="Printers"),"Peripherals","Support")) -> Support | AE58: =IF(B58<=PERCENTILE($B$2:$B$632,0.33),"Low",IF(B58<=PERCENTILE($B$2:$B$632,0.66),"Medium","High")) -> High | AF58: =UPPER(TRIM(CLEAN(SUBSTITUTE(E58,CHAR(160),"")))) -> GERMANY | AG58: 44948 | AH58: =TEXT(AG58,"MMM-YYYY") -> Jan-2023 | AI58: =EOMONTH(B58,0) -> 45657 | AJ58: =IF(V58<=7,1,0) -> 1 | AK58: =IF(N58>20%,1,0) -> 0 | AL58: =MIN(N58,'Scenario Modelling'!$B$2) -> 0.147 | AM58: =L58*(1+'Scenario Modelling'!$B$3) -> 398.843 | AN58: =O58*(1+'Scenario Modelling'!$B$4) -> 9.6 | AO58: =AN58*M58*(1-AL58) -> 5748.1282 | AP58: =(M58*(1-AL58)-AM58)*AN58 -> 1919.2354
A59: ORD-2025-639542 | B59: 45817 | C59: 45826 | D59: Europe | E59: France | F59: Marseille | G59: Small Business | H59: Marketplace | I59: H. Kim | J59: Accessories | K59: ACC-1770 | L59: 1225.5 | M59: -5.27 | N59: 0.075 | O59: 56 | P59: =IF(M59>0,"Valid") -> FALSE | Q59: =ABS(M59) -> 5.27 | R59: =IF(N59>30%,"Excess") -> FALSE | S59: =IF(R59="Excess",30%,N59) -> 0.075 | T59: =(C59-B59) -> 9 | U59: =IF(C59<B59,B59+7,C59) -> 45826 | V59: =(U59-B59) -> 9 | W59: =(Q59*O59*(100-S59)) -> 29489.866 | X59: =(Q59*O59) -> 295.12 | Y59: =W59-X59 -> 29194.746 | Z59: =Y59/W59 -> 0.98999249 | AA59: Jun-2025 | AB59: ="Q"&ROUNDUP(MONTH(B59)/3,0)&"-"&YEAR(B59) -> Q2-2025 | AC59: =D59&" → "&E59&" → "&F59 -> Europe → France → Marseille | AD59: =IF(OR(J59="Laptops",J59="Phones"),"Devices",IF(OR(J59="Monitors",J59="Printers"),"Peripherals","Support")) -> Support | AE59: =IF(B59<=PERCENTILE($B$2:$B$632,0.33),"Low",IF(B59<=PERCENTILE($B$2:$B$632,0.66),"Medium","High")) -> High | AF59: =UPPER(TRIM(CLEAN(SUBSTITUTE(E59,CHAR(160),"")))) -> FRANCE | AG59: 44936 | AH59: =TEXT(AG59,"MMM-YYYY") -> Jan-2023 | AI59: =EOMONTH(B59,0) -> 45838 | AJ59: =IF(V59<=7,1,0) -> 0 | AK59: =IF(N59>20%,1,0) -> 0 | AL59: =MIN(N59,'Scenario Modelling'!$B$2) -> 0.075 | AM59: =L59*(1+'Scenario Modelling'!$B$3) -> 1409.325 | AN59: =O59*(1+'Scenario Modelling'!$B$4) -> 67.2 | AO59: =AN59*M59*(1-AL59) -> -327.5832 | AP59: =(M59*(1-AL59)-AM59)*AN59 -> -95034.223
A60: ORD-2025-762301 | B60: 45779 | C60: 45790 | D60: Africa | E60: Kenya | F60: Nakuru | G60: Small Business | H60: Online | I60: A. Patel | J60: Accessories | K60: ACC-2252 | L60: 1057.6 | M60: 1437.06 | N60: 0.205 | O60: 4 | P60: =IF(M60>0,"Valid") -> Valid | Q60: =ABS(M60) -> 1437.06 | R60: =IF(N60>30%,"Excess") -> FALSE | S60: =IF(R60="Excess",30%,N60) -> 0.205 | T60: =(C60-B60) -> 11 | U60: =IF(C60<B60,B60+7,C60) -> 45790 | V60: =(U60-B60) -> 11 | W60: =(Q60*O60*(100-S60)) -> 573645.61 | X60: =(Q60*O60) -> 5748.24 | Y60: =W60-X60 -> 567897.37 | Z60: =Y60/W60 -> 0.98997946 | AA60: May-2025 | AB60: ="Q"&ROUNDUP(MONTH(B60)/3,0)&"-"&YEAR(B60) -> Q2-2025 | AC60: =D60&" → "&E60&" → "&F60 -> Africa → Kenya → Nakuru | AD60: =IF(OR(J60="Laptops",J60="Phones"),"Devices",IF(OR(J60="Monitors",J60="Printers"),"Peripherals","Support")) -> Support | AE60: =IF(B60<=PERCENTILE($B$2:$B$632,0.33),"Low",IF(B60<=PERCENTILE($B$2:$B$632,0.66),"Medium","High")) -> High | AF60: =UPPER(TRIM(CLEAN(SUBSTITUTE(E60,CHAR(160),"")))) -> KENYA | AG60: 44946 | AH60: =TEXT(AG60,"MMM-YYYY") -> Jan-2023 | AI60: =EOMONTH(B60,0) -> 45808 | AJ60: =IF(V60<=7,1,0) -> 0 | AK60: =IF(N60>20%,1,0) -> 1 | AL60: =MIN(N60,'Scenario Modelling'!$B$2) -> 0.205 | AM60: =L60*(1+'Scenario Modelling'!$B$3) -> 1216.24 | AN60: =O60*(1+'Scenario Modelling'!$B$4) -> 4.8 | AO60: =AN60*M60*(1-AL60) -> 5483.821 | AP60: =(M60*(1-AL60)-AM60)*AN60 -> -354.13104
A61: ORD-2024-906395 | B61: 45361 | C61: 45391 | D61: Europe | E61: France | F61: Lyon | G61: Corporate | H61: Direct | I61: I. Johnson | J61: Components | K61: CMP-8002 | L61: 1176.56 | M61: 1911.89 | N61: 0.119 | O61: 20 | P61: =IF(M61>0,"Valid") -> Valid | Q61: =ABS(M61) -> 1911.89 | R61: =IF(N61>30%,"Excess") -> FALSE | S61: =IF(R61="Excess",30%,N61) -> 0.119 | T61: =(C61-B61) -> 30 | U61: =IF(C61<B61,B61+7,C61) -> 45391 | V61: =(U61-B61) -> 30 | W61: =(Q61*O61*(100-S61)) -> 3819229.7 | X61: =(Q61*O61) -> 38237.8 | Y61: =W61-X61 -> 3780991.9 | Z61: =Y61/W61 -> 0.98998809 | AA61: Mar-2024 | AB61: ="Q"&ROUNDUP(MONTH(B61)/3,0)&"-"&YEAR(B61) -> Q1-2024 | AC61: =D61&" → "&E61&" → "&F61 -> Europe → France → Lyon | AD61: =IF(OR(J61="Laptops",J61="Phones"),"Devices",IF(OR(J61="Monitors",J61="Printers"),"Peripherals","Support")) -> Support | AE61: =IF(B61<=PERCENTILE($B$2:$B$632,0.33),"Low",IF(B61<=PERCENTILE($B$2:$B$632,0.66),"Medium","High")) -> Medium | AF61: =UPPER(TRIM(CLEAN(SUBSTITUTE(E61,CHAR(160),"")))) -> FRANCE | AG61: 44936 | AH61: =TEXT(AG61,"MMM-YYYY") -> Jan-2023 | AI61: =EOMONTH(B61,0) -> 45382 | AJ61: =IF(V61<=7,1,0) -> 0 | AK61: =IF(N61>20%,1,0) -> 0 | AL61: =MIN(N61,'Scenario Modelling'!$B$2) -> 0.119 | AM61: =L61*(1+'Scenario Modelling'!$B$3) -> 1353.044 | AN61: =O61*(1+'Scenario Modelling'!$B$4) -> 24 | AO61: =AN61*M61*(1-AL61) -> 40425.002 | AP61: =(M61*(1-AL61)-AM61)*AN61 -> 7951.9462
A62: ORD-2025-779574 | B62: 45910 | C62: 45912 | D62: Asia | E62: Japan | F62: Tokyo | G62: Consumer | H62: Online | I62: O. Wang | J62: Components | K62: CMP-6971 | L62: 1470.15 | M62: 2593.78 | N62: 0.11 | O62: 12 | P62: =IF(M62>0,"Valid") -> Valid | Q62: =ABS(M62) -> 2593.78 | R62: =IF(N62>30%,"Excess") -> FALSE | S62: =IF(R62="Excess",30%,N62) -> 0.11 | T62: =(C62-B62) -> 2 | U62: =IF(C62<B62,B62+7,C62) -> 45912 | V62: =(U62-B62) -> 2 | W62: =(Q62*O62*(100-S62)) -> 3109112.2 | X62: =(Q62*O62) -> 31125.36 | Y62: =W62-X62 -> 3077986.9 | Z62: =Y62/W62 -> 0.98998899 | AA62: Sep-2025 | AB62: ="Q"&ROUNDUP(MONTH(B62)/3,0)&"-"&YEAR(B62) -> Q3-2025 | AC62: =D62&" → "&E62&" → "&F62 -> Asia → Japan → Tokyo | AD62: =IF(OR(J62="Laptops",J62="Phones"),"Devices",IF(OR(J62="Monitors",J62="Printers"),"Peripherals","Support")) -> Support | AE62: =IF(B62<=PERCENTILE($B$2:$B$632,0.33),"Low",IF(B62<=PERCENTILE($B$2:$B$632,0.66),"Medium","High")) -> High | AF62: =UPPER(TRIM(CLEAN(SUBSTITUTE(E62,CHAR(160),"")))) -> JAPAN | AG62: 44988 | AH62: =TEXT(AG62,"MMM-YYYY") -> Mar-2023 | AI62: =EOMONTH(B62,0) -> 45930 | AJ62: =IF(V62<=7,1,0) -> 1 | AK62: =IF(N62>20%,1,0) -> 0 | AL62: =MIN(N62,'Scenario Modelling'!$B$2) -> 0.11 | AM62: =L62*(1+'Scenario Modelling'!$B$3) -> 1690.6725 | AN62: =O62*(1+'Scenario Modelling'!$B$4) -> 14.4 | AO62: =AN62*M62*(1-AL62) -> 33241.884 | AP62: =(M62*(1-AL62)-AM62)*AN62 -> 8896.2005
A63: ORD-2025-526650 | B63: 45774 | C63: 45802 | D63: Europe | E63: France | F63: Paris | G63: Small Business | H63: Marketplace | I63: I. Johnson | J63: Phones | K63: PHN-8350 | L63: 603.45 | M63: 1244.08 | N63: 0.2 | O63: 11 | P63: =IF(M63>0,"Valid") -> Valid | Q63: =ABS(M63) -> 1244.08 | R63: =IF(N63>30%,"Excess") -> FALSE | S63: =IF(R63="Excess",30%,N63) -> 0.2 | T63: =(C63-B63) -> 28 | U63: =IF(C63<B63,B63+7,C63) -> 45802 | V63: =(U63-B63) -> 28 | W63: =(Q63*O63*(100-S63)) -> 1365751 | X63: =(Q63*O63) -> 13684.88 | Y63: =W63-X63 -> 1352066.1 | Z63: =Y63/W63 -> 0.98997996 | AA63: Apr-2025 | AB63: ="Q"&ROUNDUP(MONTH(B63)/3,0)&"-"&YEAR(B63) -> Q2-2025 | AC63: =D63&" → "&E63&" → "&F63 -> Europe → France → Paris | AD63: =IF(OR(J63="Laptops",J63="Phones"),"Devices",IF(OR(J63="Monitors",J63="Printers"),"Peripherals","Support")) -> Devices | AE63: =IF(B63<=PERCENTILE($B$2:$B$632,0.33),"Low",IF(B63<=PERCENTILE($B$2:$B$632,0.66),"Medium","High")) -> High | AF63: =UPPER(TRIM(CLEAN(SUBSTITUTE(E63,CHAR(160),"")))) -> FRANCE | AG63: 44936 | AH63: =TEXT(AG63,"MMM-YYYY") -> Jan-2023 | AI63: =EOMONTH(B63,0) -> 45777 | AJ63: =IF(V63<=7,1,0) -> 0 | AK63: =IF(N63>20%,1,0) -> 0 | AL63: =MIN(N63,'Scenario Modelling'!$B$2) -> 0.2 | AM63: =L63*(1+'Scenario Modelling'!$B$3) -> 693.9675 | AN63: =O63*(1+'Scenario Modelling'!$B$4) -> 13.2 | AO63: =AN63*M63*(1-AL63) -> 13137.485 | AP63: =(M63*(1-AL63)-AM63)*AN63 -> 3977.1138
A64: ORD-2024-247979 | B64: 45598 | C64: 45614 | D64: Asia | E64: India | F64: Mumbai | G64: Small Business | H64: Distributor | I64: O. Wang | J64: Monitors | K64: MON-5188 | L64: 1233.58 | M64: 1912.51 | N64: 0.255 | O64: 51 | P64: =IF(M64>0,"Valid") -> Valid | Q64: =ABS(M64) -> 1912.51 | R64: =IF(N64>30%,"Excess") -> FALSE | S64: =IF(R64="Excess",30%,N64) -> 0.255 | T64: =(C64-B64) -> 16 | U64: =IF(C64<B64,B64+7,C64) -> 45614 | V64: =(U64-B64) -> 16 | W64: =(Q64*O64*(100-S64)) -> 9728928.8 | X64: =(Q64*O64) -> 97538.01 | Y64: =W64-X64 -> 9631390.8 | Z64: =Y64/W64 -> 0.98997443 | AA64: Nov-2024 | AB64: ="Q"&ROUNDUP(MONTH(B64)/3,0)&"-"&YEAR(B64) -> Q4-2024 | AC64: =D64&" → "&E64&" → "&F64 -> Asia → India → Mumbai | AD64: =IF(OR(J64="Laptops",J64="Phones"),"Devices",IF(OR(J64="Monitors",J64="Printers"),"Peripherals","Support")) -> Peripherals | AE64: =IF(B64<=PERCENTILE($B$2:$B$632,0.33),"Low",IF(B64<=PERCENTILE($B$2:$B$632,0.66),"Medium","High")) -> High | AF64: =UPPER(TRIM(CLEAN(SUBSTITUTE(E64,CHAR(160),"")))) -> INDIA | AG64: 44955 | AH64: =TEXT(AG64,"MMM-YYYY") -> Jan-2023 | AI64: =EOMONTH(B64,0) -> 45626 | AJ64: =IF(V64<=7,1,0) -> 0 | AK64: =IF(N64>20%,1,0) -> 1 | AL64: =MIN(N64,'Scenario Modelling'!$B$2) -> 0.25 | AM64: =L64*(1+'Scenario Modelling'!$B$3) -> 1418.617 | AN64: =O64*(1+'Scenario Modelling'!$B$4) -> 61.2 | AO64: =AN64*M64*(1-AL64) -> 87784.209 | AP64: =(M64*(1-AL64)-AM64)*AN64 -> 964.8486
A65: ORD-2023-480975 | B65: 44972 | C65: 44983 | D65: Africa | E65: South Africa | F65: Johannesburg | G65: Non-Profit | H65: Retail | I65: K. Singh | J65: Laptops | K65: LAP-3393 | L65: 498.5 | M65: 755.87 | N65: 0.13 | O65: 40 | P65: =IF(M65>0,"Valid") -> Valid | Q65: =ABS(M65) -> 755.87 | R65: =IF(N65>30%,"Excess") -> FALSE | S65: =IF(R65="Excess",30%,N65) -> 0.13 | T65: =(C65-B65) -> 11 | U65: =IF(C65<B65,B65+7,C65) -> 44983 | V65: =(U65-B65) -> 11 | W65: =(Q65*O65*(100-S65)) -> 3019549.5 | X65: =(Q65*O65) -> 30234.8 | Y65: =W65-X65 -> 2989314.7 | Z65: =Y65/W65 -> 0.98998698 | AA65: Feb-2023 | AB65: ="Q"&ROUNDUP(MONTH(B65)/3,0)&"-"&YEAR(B65) -> Q1-2023 | AC65: =D65&" → "&E65&" → "&F65 -> Africa → South Africa → Johannesburg | AD65: =IF(OR(J65="Laptops",J65="Phones"),"Devices",IF(OR(J65="Monitors",J65="Printers"),"Peripherals","Support")) -> Devices | AE65: =IF(B65<=PERCENTILE($B$2:$B$632,0.33),"Low",IF(B65<=PERCENTILE($B$2:$B$632,0.66),"Medium","High")) -> Low | AF65: =UPPER(TRIM(CLEAN(SUBSTITUTE(E65,CHAR(160),"")))) -> SOUTH AFRICA | AG65: =_xlfn.MINIFS($B$2:$B$633,$AF$2:$AF$633,AF65) -> 44933 | AH65: =TEXT(AG65,"MMM-YYYY") -> Jan-2023 | AI65: =EOMONTH(B65,0) -> 44985 | AJ65: =IF(V65<=7,1,0) -> 0 | AK65: =IF(N65>20%,1,0) -> 0 | AL65: =MIN(N65,'Scenario Modelling'!$B$2) -> 0.13 | AM65: =L65*(1+'Scenario Modelling'!$B$3) -> 573.275 | AN65: =O65*(1+'Scenario Modelling'!$B$4) -> 48 | AO65: =AN65*M65*(1-AL65) -> 31565.131 | AP65: =(M65*(1-AL65)-AM65)*AN65 -> 4047.9312
A66: ORD-2023-239789 | B66: 45263 | C66: 45286 | D66: Americas | E66: Brazil | F66: Rio de Janeiro | G66: Education | H66: Retail | I66: O. Wang | J66: Phones | K66: PHN-4644 | L66: 1303.11 | M66: 1145.67 | N66: 0.184 | O66: 13 | P66: =IF(M66>0,"Valid") -> Valid | Q66: =ABS(M66) -> 1145.67 | R66: =IF(N66>30%,"Excess") -> FALSE | S66: =IF(R66="Excess",30%,N66) -> 0.184 | T66: =(C66-B66) -> 23 | U66: =IF(C66<B66,B66+7,C66) -> 45286 | V66: =(U66-B66) -> 23 | W66: =(Q66*O66*(100-S66)) -> 1486630.6 | X66: =(Q66*O66) -> 14893.71 | Y66: =W66-X66 -> 1471736.8 | Z66: =Y66/W66 -> 0.98998157 | AA66: Dec-2023 | AB66: ="Q"&ROUNDUP(MONTH(B66)/3,0)&"-"&YEAR(B66) -> Q4-2023 | AC66: =D66&" → "&E66&" → "&F66 -> Americas → Brazil → Rio de Janeiro | AD66: =IF(OR(J66="Laptops",J66="Phones"),"Devices",IF(OR(J66="Monitors",J66="Printers"),"Peripherals","Support")) -> Devices | AE66: =IF(B66<=PERCENTILE($B$2:$B$632,0.33),"Low",IF(B66<=PERCENTILE($B$2:$B$632,0.66),"Medium","High")) -> Low | AF66: =UPPER(TRIM(CLEAN(SUBSTITUTE(E66,CHAR(160),"")))) -> BRAZIL | AG66: =_xlfn.MINIFS($B$2:$B$633,$AF$2:$AF$633,AF66) -> 44955 | AH66: =TEXT(AG66,"MMM-YYYY") -> Jan-2023 | AI66: =EOMONTH(B66,0) -> 45291 | AJ66: =IF(V66<=7,1,0) -> 0 | AK66: =IF(N66>20%,1,0) -> 0 | AL66: =MIN(N66,'Scenario Modelling'!$B$2) -> 0.184 | AM66: =L66*(1+'Scenario Modelling'!$B$3) -> 1498.5765 | AN66: =O66*(1+'Scenario Modelling'!$B$4) -> 15.6 | AO66: =AN66*M66*(1-AL66) -> 14583.921 | AP66: =(M66*(1-AL66)-AM66)*AN66 -> -8793.8726
A67: ORD-2023-548874 | B67: 45004 | C67: 45025 | D67: Europe | E67: United Kingdom | F67: Manchester | G67: Consumer | H67: Retail | I67: L. Okafor | J67: Accessories | K67: ACC-9150 | L67: 1082.17 | M67: 1234.1 | N67: 0.189 | O67: 16 | P67: =IF(M67>0,"Valid") -> Valid | Q67: =ABS(M67) -> 1234.1 | R67: =IF(N67>30%,"Excess") -> FALSE | S67: =IF(R67="Excess",30%,N67) -> 0.189 | T67: =(C67-B67) -> 21 | U67: =IF(C67<B67,B67+7,C67) -> 45025 | V67: =(U67-B67) -> 21 | W67: =(Q67*O67*(100-S67)) -> 1970828.1 | X67: =(Q67*O67) -> 19745.6 | Y67: =W67-X67 -> 1951082.5 | Z67: =Y67/W67 -> 0.98998106 | AA67: Mar-2023 | AB67: ="Q"&ROUNDUP(MONTH(B67)/3,0)&"-"&YEAR(B67) -> Q1-2023 | AC67: =D67&" → "&E67&" → "&F67 -> Europe → United Kingdom → Manchester | AD67: =IF(OR(J67="Laptops",J67="Phones"),"Devices",IF(OR(J67="Monitors",J67="Printers"),"Peripherals","Support")) -> Support | AE67: =IF(B67<=PERCENTILE($B$2:$B$632,0.33),"Low",IF(B67<=PERCENTILE($B$2:$B$632,0.66),"Medium","High")) -> Low | AF67: =UPPER(TRIM(CLEAN(SUBSTITUTE(E67,CHAR(160),"")))) -> UNITED KINGDOM | AG67: 44945 | AH67: =TEXT(AG67,"MMM-YYYY") -> Jan-2023 | AI67: =EOMONTH(B67,0) -> 45016 | AJ67: =IF(V67<=7,1,0) -> 0 | AK67: =IF(N67>20%,1,0) -> 0 | AL67: =MIN(N67,'Scenario Modelling'!$B$2) -> 0.189 | AM67: =L67*(1+'Scenario Modelling'!$B$3) -> 1244.4955 | AN67: =O67*(1+'Scenario Modelling'!$B$4) -> 19.2 | AO67: =AN67*M67*(1-AL67) -> 19216.418 | AP67: =(M67*(1-AL67)-AM67)*AN67 -> -4677.8957
A68: ORD-2024-347736 | B68: 45434 | C68: 45449 | D68: Asia | E68: Japan | F68: Nagoya | G68: Corporate | H68: Distributor | I68: C. Otieno | J68: Monitors | K68: MON-6870 | L68: 673.88 | M68: 1228.01 | N68: 0.105 | O68: 13 | P68: =IF(M68>0,"Valid") -> Valid | Q68: =ABS(M68) -> 1228.01 | R68: =IF(N68>30%,"Excess") -> FALSE | S68: =IF(R68="Excess",30%,N68) -> 0.105 | T68: =(C68-B68) -> 15 | U68: =IF(C68<B68,B68+7,C68) -> 45449 | V68: =(U68-B68) -> 15 | W68: =(Q68*O68*(100-S68)) -> 1594736.8 | X68: =(Q68*O68) -> 15964.13 | Y68: =W68-X68 -> 1578772.6 | Z68: =Y68/W68 -> 0.98998949 | AA68: May-2024 | AB68: ="Q"&ROUNDUP(MONTH(B68)/3,0)&"-"&YEAR(B68) -> Q2-2024 | AC68: =D68&" → "&E68&" → "&F68 -> Asia → Japan → Nagoya | AD68: =IF(OR(J68="Laptops",J68="Phones"),"Devices",IF(OR(J68="Monitors",J68="Printers"),"Peripherals","Support")) -> Peripherals | AE68: =IF(B68<=PERCENTILE($B$2:$B$632,0.33),"Low",IF(B68<=PERCENTILE($B$2:$B$632,0.66),"Medium","High")) -> Medium | AF68: =UPPER(TRIM(CLEAN(SUBSTITUTE(E68,CHAR(160),"")))) -> JAPAN | AG68: 44988 | AH68: =TEXT(AG68,"MMM-YYYY") -> Mar-2023 | AI68: =EOMONTH(B68,0) -> 45443 | AJ68: =IF(V68<=7,1,0) -> 0 | AK68: =IF(N68>20%,1,0) -> 0 | AL68: =MIN(N68,'Scenario Modelling'!$B$2) -> 0.105 | AM68: =L68*(1+'Scenario Modelling'!$B$3) -> 774.962 | AN68: =O68*(1+'Scenario Modelling'!$B$4) -> 15.6 | AO68: =AN68*M68*(1-AL68) -> 17145.476 | AP68: =(M68*(1-AL68)-AM68)*AN68 -> 5056.0684
A69: ORD-2023-749324 | B69: 45157 | C69: 45176 | D69: Africa | E69: South Africa | F69: Johannesburg | G69: Enterprise | H69: Retail | I69: D. Smith | J69: Monitors | K69: MON-2296 | L69: 494.61 | M69: 605.23 | N69: 0.204 | O69: 18 | P69: =IF(M69>0,"Valid") -> Valid | Q69: =ABS(M69) -> 605.23 | R69: =IF(N69>30%,"Excess") -> FALSE | S69: =IF(R69="Excess",30%,N69) -> 0.204 | T69: =(C69-B69) -> 19 | U69: =IF(C69<B69,B69+7,C69) -> 45176 | V69: =(U69-B69) -> 19 | W69: =(Q69*O69*(100-S69)) -> 1087191.6 | X69: =(Q69*O69) -> 10894.14 | Y69: =W69-X69 -> 1076297.5 | Z69: =Y69/W69 -> 0.98997956 | AA69: Aug-2023 | AB69: ="Q"&ROUNDUP(MONTH(B69)/3,0)&"-"&YEAR(B69) -> Q3-2023 | AC69: =D69&" → "&E69&" → "&F69 -> Africa → South Africa → Johannesburg | AD69: =IF(OR(J69="Laptops",J69="Phones"),"Devices",IF(OR(J69="Monitors",J69="Printers"),"Peripherals","Support")) -> Peripherals | AE69: =IF(B69<=PERCENTILE($B$2:$B$632,0.33),"Low",IF(B69<=PERCENTILE($B$2:$B$632,0.66),"Medium","High")) -> Low | AF69: =UPPER(TRIM(CLEAN(SUBSTITUTE(E69,CHAR(160),"")))) -> SOUTH AFRICA | AG69: =_xlfn.MINIFS($B$2:$B$633,$AF$2:$AF$633,AF69) -> 44933 | AH69: =TEXT(AG69,"MMM-YYYY") -> Jan-2023 | AI69: =EOMONTH(B69,0) -> 45169 | AJ69: =IF(V69<=7,1,0) -> 0 | AK69: =IF(N69>20%,1,0) -> 1 | AL69: =MIN(N69,'Scenario Modelling'!$B$2) -> 0.204 | AM69: =L69*(1+'Scenario Modelling'!$B$3) -> 568.8015 | AN69: =O69*(1+'Scenario Modelling'!$B$4) -> 21.6 | AO69: =AN69*M69*(1-AL69) -> 10406.083 | AP69: =(M69*(1-AL69)-AM69)*AN69 -> -1880.0299
A70: ORD-2023-809913 | B70: 45037 | C70: 45056 | D70: Asia | E70: China | F70: Shanghai | G70: Corporate | H70: Retail | I70: A. Patel | J70: Components | K70: CMP-7371 | L70: 882.33 | M70: 1880.15 | N70: 0.05 | O70: 5 | P70: =IF(M70>0,"Valid") -> Valid | Q70: =ABS(M70) -> 1880.15 | R70: =IF(N70>30%,"Excess") -> FALSE | S70: =IF(R70="Excess",30%,N70) -> 0.05 | T70: =(C70-B70) -> 19 | U70: =IF(C70<B70,B70+7,C70) -> 45056 | V70: =(U70-B70) -> 19 | W70: =(Q70*O70*(100-S70)) -> 939604.96 | X70: =(Q70*O70) -> 9400.75 | Y70: =W70-X70 -> 930204.21 | Z70: =Y70/W70 -> 0.989995 | AA70: Apr-2023 | AB70: ="Q"&ROUNDUP(MONTH(B70)/3,0)&"-"&YEAR(B70) -> Q2-2023 | AC70: =D70&" → "&E70&" → "&F70 -> Asia → China → Shanghai | AD70: =IF(OR(J70="Laptops",J70="Phones"),"Devices",IF(OR(J70="Monitors",J70="Printers"),"Peripherals","Support")) -> Support | AE70: =IF(B70<=PERCENTILE($B$2:$B$632,0.33),"Low",IF(B70<=PERCENTILE($B$2:$B$632,0.66),"Medium","High")) -> Low | AF70: =UPPER(TRIM(CLEAN(SUBSTITUTE(E70,CHAR(160),"")))) -> CHINA | AG70: =_xlfn.MINIFS($B$2:$B$633,$AF$2:$AF$633,AF70) -> 44938 | AH70: =TEXT(AG70,"MMM-YYYY") -> Jan-2023 | AI70: =EOMONTH(B70,0) -> 45046 | AJ70: =IF(V70<=7,1,0) -> 0 | AK70: =IF(N70>20%,1,0) -> 0 | AL70: =MIN(N70,'Scenario Modelling'!$B$2) -> 0.05 | AM70: =L70*(1+'Scenario Modelling'!$B$3) -> 1014.6795 | AN70: =O70*(1+'Scenario Modelling'!$B$4) -> 6 | AO70: =AN70*M70*(1-AL70) -> 10716.855 | AP70: =(M70*(1-AL70)-AM70)*AN70 -> 4628.778
A71: ORD-2024-287210 | B71: 45369 | C71: 45372 | D71: Europe | E71: Germany | F71: Munich | G71: Small Business | H71: Online | I71: M. Rossi | J71: Accessories | K71: ACC-2761 | L71: 910.63 | M71: 1269.4 | N71: 0.068 | O71: 9 | P71: =IF(M71>0,"Valid") -> Valid | Q71: =ABS(M71) -> 1269.4 | R71: =IF(N71>30%,"Excess") -> FALSE | S71: =IF(R71="Excess",30%,N71) -> 0.068 | T71: =(C71-B71) -> 3 | U71: =IF(C71<B71,B71+7,C71) -> 45372 | V71: =(U71-B71) -> 3 | W71: =(Q71*O71*(100-S71)) -> 1141683.1 | X71: =(Q71*O71) -> 11424.6 | Y71: =W71-X71 -> 1130258.5 | Z71: =Y71/W71 -> 0.9899932 | AA71: Mar-2024 | AB71: ="Q"&ROUNDUP(MONTH(B71)/3,0)&"-"&YEAR(B71) -> Q1-2024 | AC71: =D71&" → "&E71&" → "&F71 -> Europe → Germany → Munich | AD71: =IF(OR(J71="Laptops",J71="Phones"),"Devices",IF(OR(J71="Monitors",J71="Printers"),"Peripherals","Support")) -> Support | AE71: =IF(B71<=PERCENTILE($B$2:$B$632,0.33),"Low",IF(B71<=PERCENTILE($B$2:$B$632,0.66),"Medium","High")) -> Medium | AF71: =UPPER(TRIM(CLEAN(SUBSTITUTE(E71,CHAR(160),"")))) -> GERMANY | AG71: 44948 | AH71: =TEXT(AG71,"MMM-YYYY") -> Jan-2023 | AI71: =EOMONTH(B71,0) -> 45382 | AJ71: =IF(V71<=7,1,0) -> 1 | AK71: =IF(N71>20%,1,0) -> 0 | AL71: =MIN(N71,'Scenario Modelling'!$B$2) -> 0.068 | AM71: =L71*(1+'Scenario Modelling'!$B$3) -> 1047.2245 | AN71: =O71*(1+'Scenario Modelling'!$B$4) -> 10.8 | AO71: =AN71*M71*(1-AL71) -> 12777.273 | AP71: =(M71*(1-AL71)-AM71)*AN71 -> 1467.248
A72: ORD-2025-640677 | B72: 45756 | C72: 45783 | D72: Americas | E72: Brazil | F72: Brasília | G72: Enterprise | H72: Marketplace | I72: F. Müller | J72: Laptops | K72: LAP-4517 | L72: 264.19 | M72: 620.93 | N72: 0.142 | O72: 12 | P72: =IF(M72>0,"Valid") -> Valid | Q72: =ABS(M72) -> 620.93 | R72: =IF(N72>30%,"Excess") -> FALSE | S72: =IF(R72="Excess",30%,N72) -> 0.142 | T72: =(C72-B72) -> 27 | U72: =IF(C72<B72,B72+7,C72) -> 45783 | V72: =(U72-B72) -> 27 | W72: =(Q72*O72*(100-S72)) -> 744057.94 | X72: =(Q72*O72) -> 7451.16 | Y72: =W72-X72 -> 736606.78 | Z72: =Y72/W72 -> 0.98998578 | AA72: Apr-2025 | AB72: ="Q"&ROUNDUP(MONTH(B72)/3,0)&"-"&YEAR(B72) -> Q2-2025 | AC72: =D72&" → "&E72&" → "&F72 -> Americas → Brazil → Brasília | AD72: =IF(OR(J72="Laptops",J72="Phones"),"Devices",IF(OR(J72="Monitors",J72="Printers"),"Peripherals","Support")) -> Devices | AE72: =IF(B72<=PERCENTILE($B$2:$B$632,0.33),"Low",IF(B72<=PERCENTILE($B$2:$B$632,0.66),"Medium","High")) -> High | AF72: =UPPER(TRIM(CLEAN(SUBSTITUTE(E72,CHAR(160),"")))) -> BRAZIL | AG72: =_xlfn.MINIFS($B$2:$B$633,$AF$2:$AF$633,AF72) -> 44955 | AH72: =TEXT(AG72,"MMM-YYYY") -> Jan-2023 | AI72: =EOMONTH(B72,0) -> 45777 | AJ72: =IF(V72<=7,1,0) -> 0 | AK72: =IF(N72>20%,1,0) -> 0 | AL72: =MIN(N72,'Scenario Modelling'!$B$2) -> 0.142 | AM72: =L72*(1+'Scenario Modelling'!$B$3) -> 303.8185 | AN72: =O72*(1+'Scenario Modelling'!$B$4) -> 14.4 | AO72: =AN72*M72*(1-AL72) -> 7671.7143 | AP72: =(M72*(1-AL72)-AM72)*AN72 -> 3296.7279
A73: ORD-2024-939873 | B73: 45394 | C73: 45419 | D73: Africa | E73: South Africa | F73: Johannesburg | G73: Education | H73: Distributor | I73: A. Patel | J73: Laptops | K73: LAP-8489 | L73: 1376.51 | M73: 1455.91 | N73: 0.185 | O73: 17 | P73: =IF(M73>0,"Valid") -> Valid | Q73: =ABS(M73) -> 1455.91 | R73: =IF(N73>30%,"Excess") -> FALSE | S73: =IF(R73="Excess",30%,N73) -> 0.185 | T73: =(C73-B73) -> 25 | U73: =IF(C73<B73,B73+7,C73) -> 45419 | V73: =(U73-B73) -> 25 | W73: =(Q73*O73*(100-S73)) -> 2470468.2 | X73: =(Q73*O73) -> 24750.47 | Y73: =W73-X73 -> 2445717.7 | Z73: =Y73/W73 -> 0.98998147 | AA73: Apr-2024 | AB73: ="Q"&ROUNDUP(MONTH(B73)/3,0)&"-"&YEAR(B73) -> Q2-2024 | AC73: =D73&" → "&E73&" → "&F73 -> Africa → South Africa → Johannesburg | AD73: =IF(OR(J73="Laptops",J73="Phones"),"Devices",IF(OR(J73="Monitors",J73="Printers"),"Peripherals","Support")) -> Devices | AE73: =IF(B73<=PERCENTILE($B$2:$B$632,0.33),"Low",IF(B73<=PERCENTILE($B$2:$B$632,0.66),"Medium","High")) -> Medium | AF73: =UPPER(TRIM(CLEAN(SUBSTITUTE(E73,CHAR(160),"")))) -> SOUTH AFRICA | AG73: =_xlfn.MINIFS($B$2:$B$633,$AF$2:$AF$633,AF73) -> 44933 | AH73: =TEXT(AG73,"MMM-YYYY") -> Jan-2023 | AI73: =EOMONTH(B73,0) -> 45412 | AJ73: =IF(V73<=7,1,0) -> 0 | AK73: =IF(N73>20%,1,0) -> 0 | AL73: =MIN(N73,'Scenario Modelling'!$B$2) -> 0.185 | AM73: =L73*(1+'Scenario Modelling'!$B$3) -> 1582.9865 | AN73: =O73*(1+'Scenario Modelling'!$B$4) -> 20.4 | AO73: =AN73*M73*(1-AL73) -> 24205.96 | AP73: =(M73*(1-AL73)-AM73)*AN73 -> -8086.9649
A74: ORD-2024-800947 | B74: 45641 | C74: 45646 | D74: Asia | E74: China | F74: Shenzhen | G74: Small Business | H74: Direct | I74: J. Njeri | J74: Networking | K74: NET-1846 | L74: 717.55 | M74: 546.43 | N74: 0.047 | O74: 18 | P74: =IF(M74>0,"Valid") -> Valid | Q74: =ABS(M74) -> 546.43 | R74: =IF(N74>30%,"Excess") -> FALSE | S74: =IF(R74="Excess",30%,N74) -> 0.047 | T74: =(C74-B74) -> 5 | U74: =IF(C74<B74,B74+7,C74) -> 45646 | V74: =(U74-B74) -> 5 | W74: =(Q74*O74*(100-S74)) -> 983111.72 | X74: =(Q74*O74) -> 9835.74 | Y74: =W74-X74 -> 973275.98 | Z74: =Y74/W74 -> 0.9899953 | AA74: Dec-2024 | AB74: ="Q"&ROUNDUP(MONTH(B74)/3,0)&"-"&YEAR(B74) -> Q4-2024 | AC74: =D74&" → "&E74&" → "&F74 -> Asia → China → Shenzhen | AD74: =IF(OR(J74="Laptops",J74="Phones"),"Devices",IF(OR(J74="Monitors",J74="Printers"),"Peripherals","Support")) -> Support | AE74: =IF(B74<=PERCENTILE($B$2:$B$632,0.33),"Low",IF(B74<=PERCENTILE($B$2:$B$632,0.66),"Medium","High")) -> High | AF74: =UPPER(TRIM(CLEAN(SUBSTITUTE(E74,CHAR(160),"")))) -> CHINA | AG74: =_xlfn.MINIFS($B$2:$B$633,$AF$2:$AF$633,AF74) -> 44938 | AH74: =TEXT(AG74,"MMM-YYYY") -> Jan-2023 | AI74: =EOMONTH(B74,0) -> 45657 | AJ74: =IF(V74<=7,1,0) -> 1 | AK74: =IF(N74>20%,1,0) -> 0 | AL74: =MIN(N74,'Scenario Modelling'!$B$2) -> 0.047 | AM74: =L74*(1+'Scenario Modelling'!$B$3) -> 825.1825 | AN74: =O74*(1+'Scenario Modelling'!$B$4) -> 21.6 | AO74: =AN74*M74*(1-AL74) -> 11248.152 | AP74: =(M74*(1-AL74)-AM74)*AN74 -> -6575.7897
A75: ORD-2023-382272 | B75: 45066 | C75: 45064 | D75: Africa | E75: South Africa | F75: Durban | G75: Corporate | H75: Distributor | I75: A. Patel | J75: Components | K75: CMP-5208 | L75: 917.88 | M75: 1347.92 | N75: 0.343 | O75: 5 | P75: =IF(M75>0,"Valid") -> Valid | Q75: =ABS(M75) -> 1347.92 | R75: =IF(N75>30%,"Excess") -> Excess | S75: =IF(R75="Excess",30%,N75) -> 0.3 | T75: =(C75-B75) -> -2 | U75: =IF(C75<B75,B75+7,C75) -> 45073 | V75: =(U75-B75) -> 7 | W75: =(Q75*O75*(100-S75)) -> 671938.12 | X75: =(Q75*O75) -> 6739.6 | Y75: =W75-X75 -> 665198.52 | Z75: =Y75/W75 -> 0.98996991 | AA75: May-2023 | AB75: ="Q"&ROUNDUP(MONTH(B75)/3,0)&"-"&YEAR(B75) -> Q2-2023 | AC75: =D75&" → "&E75&" → "&F75 -> Africa → South Africa → Durban | AD75: =IF(OR(J75="Laptops",J75="Phones"),"Devices",IF(OR(J75="Monitors",J75="Printers"),"Peripherals","Support")) -> Support | AE75: =IF(B75<=PERCENTILE($B$2:$B$632,0.33),"Low",IF(B75<=PERCENTILE($B$2:$B$632,0.66),"Medium","High")) -> Low | AF75: =UPPER(TRIM(CLEAN(SUBSTITUTE(E75,CHAR(160),"")))) -> SOUTH AFRICA | AG75: =_xlfn.MINIFS($B$2:$B$633,$AF$2:$AF$633,AF75) -> 44933 | AH75: =TEXT(AG75,"MMM-YYYY") -> Jan-2023 | AI75: =EOMONTH(B75,0) -> 45077 | AJ75: =IF(V75<=7,1,0) -> 1 | AK75: =IF(N75>20%,1,0) -> 1 | AL75: =MIN(N75,'Scenario Modelling'!$B$2) -> 0.25 | AM75: =L75*(1+'Scenario Modelling'!$B$3) -> 1055.562 | AN75: =O75*(1+'Scenario Modelling'!$B$4) -> 6 | AO75: =AN75*M75*(1-AL75) -> 6065.64 | AP75: =(M75*(1-AL75)-AM75)*AN75 -> -267.732
A76: ORD-2023-722117 | B76: 45187 | C76: 45207 | D76: Asia | E76: India | F76: Delhi | G76: Small Business | H76: Direct | I76: B. Chen | J76: Components | K76: CMP-1009 | L76: 825.64 | M76: 1108.43 | N76: 0.114 | O76: 7 | P76: =IF(M76>0,"Valid") -> Valid | Q76: =ABS(M76) -> 1108.43 | R76: =IF(N76>30%,"Excess") -> FALSE | S76: =IF(R76="Excess",30%,N76) -> 0.114 | T76: =(C76-B76) -> 20 | U76: =IF(C76<B76,B76+7,C76) -> 45207 | V76: =(U76-B76) -> 20 | W76: =(Q76*O76*(100-S76)) -> 775016.47 | X76: =(Q76*O76) -> 7759.01 | Y76: =W76-X76 -> 767257.46 | Z76: =Y76/W76 -> 0.98998859 | AA76: Sep-2023 | AB76: ="Q"&ROUNDUP(MONTH(B76)/3,0)&"-"&YEAR(B76) -> Q3-2023 | AC76: =D76&" → "&E76&" → "&F76 -> Asia → India → Delhi | AD76: =IF(OR(J76="Laptops",J76="Phones"),"Devices",IF(OR(J76="Monitors",J76="Printers"),"Peripherals","Support")) -> Support | AE76: =IF(B76<=PERCENTILE($B$2:$B$632,0.33),"Low",IF(B76<=PERCENTILE($B$2:$B$632,0.66),"Medium","High")) -> Low | AF76: =UPPER(TRIM(CLEAN(SUBSTITUTE(E76,CHAR(160),"")))) -> INDIA | AG76: 44955 | AH76: =TEXT(AG76,"MMM-YYYY") -> Jan-2023 | AI76: =EOMONTH(B76,0) -> 45199 | AJ76: =IF(V76<=7,1,0) -> 0 | AK76: =IF(N76>20%,1,0) -> 0 | AL76: =MIN(N76,'Scenario Modelling'!$B$2) -> 0.114 | AM76: =L76*(1+'Scenario Modelling'!$B$3) -> 949.486 | AN76: =O76*(1+'Scenario Modelling'!$B$4) -> 8.4 | AO76: =AN76*M76*(1-AL76) -> 8249.3794 | AP76: =(M76*(1-AL76)-AM76)*AN76 -> 273.69703
A77: ORD-2024-446699 | B77: 45532 | C77: 45560 | D77: Americas | E77: Brazil | F77: Rio de Janeiro | G77: Non-Profit | H77: Online | I77: Unidentified sales person | J77: Accessories | K77: ACC-4490 | L77: 1394.65 | M77: 3144.1 | N77: 0.134 | O77: 13 | P77: =IF(M77>0,"Valid") -> Valid | Q77: =ABS(M77) -> 3144.1 | R77: =IF(N77>30%,"Excess") -> FALSE | S77: =IF(R77="Excess",30%,N77) -> 0.134 | T77: =(C77-B77) -> 28 | U77: =IF(C77<B77,B77+7,C77) -> 45560 | V77: =(U77-B77) -> 28 | W77: =(Q77*O77*(100-S77)) -> 4081853 | X77: =(Q77*O77) -> 40873.3 | Y77: =W77-X77 -> 4040979.7 | Z77: =Y77/W77 -> 0.98998658 | AA77: Aug-2024 | AB77: ="Q"&ROUNDUP(MONTH(B77)/3,0)&"-"&YEAR(B77) -> Q3-2024 | AC77: =D77&" → "&E77&" → "&F77 -> Americas → Brazil → Rio de Janeiro | AD77: =IF(OR(J77="Laptops",J77="Phones"),"Devices",IF(OR(J77="Monitors",J77="Printers"),"Peripherals","Support")) -> Support | AE77: =IF(B77<=PERCENTILE($B$2:$B$632,0.33),"Low",IF(B77<=PERCENTILE($B$2:$B$632,0.66),"Medium","High")) -> Medium | AF77: =UPPER(TRIM(CLEAN(SUBSTITUTE(E77,CHAR(160),"")))) -> BRAZIL | AG77: =_xlfn.MINIFS($B$2:$B$633,$AF$2:$AF$633,AF77) -> 44955 | AH77: =TEXT(AG77,"MMM-YYYY") -> Jan-2023 | AI77: =EOMONTH(B77,0) -> 45535 | AJ77: =IF(V77<=7,1,0) -> 0 | AK77: =IF(N77>20%,1,0) -> 0 | AL77: =MIN(N77,'Scenario Modelling'!$B$2) -> 0.134 | AM77: =L77*(1+'Scenario Modelling'!$B$3) -> 1603.8475 | AN77: =O77*(1+'Scenario Modelling'!$B$4) -> 15.6 | AO77: =AN77*M77*(1-AL77) -> 42475.533 | AP77: =(M77*(1-AL77)-AM77)*AN77 -> 17455.512
A78: ORD-2024-451005 | B78: 45473 | C78: 45471 | D78: Americas | E78: Brazil | F78: Rio de Janeiro | G78: Small Business | H78: Direct | I78: L. Okafor | J78: Accessories | K78: ACC-9162 | L78: 1112.98 | M78: 2095.73 | N78: 0.072 | O78: 17 | P78: =IF(M78>0,"Valid") -> Valid | Q78: =ABS(M78) -> 2095.73 | R78: =IF(N78>30%,"Excess") -> FALSE | S78: =IF(R78="Excess",30%,N78) -> 0.072 | T78: =(C78-B78) -> -2 | U78: =IF(C78<B78,B78+7,C78) -> 45480 | V78: =(U78-B78) -> 7 | W78: =(Q78*O78*(100-S78)) -> 3560175.8 | X78: =(Q78*O78) -> 35627.41 | Y78: =W78-X78 -> 3524548.4 | Z78: =Y78/W78 -> 0.98999279 | AA78: Jun-2024 | AB78: ="Q"&ROUNDUP(MONTH(B78)/3,0)&"-"&YEAR(B78) -> Q2-2024 | AC78: =D78&" → "&E78&" → "&F78 -> Americas → Brazil → Rio de Janeiro | AD78: =IF(OR(J78="Laptops",J78="Phones"),"Devices",IF(OR(J78="Monitors",J78="Printers"),"Peripherals","Support")) -> Support | AE78: =IF(B78<=PERCENTILE($B$2:$B$632,0.33),"Low",IF(B78<=PERCENTILE($B$2:$B$632,0.66),"Medium","High")) -> Medium | AF78: =UPPER(TRIM(CLEAN(SUBSTITUTE(E78,CHAR(160),"")))) -> BRAZIL | AG78: =_xlfn.MINIFS($B$2:$B$633,$AF$2:$AF$633,AF78) -> 44955 | AH78: =TEXT(AG78,"MMM-YYYY") -> Jan-2023 | AI78: =EOMONTH(B78,0) -> 45473 | AJ78: =IF(V78<=7,1,0) -> 1 | AK78: =IF(N78>20%,1,0) -> 0 | AL78: =MIN(N78,'Scenario Modelling'!$B$2) -> 0.072 | AM78: =L78*(1+'Scenario Modelling'!$B$3) -> 1279.927 | AN78: =O78*(1+'Scenario Modelling'!$B$4) -> 20.4 | AO78: =AN78*M78*(1-AL78) -> 39674.684 | AP78: =(M78*(1-AL78)-AM78)*AN78 -> 13564.173
A79: ORD-2023-290279 | B79: 45091 | C79: 45093 | D79: Europe | E79: United Kingdom | F79: Manchester | G79: Non-Profit | H79: Direct | I79: K. Singh | J79: Components | K79: CMP-5820 | L79: 357.36 | M79: 703.62 | N79: 0.257 | O79: 20 | P79: =IF(M79>0,"Valid") -> Valid | Q79: =ABS(M79) -> 703.62 | R79: =IF(N79>30%,"Excess") -> FALSE | S79: =IF(R79="Excess",30%,N79) -> 0.257 | T79: =(C79-B79) -> 2 | U79: =IF(C79<B79,B79+7,C79) -> 45093 | V79: =(U79-B79) -> 2 | W79: =(Q79*O79*(100-S79)) -> 1403623.4 | X79: =(Q79*O79) -> 14072.4 | Y79: =W79-X79 -> 1389551 | Z79: =Y79/W79 -> 0.98997423 | AA79: Jun-2023 | AB79: ="Q"&ROUNDUP(MONTH(B79)/3,0)&"-"&YEAR(B79) -> Q2-2023 | AC79: =D79&" → "&E79&" → "&F79 -> Europe → United Kingdom → Manchester | AD79: =IF(OR(J79="Laptops",J79="Phones"),"Devices",IF(OR(J79="Monitors",J79="Printers"),"Peripherals","Support")) -> Support | AE79: =IF(B79<=PERCENTILE($B$2:$B$632,0.33),"Low",IF(B79<=PERCENTILE($B$2:$B$632,0.66),"Medium","High")) -> Low | AF79: =UPPER(TRIM(CLEAN(SUBSTITUTE(E79,CHAR(160),"")))) -> UNITED KINGDOM | AG79: 44945 | AH79: =TEXT(AG79,"MMM-YYYY") -> Jan-2023 | AI79: =EOMONTH(B79,0) -> 45107 | AJ79: =IF(V79<=7,1,0) -> 1 | AK79: =IF(N79>20%,1,0) -> 1 | AL79: =MIN(N79,'Scenario Modelling'!$B$2) -> 0.25 | AM79: =L79*(1+'Scenario Modelling'!$B$3) -> 410.964 | AN79: =O79*(1+'Scenario Modelling'!$B$4) -> 24 | AO79: =AN79*M79*(1-AL79) -> 12665.16 | AP79: =(M79*(1-AL79)-AM79)*AN79 -> 2802.024
A80: ORD-2024-192263 | B80: 45617 | C80: 45647 | D80: Europe | E80: France | F80: Marseille | G80: Small Business | H80: Direct | I80: I. Johnson | J80: Monitors | K80: MON-7943 | L80: 1122.68 | M80: 1997.19 | N80: 0.186 | O80: 3 | P80: =IF(M80>0,"Valid") -> Valid | Q80: =ABS(M80) -> 1997.19 | R80: =IF(N80>30%,"Excess") -> FALSE | S80: =IF(R80="Excess",30%,N80) -> 0.186 | T80: =(C80-B80) -> 30 | U80: =IF(C80<B80,B80+7,C80) -> 45647 | V80: =(U80-B80) -> 30 | W80: =(Q80*O80*(100-S80)) -> 598042.57 | X80: =(Q80*O80) -> 5991.57 | Y80: =W80-X80 -> 592051 | Z80: =Y80/W80 -> 0.98998137 | AA80: Nov-2024 | AB80: ="Q"&ROUNDUP(MONTH(B80)/3,0)&"-"&YEAR(B80) -> Q4-2024 | AC80: =D80&" → "&E80&" → "&F80 -> Europe → France → Marseille | AD80: =IF(OR(J80="Laptops",J80="Phones"),"Devices",IF(OR(J80="Monitors",J80="Printers"),"Peripherals","Support")) -> Peripherals | AE80: =IF(B80<=PERCENTILE($B$2:$B$632,0.33),"Low",IF(B80<=PERCENTILE($B$2:$B$632,0.66),"Medium","High")) -> High | AF80: =UPPER(TRIM(CLEAN(SUBSTITUTE(E80,CHAR(160),"")))) -> FRANCE | AG80: 44936 | AH80: =TEXT(AG80,"MMM-YYYY") -> Jan-2023 | AI80: =EOMONTH(B80,0) -> 45626 | AJ80: =IF(V80<=7,1,0) -> 0 | AK80: =IF(N80>20%,1,0) -> 0 | AL80: =MIN(N80,'Scenario Modelling'!$B$2) -> 0.186 | AM80: =L80*(1+'Scenario Modelling'!$B$3) -> 1291.082 | AN80: =O80*(1+'Scenario Modelling'!$B$4) -> 3.6 | AO80: =AN80*M80*(1-AL80) -> 5852.5656 | AP80: =(M80*(1-AL80)-AM80)*AN80 -> 1204.6704
A81: ORD-2023-159379 | B81: 44965 | C81: 44968 | D81: Africa | E81: South Africa | F81: Cape Town | G81: Corporate | H81: Direct | I81: M. Rossi | J81: Networking | K81: NET-5018 | L81: 1410.05 | M81: 2763.95 | N81: 0.161 | O81: 26 | P81: =IF(M81>0,"Valid") -> Valid | Q81: =ABS(M81) -> 2763.95 | R81: =IF(N81>30%,"Excess") -> FALSE | S81: =IF(R81="Excess",30%,N81) -> 0.161 | T81: =(C81-B81) -> 3 | U81: =IF(C81<B81,B81+7,C81) -> 44968 | V81: =(U81-B81) -> 3 | W81: =(Q81*O81*(100-S81)) -> 7174700.1 | X81: =(Q81*O81) -> 71862.7 | Y81: =W81-X81 -> 7102837.4 | Z81: =Y81/W81 -> 0.98998387 | AA81: Feb-2023 | AB81: ="Q"&ROUNDUP(MONTH(B81)/3,0)&"-"&YEAR(B81) -> Q1-2023 | AC81: =D81&" → "&E81&" → "&F81 -> Africa → South Africa → Cape Town | AD81: =IF(OR(J81="Laptops",J81="Phones"),"Devices",IF(OR(J81="Monitors",J81="Printers"),"Peripherals","Support")) -> Support | AE81: =IF(B81<=PERCENTILE($B$2:$B$632,0.33),"Low",IF(B81<=PERCENTILE($B$2:$B$632,0.66),"Medium","High")) -> Low | AF81: =UPPER(TRIM(CLEAN(SUBSTITUTE(E81,CHAR(160),"")))) -> SOUTH AFRICA | AG81: =_xlfn.MINIFS($B$2:$B$633,$AF$2:$AF$633,AF81) -> 44933 | AH81: =TEXT(AG81,"MMM-YYYY") -> Jan-2023 | AI81: =EOMONTH(B81,0) -> 44985 | AJ81: =IF(V81<=7,1,0) -> 1 | AK81: =IF(N81>20%,1,0) -> 0 | AL81: =MIN(N81,'Scenario Modelling'!$B$2) -> 0.161 | AM81: =L81*(1+'Scenario Modelling'!$B$3) -> 1621.5575 | AN81: =O81*(1+'Scenario Modelling'!$B$4) -> 31.2 | AO81: =AN81*M81*(1-AL81) -> 72351.366 | AP81: =(M81*(1-AL81)-AM81)*AN81 -> 21758.772
A82: ORD-2023-343322 | B82: 45157 | C82: 45181 | D82: Americas | E82: Canada | F82: Vancouver | G82: Enterprise | H82: Retail | I82: I. Johnson | J82: Printers | K82: PRN-9669 | L82: 1183.95 | M82: 1503.53 | N82: 0.241 | O82: 16 | P82: =IF(M82>0,"Valid") -> Valid | Q82: =ABS(M82) -> 1503.53 | R82: =IF(N82>30%,"Excess") -> FALSE | S82: =IF(R82="Excess",30%,N82) -> 0.241 | T82: =(C82-B82) -> 24 | U82: =IF(C82<B82,B82+7,C82) -> 45181 | V82: =(U82-B82) -> 24 | W82: =(Q82*O82*(100-S82)) -> 2399850.4 | X82: =(Q82*O82) -> 24056.48 | Y82: =W82-X82 -> 2375793.9 | Z82: =Y82/W82 -> 0.98997584 | AA82: Aug-2023 | AB82: ="Q"&ROUNDUP(MONTH(B82)/3,0)&"-"&YEAR(B82) -> Q3-2023 | AC82: =D82&" → "&E82&" → "&F82 -> Americas → Canada → Vancouver | AD82: =IF(OR(J82="Laptops",J82="Phones"),"Devices",IF(OR(J82="Monitors",J82="Printers"),"Peripherals","Support")) -> Peripherals | AE82: =IF(B82<=PERCENTILE($B$2:$B$632,0.33),"Low",IF(B82<=PERCENTILE($B$2:$B$632,0.66),"Medium","High")) -> Low | AF82: =UPPER(TRIM(CLEAN(SUBSTITUTE(E82,CHAR(160),"")))) -> CANADA | AG82: =_xlfn.MINIFS($B$2:$B$633,$AF$2:$AF$633,AF82) -> 44928 | AH82: =TEXT(AG82,"MMM-YYYY") -> Jan-2023 | AI82: =EOMONTH(B82,0) -> 45169 | AJ82: =IF(V82<=7,1,0) -> 0 | AK82: =IF(N82>20%,1,0) -> 1 | AL82: =MIN(N82,'Scenario Modelling'!$B$2) -> 0.241 | AM82: =L82*(1+'Scenario Modelling'!$B$3) -> 1361.5425 | AN82: =O82*(1+'Scenario Modelling'!$B$4) -> 19.2 | AO82: =AN82*M82*(1-AL82) -> 21910.642 | AP82: =(M82*(1-AL82)-AM82)*AN82 -> -4230.974
A83: ORD-2025-114382 | B83: 45791 | C83: 45801 | D83: Europe | E83: France | F83: Paris | G83: Small Business | H83: Marketplace | I83: K. Singh | J83: Components | K83: CMP-2865 | L83: 170.39 | M83: 388.04 | N83: 0.084 | O83: 15 | P83: =IF(M83>0,"Valid") -> Valid | Q83: =ABS(M83) -> 388.04 | R83: =IF(N83>30%,"Excess") -> FALSE | S83: =IF(R83="Excess",30%,N83) -> 0.084 | T83: =(C83-B83) -> 10 | U83: =IF(C83<B83,B83+7,C83) -> 45801 | V83: =(U83-B83) -> 10 | W83: =(Q83*O83*(100-S83)) -> 581571.07 | X83: =(Q83*O83) -> 5820.6 | Y83: =W83-X83 -> 575750.47 | Z83: =Y83/W83 -> 0.98999159 | AA83: May-2025 | AB83: ="Q"&ROUNDUP(MONTH(B83)/3,0)&"-"&YEAR(B83) -> Q2-2025 | AC83: =D83&" → "&E83&" → "&F83 -> Europe → France → Paris | AD83: =IF(OR(J83="Laptops",J83="Phones"),"Devices",IF(OR(J83="Monitors",J83="Printers"),"Peripherals","Support")) -> Support | AE83: =IF(B83<=PERCENTILE($B$2:$B$632,0.33),"Low",IF(B83<=PERCENTILE($B$2:$B$632,0.66),"Medium","High")) -> High | AF83: =UPPER(TRIM(CLEAN(SUBSTITUTE(E83,CHAR(160),"")))) -> FRANCE | AG83: 44936 | AH83: =TEXT(AG83,"MMM-YYYY") -> Jan-2023 | AI83: =EOMONTH(B83,0) -> 45808 | AJ83: =IF(V83<=7,1,0) -> 0 | AK83: =IF(N83>20%,1,0) -> 0 | AL83: =MIN(N83,'Scenario Modelling'!$B$2) -> 0.084 | AM83: =L83*(1+'Scenario Modelling'!$B$3) -> 195.9485 | AN83: =O83*(1+'Scenario Modelling'!$B$4) -> 18 | AO83: =AN83*M83*(1-AL83) -> 6398.0035 | AP83: =(M83*(1-AL83)-AM83)*AN83 -> 2870.9305
A84: ORD-2025-488349 | B84: 45770 | C84: 45769 | D84: Americas | E84: USA | F84: San Francisco | G84: Non-Profit | H84: Distributor | I84: D. Smith | J84: Monitors | K84: MON-3371 | L84: 23.24 | M84: 44.57 | N84: 0.215 | O84: 15 | P84: =IF(M84>0,"Valid") -> Valid | Q84: =ABS(M84) -> 44.57 | R84: =IF(N84>30%,"Excess") -> FALSE | S84: =IF(R84="Excess",30%,N84) -> 0.215 | T84: =(C84-B84) -> -1 | U84: =IF(C84<B84,B84+7,C84) -> 45777 | V84: =(U84-B84) -> 7 | W84: =(Q84*O84*(100-S84)) -> 66711.262 | X84: =(Q84*O84) -> 668.55 | Y84: =W84-X84 -> 66042.712 | Z84: =Y84/W84 -> 0.98997845 | AA84: Apr-2025 | AB84: ="Q"&ROUNDUP(MONTH(B84)/3,0)&"-"&YEAR(B84) -> Q2-2025 | AC84: =D84&" → "&E84&" → "&F84 -> Americas → USA → San Francisco | AD84: =IF(OR(J84="Laptops",J84="Phones"),"Devices",IF(OR(J84="Monitors",J84="Printers"),"Peripherals","Support")) -> Peripherals | AE84: =IF(B84<=PERCENTILE($B$2:$B$632,0.33),"Low",IF(B84<=PERCENTILE($B$2:$B$632,0.66),"Medium","High")) -> High | AF84: =UPPER(TRIM(CLEAN(SUBSTITUTE(E84,CHAR(160),"")))) -> USA | AG84: 44939 | AH84: =TEXT(AG84,"MMM-YYYY") -> Jan-2023 | AI84: =EOMONTH(B84,0) -> 45777 | AJ84: =IF(V84<=7,1,0) -> 1 | AK84: =IF(N84>20%,1,0) -> 1 | AL84: =MIN(N84,'Scenario Modelling'!$B$2) -> 0.215 | AM84: =L84*(1+'Scenario Modelling'!$B$3) -> 26.726 | AN84: =O84*(1+'Scenario Modelling'!$B$4) -> 18 | AO84: =AN84*M84*(1-AL84) -> 629.7741 | AP84: =(M84*(1-AL84)-AM84)*AN84 -> 148.7061
A85: ORD-2025-330203 | B85: 45741 | C85: 45764 | D85: Europe | E85: United Kingdom | F85: London | G85: Consumer | H85: Retail | I85: H. Kim | J85: Networking | K85: NET-7166 | L85: 1421.19 | M85: 1808.26 | N85: 0.104 | O85: 13 | P85: =IF(M85>0,"Valid") -> Valid | Q85: =ABS(M85) -> 1808.26 | R85: =IF(N85>30%,"Excess") -> FALSE | S85: =IF(R85="Excess",30%,N85) -> 0.104 | T85: =(C85-B85) -> 23 | U85: =IF(C85<B85,B85+7,C85) -> 45764 | V85: =(U85-B85) -> 23 | W85: =(Q85*O85*(100-S85)) -> 2348293.2 | X85: =(Q85*O85) -> 23507.38 | Y85: =W85-X85 -> 2324785.9 | Z85: =Y85/W85 -> 0.98998959 | AA85: Mar-2025 | AB85: ="Q"&ROUNDUP(MONTH(B85)/3,0)&"-"&YEAR(B85) -> Q1-2025 | AC85: =D85&" → "&E85&" → "&F85 -> Europe → United Kingdom → London | AD85: =IF(OR(J85="Laptops",J85="Phones"),"Devices",IF(OR(J85="Monitors",J85="Printers"),"Peripherals","Support")) -> Support | AE85: =IF(B85<=PERCENTILE($B$2:$B$632,0.33),"Low",IF(B85<=PERCENTILE($B$2:$B$632,0.66),"Medium","High")) -> High | AF85: =UPPER(TRIM(CLEAN(SUBSTITUTE(E85,CHAR(160),"")))) -> UNITED KINGDOM | AG85: 44945 | AH85: =TEXT(AG85,"MMM-YYYY") -> Jan-2023 | AI85: =EOMONTH(B85,0) -> 45747 | AJ85: =IF(V85<=7,1,0) -> 0 | AK85: =IF(N85>20%,1,0) -> 0 | AL85: =MIN(N85,'Scenario Modelling'!$B$2) -> 0.104 | AM85: =L85*(1+'Scenario Modelling'!$B$3) -> 1634.3685 | AN85: =O85*(1+'Scenario Modelling'!$B$4) -> 15.6 | AO85: =AN85*M85*(1-AL85) -> 25275.135 | AP85: =(M85*(1-AL85)-AM85)*AN85 -> -221.01362
A86: ORD-2023-841426 | B86: 45282 | C86: 45283 | D86: Africa | E86: South Africa | F86: Cape Town | G86: Non-Profit | H86: Marketplace | I86: D. Smith | J86: Components | K86: CMP-4531 | L86: 1186.18 | M86: 1285.09 | N86: 0.07 | O86: 11 | P86: =IF(M86>0,"Valid") -> Valid | Q86: =ABS(M86) -> 1285.09 | R86: =IF(N86>30%,"Excess") -> FALSE | S86: =IF(R86="Excess",30%,N86) -> 0.07 | T86: =(C86-B86) -> 1 | U86: =IF(C86<B86,B86+7,C86) -> 45283 | V86: =(U86-B86) -> 1 | W86: =(Q86*O86*(100-S86)) -> 1412609.5 | X86: =(Q86*O86) -> 14135.99 | Y86: =W86-X86 -> 1398473.5 | Z86: =Y86/W86 -> 0.989993 | AA86: Dec-2023 | AB86: ="Q"&ROUNDUP(MONTH(B86)/3,0)&"-"&YEAR(B86) -> Q4-2023 | AC86: =D86&" → "&E86&" → "&F86 -> Africa → South Africa → Cape Town | AD86: =IF(OR(J86="Laptops",J86="Phones"),"Devices",IF(OR(J86="Monitors",J86="Printers"),"Peripherals","Support")) -> Support | AE86: =IF(B86<=PERCENTILE($B$2:$B$632,0.33),"Low",IF(B86<=PERCENTILE($B$2:$B$632,0.66),"Medium","High")) -> Medium | AF86: =UPPER(TRIM(CLEAN(SUBSTITUTE(E86,CHAR(160),"")))) -> SOUTH AFRICA | AG86: 44933 | AH86: =TEXT(AG86,"MMM-YYYY") -> Jan-2023 | AI86: =EOMONTH(B86,0) -> 45291 | AJ86: =IF(V86<=7,1,0) -> 1 | AK86: =IF(N86>20%,1,0) -> 0 | AL86: =MIN(N86,'Scenario Modelling'!$B$2) -> 0.07 | AM86: =L86*(1+'Scenario Modelling'!$B$3) -> 1364.107 | AN86: =O86*(1+'Scenario Modelling'!$B$4) -> 13.2 | AO86: =AN86*M86*(1-AL86) -> 15775.765 | AP86: =(M86*(1-AL86)-AM86)*AN86 -> -2230.4476
A87: ORD-2024-594592 | B87: 45388 | C87: 45407 | D87: Asia | E87: China | F87: Shanghai | G87: Corporate | H87: Retail | I87: K. Singh | J87: Components | K87: CMP-8196 | L87: 1366.48 | M87: 1678.14 | N87: 0.154 | O87: 10 | P87: =IF(M87>0,"Valid") -> Valid | Q87: =ABS(M87) -> 1678.14 | R87: =IF(N87>30%,"Excess") -> FALSE | S87: =IF(R87="Excess",30%,N87) -> 0.154 | T87: =(C87-B87) -> 19 | U87: =IF(C87<B87,B87+7,C87) -> 45407 | V87: =(U87-B87) -> 19 | W87: =(Q87*O87*(100-S87)) -> 1675555.7 | X87: =(Q87*O87) -> 16781.4 | Y87: =W87-X87 -> 1658774.3 | Z87: =Y87/W87 -> 0.98998458 | AA87: Apr-2024 | AB87: ="Q"&ROUNDUP(MONTH(B87)/3,0)&"-"&YEAR(B87) -> Q2-2024 | AC87: =D87&" → "&E87&" → "&F87 -> Asia → China → Shanghai | AD87: =IF(OR(J87="Laptops",J87="Phones"),"Devices",IF(OR(J87="Monitors",J87="Printers"),"Peripherals","Support")) -> Support | AE87: =IF(B87<=PERCENTILE($B$2:$B$632,0.33),"Low",IF(B87<=PERCENTILE($B$2:$B$632,0.66),"Medium","High")) -> Medium | AF87: =UPPER(TRIM(CLEAN(SUBSTITUTE(E87,CHAR(160),"")))) -> CHINA | AG87: =_xlfn.MINIFS($B$2:$B$633,$AF$2:$AF$633,AF87) -> 44938 | AH87: =TEXT(AG87,"MMM-YYYY") -> Jan-2023 | AI87: =EOMONTH(B87,0) -> 45412 | AJ87: =IF(V87<=7,1,0) -> 0 | AK87: =IF(N87>20%,1,0) -> 0 | AL87: =MIN(N87,'Scenario Modelling'!$B$2) -> 0.154 | AM87: =L87*(1+'Scenario Modelling'!$B$3) -> 1571.452 | AN87: =O87*(1+'Scenario Modelling'!$B$4) -> 12 | AO87: =AN87*M87*(1-AL87) -> 17036.477 | AP87: =(M87*(1-AL87)-AM87)*AN87 -> -1820.9467
A88: ORD-2025-863978 | B88: 45876 | C88: 45888 | D88: Africa | E88: Kenya | F88: Nakuru | G88: Corporate | H88: Unknown Channel | I88: M. Rossi | J88: Components | K88: CMP-2854 | L88: 601.51 | M88: 679.35 | N88: 0.188 | O88: 3 | P88: =IF(M88>0,"Valid") -> Valid | Q88: =ABS(M88) -> 679.35 | R88: =IF(N88>30%,"Excess") -> FALSE | S88: =IF(R88="Excess",30%,N88) -> 0.188 | T88: =(C88-B88) -> 12 | U88: =IF(C88<B88,B88+7,C88) -> 45888 | V88: =(U88-B88) -> 12 | W88: =(Q88*O88*(100-S88)) -> 203421.85 | X88: =(Q88*O88) -> 2038.05 | Y88: =W88-X88 -> 201383.8 | Z88: =Y88/W88 -> 0.98998116 | AA88: Aug-2025 | AB88: ="Q"&ROUNDUP(MONTH(B88)/3,0)&"-"&YEAR(B88) -> Q3-2025 | AC88: =D88&" → "&E88&" → "&F88 -> Africa → Kenya → Nakuru | AD88: =IF(OR(J88="Laptops",J88="Phones"),"Devices",IF(OR(J88="Monitors",J88="Printers"),"Peripherals","Support")) -> Support | AE88: =IF(B88<=PERCENTILE($B$2:$B$632,0.33),"Low",IF(B88<=PERCENTILE($B$2:$B$632,0.66),"Medium","High")) -> High | AF88: =UPPER(TRIM(CLEAN(SUBSTITUTE(E88,CHAR(160),"")))) -> KENYA | AG88: 44946 | AH88: =TEXT(AG88,"MMM-YYYY") -> Jan-2023 | AI88: =EOMONTH(B88,0) -> 45900 | AJ88: =IF(V88<=7,1,0) -> 0 | AK88: =IF(N88>20%,1,0) -> 0 | AL88: =MIN(N88,'Scenario Modelling'!$B$2) -> 0.188 | AM88: =L88*(1+'Scenario Modelling'!$B$3) -> 691.7365 | AN88: =O88*(1+'Scenario Modelling'!$B$4) -> 3.6 | AO88: =AN88*M88*(1-AL88) -> 1985.8759 | AP88: =(M88*(1-AL88)-AM88)*AN88 -> -504.37548
A89: ORD-2024-604471 | B89: 45312 | C89: 45316 | D89: Asia | E89: India | F89: Delhi | G89: Consumer | H89: Direct | I89: C. Otieno | J89: Monitors | K89: MON-8973 | L89: 523.7 | M89: 1109.92 | N89: 0.03 | O89: 11 | P89: =IF(M89>0,"Valid") -> Valid | Q89: =ABS(M89) -> 1109.92 | R89: =IF(N89>30%,"Excess") -> FALSE | S89: =IF(R89="Excess",30%,N89) -> 0.03 | T89: =(C89-B89) -> 4 | U89: =IF(C89<B89,B89+7,C89) -> 45316 | V89: =(U89-B89) -> 4 | W89: =(Q89*O89*(100-S89)) -> 1220545.7 | X89: =(Q89*O89) -> 12209.12 | Y89: =W89-X89 -> 1208336.6 | Z89: =Y89/W89 -> 0.989997 | AA89: Jan-2024 | AB89: ="Q"&ROUNDUP(MONTH(B89)/3,0)&"-"&YEAR(B89) -> Q1-2024 | AC89: =D89&" → "&E89&" → "&F89 -> Asia → India → Delhi | AD89: =IF(OR(J89="Laptops",J89="Phones"),"Devices",IF(OR(J89="Monitors",J89="Printers"),"Peripherals","Support")) -> Peripherals | AE89: =IF(B89<=PERCENTILE($B$2:$B$632,0.33),"Low",IF(B89<=PERCENTILE($B$2:$B$632,0.66),"Medium","High")) -> Medium | AF89: =UPPER(TRIM(CLEAN(SUBSTITUTE(E89,CHAR(160),"")))) -> INDIA | AG89: 44955 | AH89: =TEXT(AG89,"MMM-YYYY") -> Jan-2023 | AI89: =EOMONTH(B89,0) -> 45322 | AJ89: =IF(V89<=7,1,0) -> 1 | AK89: =IF(N89>20%,1,0) -> 0 | AL89: =MIN(N89,'Scenario Modelling'!$B$2) -> 0.03 | AM89: =L89*(1+'Scenario Modelling'!$B$3) -> 602.255 | AN89: =O89*(1+'Scenario Modelling'!$B$4) -> 13.2 | AO89: =AN89*M89*(1-AL89) -> 14211.416 | AP89: =(M89*(1-AL89)-AM89)*AN89 -> 6261.6497
A90: ORD-2023-258768 | B90: 45106 | C90: 45109 | D90: Asia | E90: Japan | F90: Nagoya | G90: Education | H90: Marketplace | I90: F. Müller | J90: Monitors | K90: MON-2990 | L90: 55.65 | M90: 83.57 | N90: 0.066 | O90: 8 | P90: =IF(M90>0,"Valid") -> Valid | Q90: =ABS(M90) -> 83.57 | R90: =IF(N90>30%,"Excess") -> FALSE | S90: =IF(R90="Excess",30%,N90) -> 0.066 | T90: =(C90-B90) -> 3 | U90: =IF(C90<B90,B90+7,C90) -> 45109 | V90: =(U90-B90) -> 3 | W90: =(Q90*O90*(100-S90)) -> 66811.875 | X90: =(Q90*O90) -> 668.56 | Y90: =W90-X90 -> 66143.315 | Z90: =Y90/W90 -> 0.9899934 | AA90: Jun-2023 | AB90: ="Q"&ROUNDUP(MONTH(B90)/3,0)&"-"&YEAR(B90) -> Q2-2023 | AC90: =D90&" → "&E90&" → "&F90 -> Asia → Japan → Nagoya | AD90: =IF(OR(J90="Laptops",J90="Phones"),"Devices",IF(OR(J90="Monitors",J90="Printers"),"Peripherals","Support")) -> Peripherals | AE90: =IF(B90<=PERCENTILE($B$2:$B$632,0.33),"Low",IF(B90<=PERCENTILE($B$2:$B$632,0.66),"Medium","High")) -> Low | AF90: =UPPER(TRIM(CLEAN(SUBSTITUTE(E90,CHAR(160),"")))) -> JAPAN | AG90: 44988 | AH90: =TEXT(AG90,"MMM-YYYY") -> Mar-2023 | AI90: =EOMONTH(B90,0) -> 45107 | AJ90: =IF(V90<=7,1,0) -> 1 | AK90: =IF(N90>20%,1,0) -> 0 | AL90: =MIN(N90,'Scenario Modelling'!$B$2) -> 0.066 | AM90: =L90*(1+'Scenario Modelling'!$B$3) -> 63.9975 | AN90: =O90*(1+'Scenario Modelling'!$B$4) -> 9.6 | AO90: =AN90*M90*(1-AL90) -> 749.32205 | AP90: =(M90*(1-AL90)-AM90)*AN90 -> 134.94605
A91: ORD-2025-626047 | B91: 45775 | C91: 45792 | D91: Asia | E91: Japan | F91: Nagoya | G91: Education | H91: Direct | I91: N. Brown | J91: Networking | K91: NET-1966 | L91: 691.19 | M91: 1284.3 | N91: 0.074 | O91: 7 | P91: =IF(M91>0,"Valid") -> Valid | Q91: =ABS(M91) -> 1284.3 | R91: =IF(N91>30%,"Excess") -> FALSE | S91: =IF(R91="Excess",30%,N91) -> 0.074 | T91: =(C91-B91) -> 17 | U91: =IF(C91<B91,B91+7,C91) -> 45792 | V91: =(U91-B91) -> 17 | W91: =(Q91*O91*(100-S91)) -> 898344.73 | X91: =(Q91*O91) -> 8990.1 | Y91: =W91-X91 -> 889354.63 | Z91: =Y91/W91 -> 0.98999259 | AA91: Apr-2025 | AB91: ="Q"&ROUNDUP(MONTH(B91)/3,0)&"-"&YEAR(B91) -> Q2-2025 | AC91: =D91&" → "&E91&" → "&F91 -> Asia → Japan → Nagoya | AD91: =IF(OR(J91="Laptops",J91="Phones"),"Devices",IF(OR(J91="Monitors",J91="Printers"),"Peripherals","Support")) -> Support | AE91: =IF(B91<=PERCENTILE($B$2:$B$632,0.33),"Low",IF(B91<=PERCENTILE($B$2:$B$632,0.66),"Medium","High")) -> High | AF91: =UPPER(TRIM(CLEAN(SUBSTITUTE(E91,CHAR(160),"")))) -> JAPAN | AG91: 44988 | AH91: =TEXT(AG91,"MMM-YYYY") -> Mar-2023 | AI91: =EOMONTH(B91,0) -> 45777 | AJ91: =IF(V91<=7,1,0) -> 0 | AK91: =IF(N91>20%,1,0) -> 0 | AL91: =MIN(N91,'Scenario Modelling'!$B$2) -> 0.074 | AM91: =L91*(1+'Scenario Modelling'!$B$3) -> 794.8685 | AN91: =O91*(1+'Scenario Modelling'!$B$4) -> 8.4 | AO91: =AN91*M91*(1-AL91) -> 9989.7991 | AP91: =(M91*(1-AL91)-AM91)*AN91 -> 3312.9037
A92: ORD-2025-526752 | B92: 45817 | C92: 45833 | D92: Asia | E92: India | F92: Hyderabad | G92: Enterprise | H92: Distributor | I92: M. Rossi | J92: Phones | K92: PHN-3482 | L92: 527.33 | M92: 911.72 | N92: 0.144 | O92: 25 | P92: =IF(M92>0,"Valid") -> Valid | Q92: =ABS(M92) -> 911.72 | R92: =IF(N92>30%,"Excess") -> FALSE | S92: =IF(R92="Excess",30%,N92) -> 0.144 | T92: =(C92-B92) -> 16 | U92: =IF(C92<B92,B92+7,C92) -> 45833 | V92: =(U92-B92) -> 16 | W92: =(Q92*O92*(100-S92)) -> 2276017.8 | X92: =(Q92*O92) -> 22793 | Y92: =W92-X92 -> 2253224.8 | Z92: =Y92/W92 -> 0.98998558 | AA92: Jun-2025 | AB92: ="Q"&ROUNDUP(MONTH(B92)/3,0)&"-"&YEAR(B92) -> Q2-2025 | AC92: =D92&" → "&E92&" → "&F92 -> Asia → India → Hyderabad | AD92: =IF(OR(J92="Laptops",J92="Phones"),"Devices",IF(OR(J92="Monitors",J92="Printers"),"Peripherals","Support")) -> Devices | AE92: =IF(B92<=PERCENTILE($B$2:$B$632,0.33),"Low",IF(B92<=PERCENTILE($B$2:$B$632,0.66),"Medium","High")) -> High | AF92: =UPPER(TRIM(CLEAN(SUBSTITUTE(E92,CHAR(160),"")))) -> INDIA | AG92: 44955 | AH92: =TEXT(AG92,"MMM-YYYY") -> Jan-2023 | AI92: =EOMONTH(B92,0) -> 45838 | AJ92: =IF(V92<=7,1,0) -> 0 | AK92: =IF(N92>20%,1,0) -> 0 | AL92: =MIN(N92,'Scenario Modelling'!$B$2) -> 0.144 | AM92: =L92*(1+'Scenario Modelling'!$B$3) -> 606.4295 | AN92: =O92*(1+'Scenario Modelling'!$B$4) -> 30 | AO92: =AN92*M92*(1-AL92) -> 23412.97 | AP92: =(M92*(1-AL92)-AM92)*AN92 -> 5220.0846
A93: ORD-2023-374486 | B93: 45101 | C93: 45100 | D93: Americas | E93: Brazil | F93: Rio de Janeiro | G93: Non-Profit | H93: Retail | I93: E. Garcia | J93: Printers | K93: PRN-6490 | L93: 804.01 | M93: 1405.07 | N93: 0.096 | O93: 8 | P93: =IF(M93>0,"Valid") -> Valid | Q93: =ABS(M93) -> 1405.07 | R93: =IF(N93>30%,"Excess") -> FALSE | S93: =IF(R93="Excess",30%,N93) -> 0.096 | T93: =(C93-B93) -> -1 | U93: =IF(C93<B93,B93+7,C93) -> 45108 | V93: =(U93-B93) -> 7 | W93: =(Q93*O93*(100-S93)) -> 1122976.9 | X93: =(Q93*O93) -> 11240.56 | Y93: =W93-X93 -> 1111736.3 | Z93: =Y93/W93 -> 0.98999039 | AA93: Jun-2023 | AB93: ="Q"&ROUNDUP(MONTH(B93)/3,0)&"-"&YEAR(B93) -> Q2-2023 | AC93: =D93&" → "&E93&" → "&F93 -> Americas → Brazil → Rio de Janeiro | AD93: =IF(OR(J93="Laptops",J93="Phones"),"Devices",IF(OR(J93="Monitors",J93="Printers"),"Peripherals","Support")) -> Peripherals | AE93: =IF(B93<=PERCENTILE($B$2:$B$632,0.33),"Low",IF(B93<=PERCENTILE($B$2:$B$632,0.66),"Medium","High")) -> Low | AF93: =UPPER(TRIM(CLEAN(SUBSTITUTE(E93,CHAR(160),"")))) -> BRAZIL | AG93: =_xlfn.MINIFS($B$2:$B$633,$AF$2:$AF$633,AF93) -> 44955 | AH93: =TEXT(AG93,"MMM-YYYY") -> Jan-2023 | AI93: =EOMONTH(B93,0) -> 45107 | AJ93: =IF(V93<=7,1,0) -> 1 | AK93: =IF(N93>20%,1,0) -> 0 | AL93: =MIN(N93,'Scenario Modelling'!$B$2) -> 0.096 | AM93: =L93*(1+'Scenario Modelling'!$B$3) -> 924.6115 | AN93: =O93*(1+'Scenario Modelling'!$B$4) -> 9.6 | AO93: =AN93*M93*(1-AL93) -> 12193.759 | AP93: =(M93*(1-AL93)-AM93)*AN93 -> 3317.4891
A94: ORD-2024-997336 | B94: 45569 | C94: 45598 | D94: Africa | E94: Nigeria | F94: Abuja | G94: Corporate | H94: Distributor | I94: F. Müller | J94: Accessories | K94: ACC-9038 | L94: 412.09 | M94: 968.94 | N94: 0.099 | O94: 23 | P94: =IF(M94>0,"Valid") -> Valid | Q94: =ABS(M94) -> 968.94 | R94: =IF(N94>30%,"Excess") -> FALSE | S94: =IF(R94="Excess",30%,N94) -> 0.099 | T94: =(C94-B94) -> 29 | U94: =IF(C94<B94,B94+7,C94) -> 45598 | V94: =(U94-B94) -> 29 | W94: =(Q94*O94*(100-S94)) -> 2226355.7 | X94: =(Q94*O94) -> 22285.62 | Y94: =W94-X94 -> 2204070.1 | Z94: =Y94/W94 -> 0.98999009 | AA94: Oct-2024 | AB94: ="Q"&ROUNDUP(MONTH(B94)/3,0)&"-"&YEAR(B94) -> Q4-2024 | AC94: =D94&" → "&E94&" → "&F94 -> Africa → Nigeria → Abuja | AD94: =IF(OR(J94="Laptops",J94="Phones"),"Devices",IF(OR(J94="Monitors",J94="Printers"),"Peripherals","Support")) -> Support | AE94: =IF(B94<=PERCENTILE($B$2:$B$632,0.33),"Low",IF(B94<=PERCENTILE($B$2:$B$632,0.66),"Medium","High")) -> Medium | AF94: =UPPER(TRIM(CLEAN(SUBSTITUTE(E94,CHAR(160),"")))) -> NIGERIA | AG94: =_xlfn.MINIFS($B$2:$B$633,$AF$2:$AF$633,AF94) -> 44941 | AH94: =TEXT(AG94,"MMM-YYYY") -> Jan-2023 | AI94: =EOMONTH(B94,0) -> 45596 | AJ94: =IF(V94<=7,1,0) -> 0 | AK94: =IF(N94>20%,1,0) -> 0 | AL94: =MIN(N94,'Scenario Modelling'!$B$2) -> 0.099 | AM94: =L94*(1+'Scenario Modelling'!$B$3) -> 473.9035 | AN94: =O94*(1+'Scenario Modelling'!$B$4) -> 27.6 | AO94: =AN94*M94*(1-AL94) -> 24095.212 | AP94: =(M94*(1-AL94)-AM94)*AN94 -> 11015.476
A95: ORD-2025-725646 | B95: 45910 | C95: 45930 | D95: Africa | E95: Kenya | F95: Mombasa | G95: Corporate | H95: Direct | I95: L. Okafor | J95: Phones | K95: PHN-6954 | L95: 1009.48 | M95: 1088.81 | N95: 0.16 | O95: 6 | P95: =IF(M95>0,"Valid") -> Valid | Q95: =ABS(M95) -> 1088.81 | R95: =IF(N95>30%,"Excess") -> FALSE | S95: =IF(R95="Excess",30%,N95) -> 0.16 | T95: =(C95-B95) -> 20 | U95: =IF(C95<B95,B95+7,C95) -> 45930 | V95: =(U95-B95) -> 20 | W95: =(Q95*O95*(100-S95)) -> 652240.74 | X95: =(Q95*O95) -> 6532.86 | Y95: =W95-X95 -> 645707.88 | Z95: =Y95/W95 -> 0.98998397 | AA95: Sep-2025 | AB95: ="Q"&ROUNDUP(MONTH(B95)/3,0)&"-"&YEAR(B95) -> Q3-2025 | AC95: =D95&" → "&E95&" → "&F95 -> Africa → Kenya → Mombasa | AD95: =IF(OR(J95="Laptops",J95="Phones"),"Devices",IF(OR(J95="Monitors",J95="Printers"),"Peripherals","Support")) -> Devices | AE95: =IF(B95<=PERCENTILE($B$2:$B$632,0.33),"Low",IF(B95<=PERCENTILE($B$2:$B$632,0.66),"Medium","High")) -> High | AF95: =UPPER(TRIM(CLEAN(SUBSTITUTE(E95,CHAR(160),"")))) -> KENYA | AG95: 44946 | AH95: =TEXT(AG95,"MMM-YYYY") -> Jan-2023 | AI95: =EOMONTH(B95,0) -> 45930 | AJ95: =IF(V95<=7,1,0) -> 0 | AK95: =IF(N95>20%,1,0) -> 0 | AL95: =MIN(N95,'Scenario Modelling'!$B$2) -> 0.16 | AM95: =L95*(1+'Scenario Modelling'!$B$3) -> 1160.902 | AN95: =O95*(1+'Scenario Modelling'!$B$4) -> 7.2 | AO95: =AN95*M95*(1-AL95) -> 6585.1229 | AP95: =(M95*(1-AL95)-AM95)*AN95 -> -1773.3715
A96: ORD-2023-868734 | B96: 45022 | C96: 45043 | D96: Europe | E96: United Kingdom | F96: Manchester | G96: Enterprise | H96: Distributor | I96: I. Johnson | J96: Printers | K96: PRN-8970 | L96: 1084.79 | M96: 2484.99 | N96: 0.034 | O96: 18 | P96: =IF(M96>0,"Valid") -> Valid | Q96: =ABS(M96) -> 2484.99 | R96: =IF(N96>30%,"Excess") -> FALSE | S96: =IF(R96="Excess",30%,N96) -> 0.034 | T96: =(C96-B96) -> 21 | U96: =IF(C96<B96,B96+7,C96) -> 45043 | V96: =(U96-B96) -> 21 | W96: =(Q96*O96*(100-S96)) -> 4471461.2 | X96: =(Q96*O96) -> 44729.82 | Y96: =W96-X96 -> 4426731.4 | Z96: =Y96/W96 -> 0.9899966 | AA96: Apr-2023 | AB96: ="Q"&ROUNDUP(MONTH(B96)/3,0)&"-"&YEAR(B96) -> Q2-2023 | AC96: =D96&" → "&E96&" → "&F96 -> Europe → United Kingdom → Manchester | AD96: =IF(OR(J96="Laptops",J96="Phones"),"Devices",IF(OR(J96="Monitors",J96="Printers"),"Peripherals","Support")) -> Peripherals | AE96: =IF(B96<=PERCENTILE($B$2:$B$632,0.33),"Low",IF(B96<=PERCENTILE($B$2:$B$632,0.66),"Medium","High")) -> Low | AF96: =UPPER(TRIM(CLEAN(SUBSTITUTE(E96,CHAR(160),"")))) -> UNITED KINGDOM | AG96: 44945 | AH96: =TEXT(AG96,"MMM-YYYY") -> Jan-2023 | AI96: =EOMONTH(B96,0) -> 45046 | AJ96: =IF(V96<=7,1,0) -> 0 | AK96: =IF(N96>20%,1,0) -> 0 | AL96: =MIN(N96,'Scenario Modelling'!$B$2) -> 0.034 | AM96: =L96*(1+'Scenario Modelling'!$B$3) -> 1247.5085 | AN96: =O96*(1+'Scenario Modelling'!$B$4) -> 21.6 | AO96: =AN96*M96*(1-AL96) -> 51850.807 | AP96: =(M96*(1-AL96)-AM96)*AN96 -> 24904.624
A97: ORD-2025-262491 | B97: 45870 | C97: 45885 | D97: Asia | E97: India | F97: Unknown City | G97: Enterprise | H97: Direct | I97: O. Wang | J97: Monitors | K97: MON-1822 | L97: 24.44 | M97: 28.69 | N97: 0.146 | O97: 6 | P97: =IF(M97>0,"Valid") -> Valid | Q97: =ABS(M97) -> 28.69 | R97: =IF(N97>30%,"Excess") -> FALSE | S97: =IF(R97="Excess",30%,N97) -> 0.146 | T97: =(C97-B97) -> 15 | U97: =IF(C97<B97,B97+7,C97) -> 45885 | V97: =(U97-B97) -> 15 | W97: =(Q97*O97*(100-S97)) -> 17188.868 | X97: =(Q97*O97) -> 172.14 | Y97: =W97-X97 -> 17016.728 | Z97: =Y97/W97 -> 0.98998538 | AA97: Aug-2025 | AB97: ="Q"&ROUNDUP(MONTH(B97)/3,0)&"-"&YEAR(B97) -> Q3-2025 | AC97: =D97&" → "&E97&" → "&F97 -> Asia → India → Unknown City | AD97: =IF(OR(J97="Laptops",J97="Phones"),"Devices",IF(OR(J97="Monitors",J97="Printers"),"Peripherals","Support")) -> Peripherals | AE97: =IF(B97<=PERCENTILE($B$2:$B$632,0.33),"Low",IF(B97<=PERCENTILE($B$2:$B$632,0.66),"Medium","High")) -> High | AF97: =UPPER(TRIM(CLEAN(SUBSTITUTE(E97,CHAR(160),"")))) -> INDIA | AG97: 44955 | AH97: =TEXT(AG97,"MMM-YYYY") -> Jan-2023 | AI97: =EOMONTH(B97,0) -> 45900 | AJ97: =IF(V97<=7,1,0) -> 0 | AK97: =IF(N97>20%,1,0) -> 0 | AL97: =MIN(N97,'Scenario Modelling'!$B$2) -> 0.146 | AM97: =L97*(1+'Scenario Modelling'!$B$3) -> 28.106 | AN97: =O97*(1+'Scenario Modelling'!$B$4) -> 7.2 | AO97: =AN97*M97*(1-AL97) -> 176.40907 | AP97: =(M97*(1-AL97)-AM97)*AN97 -> -25.954128
A98: ORD-2024-638884 | B98: 45440 | C98: 45438 | D98: Africa | E98: Nigeria | F98: Abuja | G98: Enterprise | H98: Online | I98: F. Müller | J98: Accessories | K98: ACC-5177 | L98: 1227.08 | M98: 1896.62 | N98: 0 | O98: 18 | P98: =IF(M98>0,"Valid") -> Valid | Q98: =ABS(M98) -> 1896.62 | R98: =IF(N98>30%,"Excess") -> FALSE | S98: =IF(R98="Excess",30%,N98) -> 0 | T98: =(C98-B98) -> -2 | U98: =IF(C98<B98,B98+7,C98) -> 45447 | V98: =(U98-B98) -> 7 | W98: =(Q98*O98*(100-S98)) -> 3413916 | X98: =(Q98*O98) -> 34139.16 | Y98: =W98-X98 -> 3379776.8 | Z98: =Y98/W98 -> 0.99 | AA98: May-2024 | AB98: ="Q"&ROUNDUP(MONTH(B98)/3,0)&"-"&YEAR(B98) -> Q2-2024 | AC98: =D98&" → "&E98&" → "&F98 -> Africa → Nigeria → Abuja | AD98: =IF(OR(J98="Laptops",J98="Phones"),"Devices",IF(OR(J98="Monitors",J98="Printers"),"Peripherals","Support")) -> Support | AE98: =IF(B98<=PERCENTILE($B$2:$B$632,0.33),"Low",IF(B98<=PERCENTILE($B$2:$B$632,0.66),"Medium","High")) -> Medium | AF98: =UPPER(TRIM(CLEAN(SUBSTITUTE(E98,CHAR(160),"")))) -> NIGERIA | AG98: 44941 | AH98: =TEXT(AG98,"MMM-YYYY") -> Jan-2023 | AI98: =EOMONTH(B98,0) -> 45443 | AJ98: =IF(V98<=7,1,0) -> 1 | AK98: =IF(N98>20%,1,0) -> 0 | AL98: =MIN(N98,'Scenario Modelling'!$B$2) -> 0 | AM98: =L98*(1+'Scenario Modelling'!$B$3) -> 1411.142 | AN98: =O98*(1+'Scenario Modelling'!$B$4) -> 21.6 | AO98: =AN98*M98*(1-AL98) -> 40966.992 | AP98: =(M98*(1-AL98)-AM98)*AN98 -> 10486.325
A99: ORD-2025-541501 | B99: 45860 | C99: 45887 | D99: Asia | E99: China | F99: Shenzhen | G99: Non-Profit | H99: Marketplace | I99: M. Rossi | J99: Networking | K99: NET-1804 | L99: 547.32 | M99: 419.17 | N99: 0.092 | O99: 14 | P99: =IF(M99>0,"Valid") -> Valid | Q99: =ABS(M99) -> 419.17 | R99: =IF(N99>30%,"Excess") -> FALSE | S99: =IF(R99="Excess",30%,N99) -> 0.092 | T99: =(C99-B99) -> 27 | U99: =IF(C99<B99,B99+7,C99) -> 45887 | V99: =(U99-B99) -> 27 | W99: =(Q99*O99*(100-S99)) -> 586298.11 | X99: =(Q99*O99) -> 5868.38 | Y99: =W99-X99 -> 580429.73 | Z99: =Y99/W99 -> 0.98999079 | AA99: Jul-2025 | AB99: ="Q"&ROUNDUP(MONTH(B99)/3,0)&"-"&YEAR(B99) -> Q3-2025 | AC99: =D99&" → "&E99&" → "&F99 -> Asia → China → Shenzhen | AD99: =IF(OR(J99="Laptops",J99="Phones"),"Devices",IF(OR(J99="Monitors",J99="Printers"),"Peripherals","Support")) -> Support | AE99: =IF(B99<=PERCENTILE($B$2:$B$632,0.33),"Low",IF(B99<=PERCENTILE($B$2:$B$632,0.66),"Medium","High")) -> High | AF99: =UPPER(TRIM(CLEAN(SUBSTITUTE(E99,CHAR(160),"")))) -> CHINA | AG99: =_xlfn.MINIFS($B$2:$B$633,$AF$2:$AF$633,AF99) -> 44938 | AH99: =TEXT(AG99,"MMM-YYYY") -> Jan-2023 | AI99: =EOMONTH(B99,0) -> 45869 | AJ99: =IF(V99<=7,1,0) -> 0 | AK99: =IF(N99>20%,1,0) -> 0 | AL99: =MIN(N99,'Scenario Modelling'!$B$2) -> 0.092 | AM99: =L99*(1+'Scenario Modelling'!$B$3) -> 629.418 | AN99: =O99*(1+'Scenario Modelling'!$B$4) -> 16.8 | AO99: =AN99*M99*(1-AL99) -> 6394.1868 | AP99: =(M99*(1-AL99)-AM99)*AN99 -> -4180.0356
A100: ORD-2023-422918 | B100: 44985 | C100: 45005 | D100: Europe | E100: Germany | F100: Berlin | G100: Small Business | H100: Direct | I100: H. Kim | J100: Laptops | K100: LAP-3679 | L100: 1200.78 | M100: 2001.17 | N100: 0.292 | O100: 18 | P100: =IF(M100>0,"Valid") -> Valid | Q100: =ABS(M100) -> 2001.17 | R100: =IF(N100>30%,"Excess") -> FALSE | S100: =IF(R100="Excess",30%,N100) -> 0.292 | T100: =(C100-B100) -> 20 | U100: =IF(C100<B100,B100+7,C100) -> 45005 | V100: =(U100-B100) -> 20 | W100: =(Q100*O100*(100-S100)) -> 3591587.9 | X100: =(Q100*O100) -> 36021.06 | Y100: =W100-X100 -> 3555566.8 | Z100: =Y100/W100 -> 0.98997071 | AA100: Feb-2023 | AB100: ="Q"&ROUNDUP(MONTH(B100)/3,0)&"-"&YEAR(B100) -> Q1-2023 | AC100: =D100&" → "&E100&" → "&F100 -> Europe → Germany → Berlin | AD100: =IF(OR(J100="Laptops",J100="Phones"),"Devices",IF(OR(J100="Monitors",J100="Printers"),"Peripherals","Support")) -> Devices | AE100: =IF(B100<=PERCENTILE($B$2:$B$632,0.33),"Low",IF(B100<=PERCENTILE($B$2:$B$632,0.66),"Medium","High")) -> Low | AF100: =UPPER(TRIM(CLEAN(SUBSTITUTE(E100,CHAR(160),"")))) -> GERMANY | AG100: 44948 | AH100: =TEXT(AG100,"MMM-YYYY") -> Jan-2023 | AI100: =EOMONTH(B100,0) -> 44985 | AJ100: =IF(V100<=7,1,0) -> 0 | AK100: =IF(N100>20%,1,0) -> 1 | AL100: =MIN(N100,'Scenario Modelling'!$B$2) -> 0.25 | AM100: =L100*(1+'Scenario Modelling'!$B$3) -> 1380.897 | AN100: =O100*(1+'Scenario Modelling'!$B$4) -> 21.6 | AO100: =AN100*M100*(1-AL100) -> 32418.954 | AP100: =(M100*(1-AL100)-AM100)*AN100 -> 2591.5788
...

Sheet Cohort Analysis
A2: First Sales per Country
A3: Country | B3: Min of OrderDate | C3: First Month
A4: Brazil | B4: 44955 | C4: =TEXT(B5,"MMM-YYYY") -> Jan-2023
A5: Canada | B5: 44928 | C5: =TEXT(B6,"MMM-YYYY") -> Jan-2023
A6: China | B6: 44938 | C6: =TEXT(B7,"MMM-YYYY") -> Jan-2023
A7: France | B7: 44936 | C7: =TEXT(B8,"MMM-YYYY") -> Jan-2023
A8: Germany | B8: 44948 | C8: =TEXT(B9,"MMM-YYYY") -> Jan-2023
A9: India | B9: 44955 | C9: =TEXT(B10,"MMM-YYYY") -> Mar-2023
A10: Japan | B10: 44988 | C10: =TEXT(B11,"MMM-YYYY") -> Jan-2023
A11: Kenya | B11: 44946 | C11: =TEXT(B12,"MMM-YYYY") -> Jan-2023
A12: Nigeria | B12: 44941 | C12: =TEXT(B13,"MMM-YYYY") -> Jan-2023
A13: South Africa | B13: 44933 | C13: =TEXT(B14,"MMM-YYYY") -> Jan-2023
A14: United Kingdom | B14: 44945 | C14: =TEXT(B15,"MMM-YYYY") -> Jan-2023
A15: USA | B15: 44939 | C15: =TEXT(B16,"MMM-YYYY") -> Jan-2023
A16: Grand Total | B16: 44928
A20: Country Performance per Month
A21: Country | B21: (All)
A23: Sum of Gross Revenue | B23: Order Month date
A24: Country Start Month | B24: 44957 | C24: 44985 | D24: 45016 | E24: 45046 | F24: 45077 | G24: 45107 | H24: 45138 | I24: 45169 | J24: 45199 | K24: 45230 | L24: 45260 | M24: 45291 | N24: 45322 | O24: 45351 | P24: 45382 | Q24: 45412 | R24: 45443 | S24: 45473 | T24: 45504 | U24: 45535 | V24: 45565 | W24: 45596 | X24: 45626 | Y24: 45657 | Z24: 45688 | AA24: 45716 | AB24: 45747 | AC24: 45777 | AD24: 45808 | AE24: 45838 | AF24: 45869 | AG24: 45900 | AH24: 45930 | AI24: Grand Total
A25: Jan-2023 | B25: 21340481 | C25: 49094474 | D25: 21497699 | E25: 39011471 | F25: 51000019 | G25: 25518491 | H25: 60815584 | I25: 38150422 | J25: 13073997 | K25: 28257621 | L25: 12616077 | M25: 38296676 | N25: 26409814 | O25: 35025811 | P25: 43041344 | Q25: 27485227 | R25: 44101237 | S25: 61649131 | T25: 28173611 | U25: 34107584 | V25: 33691365 | W25: 44947224 | X25: 49675459 | Y25: 37946045 | Z25: 22309390 | AA25: 22932461 | AB25: 17701245 | AC25: 38139816 | AD25: 35037801 | AE25: 42739278 | AF25: 54756261 | AG25: 38327675 | AH25: 11668160 | AI25: 1.1485389e+09
A26: Mar-2023 | D26: 3646201.9 | E26: 2402444.9 | F26: 1053500.5 | G26: 575772.69 | H26: 3688811.1 | J26: 3659204.5 | K26: 1708576.1 | L26: 1630948.5 | M26: 2952129.3 | N26: 7202374.3 | O26: 1905182.9 | R26: 1594736.8 | S26: 7647140.3 | T26: 2994117.1 | U26: 9763778.9 | V26: 6007528.5 | W26: 3503876.8 | Y26: 2450105 | Z26: 2008179.5 | AA26: 986655.77 | AB26: 5759867.5 | AC26: 2213143.6 | AD26: 7384941.2 | AE26: 1352667.6 | AF26: 1060736.1 | AG26: 3939411.1 | AH26: 8751598.8 | AI26: 97843631
A27: Grand Total | B27: 21340481 | C27: 49094474 | D27: 25143900 | E27: 41413916 | F27: 52053519 | G27: 26094263 | H27: 64504395 | I27: 38150422 | J27: 16733201 | K27: 29966197 | L27: 14247025 | M27: 41248806 | N27: 33612189 | O27: 36930993 | P27: 43041344 | Q27: 27485227 | R27: 45695974 | S27: 69296271 | T27: 31167728 | U27: 43871362 | V27: 39698894 | W27: 48451101 | X27: 49675459 | Y27: 40396150 | Z27: 24317570 | AA27: 23919117 | AB27: 23461112 | AC27: 40352960 | AD27: 42422743 | AE27: 44091946 | AF27: 55816997 | AG27: 42267087 | AH27: 20419759 | AI27: 1.2463826e+09
A29: ABC ANALYSIS: Devices | P29: ABC Analysis :Support
A30: Category Groups | B30: Devices | C30: =SUM(B33:B201) -> 3.5390939e+08 | I30: ABC Analysis: Peripheral | P30: Category Groups | Q30: Support | R30: =SUM(Q33:Q296) -> 5.2865494e+08
I31: Category Groups | J31: Peripherals | K31: =SUM(J34:J229) -> 3.6381826e+08
A32: SKU | B32: Sum of Gross Revenue | C32: Cumulative Revenue | D32: Cumulative % | E32: ABC Analysis | P32: SKU | Q32: Sum of Gross Revenue | R32: Cumulative Revenue | S32: Cumulative % | T32: ABC Analysis | AH32: PRICE COMPLIANCE
A33: LAP-8910 | B33: 12095209 | C33: =SUM($B$33:B33) -> 12095209 | D33: =C33/$C$30 -> 0.034176004 | E33: =IF(D33<=0.8,"A",IF(D33<=0.95,"B","C")) -> A | I33: SKU | J33: Sum of Gross Revenue | K33: Cumulative Revenue | L33: Cumulative % | M33: ABC Analysis | P33: CMP-8851 | Q33: 16792062 | R33: =SUM($Q$33:Q33) -> 16792062 | S33: =(R33/$R$30) -> 0.031763747 | T33: =IF(S33<=0.8,"A",IF(S33<=0.95,"B","C")) -> A | V33: SALES PERSON PRODUCTIVITY | AH33: Region | AI33: Sales person | AJ33: Sum of Flagged Discount % | AK33: Count of OrderID | AL33: High Discounts %
A34: LAP-3904 | B34: 8367460.4 | C34: =SUM($B$33:B34) -> 20462669 | D34: =C34/$C$30 -> 0.057818949 | E34: =IF(D34<=0.8,"A",IF(D34<=0.95,"B","C")) -> A | I34: MON-6962 | J34: 12413265 | K34: =SUM($J$34:J34) -> 12413265 | L34: =(K34/$K$31) -> 0.034119413 | M34: =IF(L34<=0.8,"A",IF(L34<=0.95,"B","C")) -> A | P34: NET-2365 | Q34: 10924400 | R34: =SUM($Q$33:Q34) -> 27716462 | S34: =(R34/$R$30) -> 0.052428267 | T34: =IF(S34<=0.8,"A",IF(S34<=0.95,"B","C")) -> A | V34: Sales person | W34: Count of OrderID | X34: Sum of Gross Revenue | Y34: Sum of Gross Profit | Z34: Revenue Per order | AA34: Gross Profit per order | AB34: Orders per month | AH34: Africa | AI34: M. Rossi | AJ34: 5 | AK34: 16 | AL34: =AJ34/AK34 -> 0.3125
A35: LAP-8214 | B35: 7965626.2 | C35: =SUM($B$33:B35) -> 28428295 | D35: =C35/$C$30 -> 0.08032648 | E35: =IF(D35<=0.8,"A",IF(D35<=0.95,"B","C")) -> A | I35: MON-2266 | J35: 9898162.4 | K35: =SUM($J$34:J35) -> 22311428 | L35: =(K35/$K$31) -> 0.061325751 | M35: =IF(L35<=0.8,"A",IF(L35<=0.95,"B","C")) -> A | P35: CMP-3938 | Q35: 10641140 | R35: =SUM($Q$33:Q35) -> 38357602 | S35: =(R35/$R$30) -> 0.072556972 | T35: =IF(S35<=0.8,"A",IF(S35<=0.95,"B","C")) -> A | V35: M. Rossi | W35: 48 | X35: 1.1066577e+08 | Y35: 1.095578e+08 | Z35: =X35/W35 -> 2305536.8 | AA35: =Y35/W35 -> 2282454.1 | AB35: =W35/35 -> 1.3714286 | AI35: J. Njeri | AJ35: 3 | AK35: 12 | AL35: =AJ35/AK35 -> 0.25
A36: PHN-9677 | B36: 7647140.3 | C36: =SUM($B$33:B36) -> 36075436 | D36: =C36/$C$30 -> 0.1019341 | E36: =IF(D36<=0.8,"A",IF(D36<=0.95,"B","C")) -> A | I36: MON-5188 | J36: 9728928.8 | K36: =SUM($J$34:J36) -> 32040356 | L36: =(K36/$K$31) -> 0.088066929 | M36: =IF(L36<=0.8,"A",IF(L36<=0.95,"B","C")) -> A | P36: NET-5523 | Q36: 8978223.2 | R36: =SUM($Q$33:Q36) -> 47335825 | S36: =(R36/$R$30) -> 0.089540117 | T36: =IF(S36<=0.8,"A",IF(S36<=0.95,"B","C")) -> A | V36: K. Singh | W36: 44 | X36: 1.0175746e+08 | Y36: 1.0073853e+08 | Z36: =X36/W36 -> 2312669.4 | AA36: =Y36/W36 -> 2289511.9 | AB36: =W36/35 -> 1.2571429 | AI36: A. Patel | AJ36: 3 | AK36: 16 | AL36: =AJ36/AK36 -> 0.1875
A37: LAP-5763 | B37: 7228123.8 | C37: =SUM($B$33:B37) -> 43303559 | D37: =C37/$C$30 -> 0.12235776 | E37: =IF(D37<=0.8,"A",IF(D37<=0.95,"B","C")) -> A | I37: MON-6699 | J37: 9038263.2 | K37: =SUM($J$34:J37) -> 41078620 | L37: =(K37/$K$31) -> 0.11290973 | M37: =IF(L37<=0.8,"A",IF(L37<=0.95,"B","C")) -> A | P37: ACC-6626 | Q37: 8807252.2 | R37: =SUM($Q$33:Q37) -> 56143077 | S37: =(R37/$R$30) -> 0.10619985 | T37: =IF(S37<=0.8,"A",IF(S37<=0.95,"B","C")) -> A | V37: A. Patel | W37: 46 | X37: 1.0001575e+08 | Y37: 99014357 | Z37: =X37/W37 -> 2174255.5 | AA37: =Y37/W37 -> 2152486 | AB37: =W37/35 -> 1.3142857 | AI37: D. Smith | AJ37: 2 | AK37: 10 | AL37: =AJ37/AK37 -> 0.2
A38: LAP-6499 | B38: 7125420.4 | C38: =SUM($B$33:B38) -> 50428980 | D38: =C38/$C$30 -> 0.14249122 | E38: =IF(D38<=0.8,"A",IF(D38<=0.95,"B","C")) -> A | I38: PRN-6308 | J38: 7655280.4 | K38: =SUM($J$34:J38) -> 48733900 | L38: =(K38/$K$31) -> 0.13395122 | M38: =IF(L38<=0.8,"A",IF(L38<=0.95,"B","C")) -> A | P38: NET-5987 | Q38: 8397062.2 | R38: =SUM($Q$33:Q38) -> 64540139 | S38: =(R38/$R$30) -> 0.12208368 | T38: =IF(S38<=0.8,"A",IF(S38<=0.95,"B","C")) -> A | V38: B. Chen | W38: 48 | X38: 99677187 | Y38: 98679374 | Z38: =X38/W38 -> 2076608.1 | AA38: =Y38/W38 -> 2055820.3 | AB38: =W38/35 -> 1.3714286 | AI38: L. Okafor | AJ38: 2 | AK38: 10 | AL38: =AJ38/AK38 -> 0.2
A39: LAP-1739 | B39: 6215972.4 | C39: =SUM($B$33:B39) -> 56644952 | D39: =C39/$C$30 -> 0.16005496 | E39: =IF(D39<=0.8,"A",IF(D39<=0.95,"B","C")) -> A | I39: PRN-1654 | J39: 7412028.6 | K39: =SUM($J$34:J39) -> 56145929 | L39: =(K39/$K$31) -> 0.15432411 | M39: =IF(L39<=0.8,"A",IF(L39<=0.95,"B","C")) -> A | P39: CMP-2096 | Q39: 7457794.3 | R39: =SUM($Q$33:Q39) -> 71997933 | S39: =(R39/$R$30) -> 0.13619079 | T39: =IF(S39<=0.8,"A",IF(S39<=0.95,"B","C")) -> A | V39: L. Okafor | W39: 45 | X39: 94208105 | Y39: 93265018 | Z39: =X39/W39 -> 2093513.4 | AA39: =Y39/W39 -> 2072556 | AB39: =W39/35 -> 1.2857143 | AI39: C. Otieno | AJ39: 2 | AK39: 8 | AL39: =AJ39/AK39 -> 0.25
A40: LAP-8825 | B40: 5805765 | C40: =SUM($B$33:B40) -> 62450717 | D40: =C40/$C$30 -> 0.17645962 | E40: =IF(D40<=0.8,"A",IF(D40<=0.95,"B","C")) -> A | I40: PRN-7019 | J40: 6602824.7 | K40: =SUM($J$34:J40) -> 62748753 | L40: =(K40/$K$31) -> 0.1724728 | M40: =IF(L40<=0.8,"A",IF(L40<=0.95,"B","C")) -> A | P40: NET-5018 | Q40: 7174700.1 | R40: =SUM($Q$33:Q40) -> 79172634 | S40: =(R40/$R$30) -> 0.1497624 | T40: =IF(S40<=0.8,"A",IF(S40<=0.95,"B","C")) -> A | V40: J. Njeri | W40: 50 | X40: 92750642 | Y40: 91821872 | Z40: =X40/W40 -> 1855012.8 | AA40: =Y40/W40 -> 1836437.4 | AB40: =W40/35 -> 1.4285714 | AI40: I. Johnson | AJ40: 2 | AK40: 8 | AL40: =AJ40/AK40 -> 0.25
A41: LAP-1308 | B41: 5628726.1 | C41: =SUM($B$33:B41) -> 68079443 | D41: =C41/$C$30 -> 0.19236405 | E41: =IF(D41<=0.8,"A",IF(D41<=0.95,"B","C")) -> A | I41: MON-9662 | J41: 6256289.4 | K41: =SUM($J$34:J41) -> 69005043 | L41: =(K41/$K$31) -> 0.18966899 | M41: =IF(L41<=0.8,"A",IF(L41<=0.95,"B","C")) -> A | P41: CMP-3731 | Q41: 7148968.1 | R41: =SUM($Q$33:Q41) -> 86321602 | S41: =(R41/$R$30) -> 0.16328534 | T41: =IF(S41<=0.8,"A",IF(S41<=0.95,"B","C")) -> A | V41: F. Müller | W41: 51 | X41: 89929451 | Y41: 89029281 | Z41: =X41/W41 -> 1763322.6 | AA41: =Y41/W41 -> 1745672.2 | AB41: =W41/35 -> 1.4571429 | AI41: Unidentified sales person | AJ41: 1 | AK41: 2 | AL41: =AJ41/AK41 -> 0.5
A42: LAP-1178 | B42: 5334653.2 | C42: =SUM($B$33:B42) -> 73414097 | D42: =C42/$C$30 -> 0.20743755 | E42: =IF(D42<=0.8,"A",IF(D42<=0.95,"B","C")) -> A | I42: PRN-2407 | J42: 5340171.7 | K42: =SUM($J$34:J42) -> 74345214 | L42: =(K42/$K$31) -> 0.20434712 | M42: =IF(L42<=0.8,"A",IF(L42<=0.95,"B","C")) -> A | P42: NET-1612 | Q42: 7055280 | R42: =SUM($Q$33:Q42) -> 93376882 | S42: =(R42/$R$30) -> 0.17663106 | T42: =IF(S42<=0.8,"A",IF(S42<=0.95,"B","C")) -> A | V42: H. Kim | W42: 45 | X42: 82299566 | Y42: 81475315 | Z42: =X42/W42 -> 1828879.2 | AA42: =Y42/W42 -> 1810562.6 | AB42: =W42/35 -> 1.2857143 | AI42: E. Garcia | AJ42: 1 | AK42: 5 | AL42: =AJ42/AK42 -> 0.2
A43: PHN-8368 | B43: 5278007 | C43: =SUM($B$33:B43) -> 78692104 | D43: =C43/$C$30 -> 0.22235099 | E43: =IF(D43<=0.8,"A",IF(D43<=0.95,"B","C")) -> A | I43: MON-5386 | J43: 5078104.3 | K43: =SUM($J$34:J43) -> 79423319 | L43: =(K43/$K$31) -> 0.21830493 | M43: =IF(L43<=0.8,"A",IF(L43<=0.95,"B","C")) -> A | P43: CMP-2040 | Q43: 7018754.6 | R43: =SUM($Q$33:Q43) -> 1.0039564e+08 | S43: =(R43/$R$30) -> 0.18990769 | T43: =IF(S43<=0.8,"A",IF(S43<=0.95,"B","C")) -> A | V43: C. Otieno | W43: 37 | X43: 81703074 | Y43: 80884758 | Z43: =X43/W43 -> 2208191.2 | AA43: =Y43/W43 -> 2186074.5 | AB43: =W43/35 -> 1.0571429 | AI43: H. Kim | AJ43: 1 | AK43: 7 | AL43: =AJ43/AK43 -> 0.14285714
A44: PHN-5683 | B44: 4977729.7 | C44: =SUM($B$33:B44) -> 83669833 | D44: =C44/$C$30 -> 0.23641598 | E44: =IF(D44<=0.8,"A",IF(D44<=0.95,"B","C")) -> A | I44: PRN-5384 | J44: 4867725.3 | K44: =SUM($J$34:J44) -> 84291044 | L44: =(K44/$K$31) -> 0.23168448 | M44: =IF(L44<=0.8,"A",IF(L44<=0.95,"B","C")) -> A | P44: NET-6036 | Q44: 6320497.8 | R44: =SUM($Q$33:Q44) -> 1.0671613e+08 | S44: =(R44/$R$30) -> 0.2018635 | T44: =IF(S44<=0.8,"A",IF(S44<=0.95,"B","C")) -> A | V44: O. Wang | W44: 37 | X44: 75713644 | Y44: 74955403 | Z44: =X44/W44 -> 2046314.7 | AA44: =Y44/W44 -> 2025821.7 | AB44: =W44/35 -> 1.0571429 | AI44: N. Brown | AJ44: 0 | AK44: 4 | AL44: =AJ44/AK44 -> 0
A45: LAP-7523 | B45: 4860461.3 | C45: =SUM($B$33:B45) -> 88530295 | D45: =C45/$C$30 -> 0.25014961 | E45: =IF(D45<=0.8,"A",IF(D45<=0.95,"B","C")) -> A | I45: MON-9733 | J45: 4748447.8 | K45: =SUM($J$34:J45) -> 89039492 | L45: =(K45/$K$31) -> 0.24473618 | M45: =IF(L45<=0.8,"A",IF(L45<=0.95,"B","C")) -> A | P45: ACC-2988 | Q45: 6237253.5 | R45: =SUM($Q$33:Q45) -> 1.1295339e+08 | S45: =(R45/$R$30) -> 0.21366184 | T45: =IF(S45<=0.8,"A",IF(S45<=0.95,"B","C")) -> A | V45: D. Smith | W45: 38 | X45: 64440180 | Y45: 63795095 | Z45: =X45/W45 -> 1695794.2 | AA45: =Y45/W45 -> 1678818.3 | AB45: =W45/35 -> 1.0857143 | AI45: G. Dubois | AJ45: 0 | AK45: 3 | AL45: =AJ45/AK45 -> 0
A46: LAP-4483 | B46: 4838375.6 | C46: =SUM($B$33:B46) -> 93368670 | D46: =C46/$C$30 -> 0.26382083 | E46: =IF(D46<=0.8,"A",IF(D46<=0.95,"B","C")) -> A | I46: PRN-6131 | J46: 4676542.6 | K46: =SUM($J$34:J46) -> 93716034 | L46: =(K46/$K$31) -> 0.25759025 | M46: =IF(L46<=0.8,"A",IF(L46<=0.95,"B","C")) -> A | P46: NET-1282 | Q46: 6052997.7 | R46: =SUM($Q$33:Q46) -> 1.1900639e+08 | S46: =(R46/$R$30) -> 0.22511165 | T46: =IF(S46<=0.8,"A",IF(S46<=0.95,"B","C")) -> A | V46: I. Johnson | W46: 38 | X46: 62522858 | Y46: 61896780 | Z46: =X46/W46 -> 1645338.4 | AA46: =Y46/W46 -> 1628862.6 | AB46: =W46/35 -> 1.0857143 | AI46: O. Wang | AJ46: 0 | AK46: 9 | AL46: =AJ46/AK46 -> 0
... A49: PHN-7488 | B49: 4410479.6 | C49: =SUM($B$33:B49) -> 1.0690441e+08 | D49: =C49/$C$30 -> 0.30206718 | E49: =IF(D49<=0.8,"A",IF(D49<=0.95,"B","C")) -> A | I49: PRN-9490 | J49: 4390794 | K49: =SUM($J$34:J49) -> 1.0705113e+08 | L49: =(K49/$K$31) -> 0.29424343 | M49: =IF(L49<=0.8,"A",IF(L49<=0.95,"B","C")) -> A | P49: CMP-8127 | Q49: 5880911.3 | R49: =SUM($Q$33:Q49) -> 1.3678199e+08 | S49: =(R49/$R$30) -> 0.25873586 | T49: =IF(S49<=0.8,"A",IF(S49<=0.95,"B","C")) -> A | V49: N. Brown | W49: 32 | X49: 43529928 | Y49: 43094155 | Z49: =X49/W49 -> 1360310.3 | AA49: =Y49/W49 -> 1346692.3 | AB49: =W49/35 -> 0.91428571 | AI49: F. Müller | AJ49: 0 | AK49: 13 | AL49: =AJ49/AK49 -> 0
A50: PHN-4568 | B50: 4339824.4 | C50: =SUM($B$33:B50) -> 1.1124424e+08 | D50: =C50/$C$30 -> 0.31432971 | E50: =IF(D50<=0.8,"A",IF(D50<=0.95,"B","C")) -> A | I50: MON-9967 | J50: 4267039.6 | K50: =SUM($J$34:J50) -> 1.1131817e+08 | L50: =(K50/$K$31) -> 0.30597192 | M50: =IF(L50<=0.8,"A",IF(L50<=0.95,"B","C")) -> A | P50: NET-3828 | Q50: 5236313.1 | R50: =SUM($Q$33:Q50) -> 1.420183e+08 | S50: =(R50/$R$30) -> 0.26864083 | T50: =IF(S50<=0.8,"A",IF(S50<=0.95,"B","C")) -> A | V50: Unidentified sales person | W50: 8 | X50: 29653651 | Y50: 29356635 | AA50: =Y50/W50 -> 3669579.4 | AB50: =W50/35 -> 0.22857143 | AH50: Africa Total | AJ50: 22 | AK50: 145 | AL50: =AJ50/AK50 -> 0.15172414
A51: PHN-1197 | B51: 4320990.1 | C51: =SUM($B$33:B51) -> 1.1556523e+08 | D51: =C51/$C$30 -> 0.32653902 | E51: =IF(D51<=0.8,"A",IF(D51<=0.95,"B","C")) -> A | I51: PRN-7079 | J51: 4234221.7 | K51: =SUM($J$34:J51) -> 1.1555239e+08 | L51: =(K51/$K$31) -> 0.31761021 | M51: =IF(L51<=0.8,"A",IF(L51<=0.95,"B","C")) -> A | P51: NET-3535 | Q51: 4829120.4 | R51: =SUM($Q$33:Q51) -> 1.4684742e+08 | S51: =(R51/$R$30) -> 0.27777556 | T51: =IF(S51<=0.8,"A",IF(S51<=0.95,"B","C")) -> A | V51: Grand Total | W51: 631 | X51: 1.2463826e+09 | Y51: 1.2339033e+09 | AB51: =W51/35 -> 18.028571 | AH51: Americas | AI51: I. Johnson | AJ51: 5 | AK51: 14 | AL51: =AJ51/AK51 -> 0.35714286
A52: PHN-8804 | B52: 4232484.3 | C52: =SUM($B$33:B52) -> 1.1979771e+08 | D52: =C52/$C$30 -> 0.33849825 | E52: =IF(D52<=0.8,"A",IF(D52<=0.95,"B","C")) -> A | I52: PRN-4911 | J52: 4078284.2 | K52: =SUM($J$34:J52) -> 1.1963068e+08 | L52: =(K52/$K$31) -> 0.32881988 | M52: =IF(L52<=0.8,"A",IF(L52<=0.95,"B","C")) -> A | P52: ACC-9533 | Q52: 4782420.8 | R52: =SUM($Q$33:Q52) -> 1.5162984e+08 | S52: =(R52/$R$30) -> 0.28682195 | T52: =IF(S52<=0.8,"A",IF(S52<=0.95,"B","C")) -> A | AI52: A. Patel | AJ52: 5 | AK52: 10 | AL52: =AJ52/AK52 -> 0.5
A53: LAP-3220 | B53: 4160525.8 | C53: =SUM($B$33:B53) -> 1.2395824e+08 | D53: =C53/$C$30 -> 0.35025416 | E53: =IF(D53<=0.8,"A",IF(D53<=0.95,"B","C")) -> A | I53: PRN-5876 | J53: 4070822.3 | K53: =SUM($J$34:J53) -> 1.237015e+08 | L53: =(K53/$K$31) -> 0.34000905 | M53: =IF(L53<=0.8,"A",IF(L53<=0.95,"B","C")) -> A | P53: ACC-9283 | Q53: 4645026 | R53: =SUM($Q$33:Q53) -> 1.5627487e+08 | S53: =(R53/$R$30) -> 0.29560845 | T53: =IF(S53<=0.8,"A",IF(S53<=0.95,"B","C")) -> A | AI53: D. Smith | AJ53: 4 | AK53: 8 | AL53: =AJ53/AK53 -> 0.5
A54: PHN-7974 | B54: 4156703.5 | C54: =SUM($B$33:B54) -> 1.2811494e+08 | D54: =C54/$C$30 -> 0.36199927 | E54: =IF(D54<=0.8,"A",IF(D54<=0.95,"B","C")) -> A | I54: PRN-2293 | J54: 4032531 | K54: =SUM($J$34:J54) -> 1.2773403e+08 | L54: =(K54/$K$31) -> 0.35109296 | M54: =IF(L54<=0.8,"A",IF(L54<=0.95,"B","C")) -> A | P54: NET-1699 | Q54: 4550542.2 | R54: =SUM($Q$33:Q54) -> 1.6082541e+08 | S54: =(R54/$R$30) -> 0.30421623 | T54: =IF(S54<=0.8,"A",IF(S54<=0.95,"B","C")) -> A | AI54: L. Okafor | AJ54: 3 | AK54: 12 | AL54: =AJ54/AK54 -> 0.25
A55: PHN-4915 | B55: 4097952.7 | C55: =SUM($B$33:B55) -> 1.3221289e+08 | D55: =C55/$C$30 -> 0.37357837 | E55: =IF(D55<=0.8,"A",IF(D55<=0.95,"B","C")) -> A | I55: MON-8651 | J55: 4016721 | K55: =SUM($J$34:J55) -> 1.3175075e+08 | L55: =(K55/$K$31) -> 0.36213342 | M55: =IF(L55<=0.8,"A",IF(L55<=0.95,"B","C")) -> A | P55: NET-6370 | Q55: 4500364.7 | R55: =SUM($Q$33:Q55) -> 1.6532577e+08 | S55: =(R55/$R$30) -> 0.31272909 | T55: =IF(S55<=0.8,"A",IF(S55<=0.95,"B","C")) -> A | AI55: C. Otieno | AJ55: 2 | AK55: 14 | AL55: =AJ55/AK55 -> 0.14285714
A56: LAP-3385 | B56: 4079915 | C56: =SUM($B$33:B56) -> 1.3629281e+08 | D56: =C56/$C$30 -> 0.3851065 | E56: =IF(D56<=0.8,"A",IF(D56<=0.95,"B","C")) -> A | I56: PRN-1504 | J56: 3936048.3 | K56: =SUM($J$34:J56) -> 1.356868e+08 | L56: =(K56/$K$31) -> 0.37295214 | M56: =IF(L56<=0.8,"A",IF(L56<=0.95,"B","C")) -> A | P56: NET-5195 | Q56: 4404241 | R56: =SUM($Q$33:Q56) -> 1.6973002e+08 | S56: =(R56/$R$30) -> 0.32106012 | T56: =IF(S56<=0.8,"A",IF(S56<=0.95,"B","C")) -> A | AI56: M. Rossi | AJ56: 2 | AK56: 12 | AL56: =AJ56/AK56 -> 0.16666667
A57: LAP-7553 | B57: 4047936.8 | C57: =SUM($B$33:B57) -> 1.4034074e+08 | D57: =C57/$C$30 -> 0.39654428 | E57: =IF(D57<=0.8,"A",IF(D57<=0.95,"B","C")) -> A | I57: PRN-2749 | J57: 3833362.1 | K57: =SUM($J$34:J57) -> 1.3952016e+08 | L57: =(K57/$K$31) -> 0.38348862 | M57: =IF(L57<=0.8,"A",IF(L57<=0.95,"B","C")) -> A | P57: NET-1893 | Q57: 4378573.8 | R57: =SUM($Q$33:Q57) -> 1.7410859e+08 | S57: =(R57/$R$30) -> 0.3293426 | T57: =IF(S57<=0.8,"A",IF(S57<=0.95,"B","C")) -> A | AI57: N. Brown | AJ57: 1 | AK57: 7 | AL57: =AJ57/AK57 -> 0.14285714
A58: PHN-6832 | B58: 3954379 | C58: =SUM($B$33:B58) -> 1.4429512e+08 | D58: =C58/$C$30 -> 0.4077177 | E58: =IF(D58<=0.8,"A",IF(D58<=0.95,"B","C")) -> A | I58: MON-6310 | J58: 3772060.8 | K58: =SUM($J$34:J58) -> 1.4329222e+08 | L58: =(K58/$K$31) -> 0.3938566 | M58: =IF(L58<=0.8,"A",IF(L58<=0.95,"B","C")) -> A | P58: NET-5268 | Q58: 4373270.7 | R58: =SUM($Q$33:Q58) -> 1.7848186e+08 | S58: =(R58/$R$30) -> 0.33761504 | T58: =IF(S58<=0.8,"A",IF(S58<=0.95,"B","C")) -> A | AI58: K. Singh | AJ58: 1 | AK58: 10 | AL58: =AJ58/AK58 -> 0.1
A59: LAP-4828 | B59: 3939411.1 | C59: =SUM($B$33:B59) -> 1.4823453e+08 | D59: =C59/$C$30 -> 0.41884883 | E59: =IF(D59<=0.8,"A",IF(D59<=0.95,"B","C")) -> A | I59: MON-1018 | J59: 3713060.7 | K59: =SUM($J$34:J59) -> 1.4700528e+08 | L59: =(K59/$K$31) -> 0.40406241 | M59: =IF(L59<=0.8,"A",IF(L59<=0.95,"B","C")) -> A | P59: CMP-5006 | Q59: 4344182.3 | R59: =SUM($Q$33:Q59) -> 1.8282604e+08 | S59: =(R59/$R$30) -> 0.34583247 | T59: =IF(S59<=0.8,"A",IF(S59<=0.95,"B","C")) -> A | AI59: F. Müller | AJ59: 1 | AK59: 15 | AL59: =AJ59/AK59 -> 0.066666667
A60: PHN-6111 | B60: 3829712.9 | C60: =SUM($B$33:B60) -> 1.5206425e+08 | D60: =C60/$C$30 -> 0.42967 | E60: =IF(D60<=0.8,"A",IF(D60<=0.95,"B","C")) -> A | I60: MON-4925 | J60: 3708584.4 | K60: =SUM($J$34:J60) -> 1.5071387e+08 | L60: =(K60/$K$31) -> 0.41425592 | M60: =IF(L60<=0.8,"A",IF(L60<=0.95,"B","C")) -> A | P60: CMP-1940 | Q60: 4312464.6 | R60: =SUM($Q$33:Q60) -> 1.8713851e+08 | S60: =(R60/$R$30) -> 0.3539899 | T60: =IF(S60<=0.8,"A",IF(S60<=0.95,"B","C")) -> A | AI60: G. Dubois | AJ60: 1 | AK60: 8 | AL60: =AJ60/AK60 -> 0.125
A61: LAP-3679 | B61: 3591587.9 | C61: =SUM($B$33:B61) -> 1.5565584e+08 | D61: =C61/$C$30 -> 0.43981833 | E61: =IF(D61<=0.8,"A",IF(D61<=0.95,"B","C")) -> A | I61: MON-6341 | J61: 3702978.9 | K61: =SUM($J$34:J61) -> 1.5441685e+08 | L61: =(K61/$K$31) -> 0.42443402 | M61: =IF(L61<=0.8,"A",IF(L61<=0.95,"B","C")) -> A | P61: ACC-8098 | Q61: 4271005.5 | R61: =SUM($Q$33:Q61) -> 1.9140951e+08 | S61: =(R61/$R$30) -> 0.3620689 | T61: =IF(S61<=0.8,"A",IF(S61<=0.95,"B","C")) -> A | AI61: Unidentified sales person | AJ61: 1 | AK61: 3 | AL61: =AJ61/AK61 -> 0.33333333
A62: PHN-9234 | B62: 3566640.7 | C62: =SUM($B$33:B62) -> 1.5922248e+08 | D62: =C62/$C$30 -> 0.44989616 | E62: =IF(D62<=0.8,"A",IF(D62<=0.95,"B","C")) -> A | I62: PRN-9624 | J62: 3624045.9 | K62: =SUM($J$34:J62) -> 1.5804089e+08 | L62: =(K62/$K$31) -> 0.43439517 | M62: =IF(L62<=0.8,"A",IF(L62<=0.95,"B","C")) -> A | P62: NET-8957 | Q62: 4233209 | R62: =SUM($Q$33:Q62) -> 1.9564272e+08 | S62: =(R62/$R$30) -> 0.37007641 | T62: =IF(S62<=0.8,"A",IF(S62<=0.95,"B","C")) -> A | AI62: B. Chen | AJ62: 1 | AK62: 8 | AL62: =AJ62/AK62 -> 0.125
A63: PHN-2859 | B63: 3554993.6 | C63: =SUM($B$33:B63) -> 1.6277747e+08 | D63: =C63/$C$30 -> 0.45994109 | E63: =IF(D63<=0.8,"A",IF(D63<=0.95,"B","C")) -> A | I63: MON-4373 | J63: 3610950.1 | K63: =SUM($J$34:J63) -> 1.6165184e+08 | L63: =(K63/$K$31) -> 0.44432031 | M63: =IF(L63<=0.8,"A",IF(L63<=0.95,"B","C")) -> A | P63: ACC-4490 | Q63: 4081853 | R63: =SUM($Q$33:Q63) -> 1.9972457e+08 | S63: =(R63/$R$30) -> 0.37779762 | T63: =IF(S63<=0.8,"A",IF(S63<=0.95,"B","C")) -> A | AI63: E. Garcia | AJ63: 0 | AK63: 5 | AL63: =AJ63/AK63 -> 0
... A66: LAP-8633 | B66: 3424327.8 | C66: =SUM($B$33:B66) -> 1.731621e+08 | D66: =C66/$C$30 -> 0.48928371 | E66: =IF(D66<=0.8,"A",IF(D66<=0.95,"B","C")) -> A | I66: PRN-7089 | J66: 3427604.1 | K66: =SUM($J$34:J66) -> 1.7213751e+08 | L66: =(K66/$K$31) -> 0.47314147 | M66: =IF(L66<=0.8,"A",IF(L66<=0.95,"B","C")) -> A | P66: NET-2062 | Q66: 3905129.2 | R66: =SUM($Q$33:Q66) -> 2.1148868e+08 | S66: =(R66/$R$30) -> 0.40005052 | T66: =IF(S66<=0.8,"A",IF(S66<=0.95,"B","C")) -> A | AI66: H. Kim | AJ66: 0 | AK66: 9 | AL66: =AJ66/AK66 -> 0
A67: LAP-7099 | B67: 3419910.4 | C67: =SUM($B$33:B67) -> 1.7658201e+08 | D67: =C67/$C$30 -> 0.49894694 | E67: =IF(D67<=0.8,"A",IF(D67<=0.95,"B","C")) -> A | I67: PRN-4732 | J67: 3342110 | K67: =SUM($J$34:J67) -> 1.7547962e+08 | L67: =(K67/$K$31) -> 0.48232768 | M67: =IF(L67<=0.8,"A",IF(L67<=0.95,"B","C")) -> A | P67: CMP-8002 | Q67: 3819229.7 | R67: =SUM($Q$33:Q67) -> 2.1530791e+08 | S67: =(R67/$R$30) -> 0.40727495 | T67: =IF(S67<=0.8,"A",IF(S67<=0.95,"B","C")) -> A | AH67: Americas Total | AJ67: 27 | AK67: 157 | AL67: =AJ67/AK67 -> 0.17197452
A68: PHN-4677 | B68: 3301742 | C68: =SUM($B$33:B68) -> 1.7988375e+08 | D68: =C68/$C$30 -> 0.50827629 | E68: =IF(D68<=0.8,"A",IF(D68<=0.95,"B","C")) -> A | I68: MON-7869 | J68: 3179032.3 | K68: =SUM($J$34:J68) -> 1.7865865e+08 | L68: =(K68/$K$31) -> 0.49106565 | M68: =IF(L68<=0.8,"A",IF(L68<=0.95,"B","C")) -> A | P68: ACC-7078 | Q68: 3773607.2 | R68: =SUM($Q$33:Q68) -> 2.1908152e+08 | S68: =(R68/$R$30) -> 0.41441308 | T68: =IF(S68<=0.8,"A",IF(S68<=0.95,"B","C")) -> A | AH68: Asia | AI68: O. Wang | AJ68: 4 | AK68: 8 | AL68: =AJ68/AK68 -> 0.5
A69: PHN-7379 | B69: 3227767 | C69: =SUM($B$33:B69) -> 1.8311152e+08 | D69: =C69/$C$30 -> 0.51739661 | E69: =IF(D69<=0.8,"A",IF(D69<=0.95,"B","C")) -> A | I69: MON-1118 | J69: 3117070.3 | K69: =SUM($J$34:J69) -> 1.8177572e+08 | L69: =(K69/$K$31) -> 0.49963331 | M69: =IF(L69<=0.8,"A",IF(L69<=0.95,"B","C")) -> A | P69: NET-4675 | Q69: 3734152.6 | R69: =SUM($Q$33:Q69) -> 2.2281567e+08 | S69: =(R69/$R$30) -> 0.42147657 | T69: =IF(S69<=0.8,"A",IF(S69<=0.95,"B","C")) -> A | V69: CHANNEL MIXING & CANNIBALIZATION | AI69: F. Müller | AJ69: 3 | AK69: 12 | AL69: =AJ69/AK69 -> 0.25
A70: LAP-7979 | B70: 3182862.7 | C70: =SUM($B$33:B70) -> 1.8629438e+08 | D70: =C70/$C$30 -> 0.52639005 | E70: =IF(D70<=0.8,"A",IF(D70<=0.95,"B","C")) -> A | I70: PRN-1371 | J70: 3113944 | K70: =SUM($J$34:J70) -> 1.8488966e+08 | L70: =(K70/$K$31) -> 0.50819237 | M70: =IF(L70<=0.8,"A",IF(L70<=0.95,"B","C")) -> A | P70: ACC-1375 | Q70: 3732338 | R70: =SUM($Q$33:Q70) -> 2.2654801e+08 | S70: =(R70/$R$30) -> 0.42853664 | T70: =IF(S70<=0.8,"A",IF(S70<=0.95,"B","C")) -> A | V70: Sum of Gross Revenue | W70: Channel | AI70: L. Okafor | AJ70: 3 | AK70: 13 | AL70: =AJ70/AK70 -> 0.23076923
A71: LAP-6989 | B71: 3072467.3 | C71: =SUM($B$33:B71) -> 1.8936685e+08 | D71: =C71/$C$30 -> 0.53507155 | E71: =IF(D71<=0.8,"A",IF(D71<=0.95,"B","C")) -> A | I71: MON-8758 | J71: 3113132.6 | K71: =SUM($J$34:J71) -> 1.8800279e+08 | L71: =(K71/$K$31) -> 0.51674921 | M71: =IF(L71<=0.8,"A",IF(L71<=0.95,"B","C")) -> A | P71: NET-2460 | Q71: 3687032 | R71: =SUM($Q$33:Q71) -> 2.3023504e+08 | S71: =(R71/$R$30) -> 0.435511 | T71: =IF(S71<=0.8,"A",IF(S71<=0.95,"B","C")) -> A | V71: Region | W71: Direct | X71: Distributor | Y71: Marketplace | Z71: Online | AA71: Retail | AB71: Unknown Channel | AC71: Grand Total | AI71: C. Otieno | AJ71: 3 | AK71: 10 | AL71: =AJ71/AK71 -> 0.3
A72: LAP-9230 | B72: 3051422.8 | C72: =SUM($B$33:B72) -> 1.9241827e+08 | D72: =C72/$C$30 -> 0.5436936 | E72: =IF(D72<=0.8,"A",IF(D72<=0.95,"B","C")) -> A | I72: MON-3043 | J72: 3018191.2 | K72: =SUM($J$34:J72) -> 1.9102099e+08 | L72: =(K72/$K$31) -> 0.52504508 | M72: =IF(L72<=0.8,"A",IF(L72<=0.95,"B","C")) -> A | P72: CMP-6529 | Q72: 3682491 | R72: =SUM($Q$33:Q72) -> 2.3391753e+08 | S72: =(R72/$R$30) -> 0.44247678 | T72: =IF(S72<=0.8,"A",IF(S72<=0.95,"B","C")) -> A | V72: Africa | W72: 0.1756045 | X72: 0.24366183 | Y72: 0.20562035 | Z72: 0.1670339 | AA72: 0.19580382 | AB72: 0.012275599 | AC72: 1 | AI72: B. Chen | AJ72: 2 | AK72: 17 | AL72: =AJ72/AK72 -> 0.11764706
A73: PHN-7815 | B73: 3022387.9 | C73: =SUM($B$33:B73) -> 1.9544066e+08 | D73: =C73/$C$30 -> 0.5522336 | E73: =IF(D73<=0.8,"A",IF(D73<=0.95,"B","C")) -> A | I73: PRN-6791 | J73: 2909105.6 | K73: =SUM($J$34:J73) -> 1.9393009e+08 | L73: =(K73/$K$31) -> 0.53304112 | M73: =IF(L73<=0.8,"A",IF(L73<=0.95,"B","C")) -> A | P73: NET-1228 | Q73: 3572132.4 | R73: =SUM($Q$33:Q73) -> 2.3748966e+08 | S73: =(R73/$R$30) -> 0.4492338 | T73: =IF(S73<=0.8,"A",IF(S73<=0.95,"B","C")) -> A | V73: Americas | W73: 0.27653606 | X73: 0.21317387 | Y73: 0.13591975 | Z73: 0.2559473 | AA73: 0.1154061 | AB73: 0.0030169209 | AC73: 1 | AI73: J. Njeri | AJ73: 2 | AK73: 19 | AL73: =AJ73/AK73 -> 0.10526316
A74: LAP-3393 | B74: 3019549.5 | C74: =SUM($B$33:B74) -> 1.9846021e+08 | D74: =C74/$C$30 -> 0.56076559 | E74: =IF(D74<=0.8,"A",IF(D74<=0.95,"B","C")) -> A | I74: PRN-2829 | J74: 2898955 | K74: =SUM($J$34:J74) -> 1.9682905e+08 | L74: =(K74/$K$31) -> 0.54100926 | M74: =IF(L74<=0.8,"A",IF(L74<=0.95,"B","C")) -> A | P74: NET-4491 | Q74: 3569037.3 | R74: =SUM($Q$33:Q74) -> 2.410587e+08 | S74: =(R74/$R$30) -> 0.45598496 | T74: =IF(S74<=0.8,"A",IF(S74<=0.95,"B","C")) -> A | V74: Asia | W74: 0.22378659 | X74: 0.18161315 | Y74: 0.20225048 | Z74: 0.14063826 | AA74: 0.23652739 | AB74: 0.015184135 | AC74: 1 | AI74: H. Kim | AJ74: 2 | AK74: 16 | AL74: =AJ74/AK74 -> 0.125
A75: PHN-4854 | B75: 2867957.2 | C75: =SUM($B$33:B75) -> 2.0132816e+08 | D75: =C75/$C$30 -> 0.56886924 | E75: =IF(D75<=0.8,"A",IF(D75<=0.95,"B","C")) -> A | I75: PRN-1271 | J75: 2837445.8 | K75: =SUM($J$34:J75) -> 1.9966649e+08 | L75: =(K75/$K$31) -> 0.54880834 | M75: =IF(L75<=0.8,"A",IF(L75<=0.95,"B","C")) -> A | P75: ACC-9162 | Q75: 3560175.8 | R75: =SUM($Q$33:Q75) -> 2.4461888e+08 | S75: =(R75/$R$30) -> 0.46271937 | T75: =IF(S75<=0.8,"A",IF(S75<=0.95,"B","C")) -> A | V75: Europe | W75: 0.30817851 | X75: 0.11136842 | Y75: 0.20601877 | Z75: 0.21021137 | AA75: 0.15811115 | AB75: 0.0061117815 | AC75: 1 | AI75: N. Brown | AJ75: 1 | AK75: 10 | AL75: =AJ75/AK75 -> 0.1
A76: PHN-3077 | B76: 2854060.1 | C76: =SUM($B$33:B76) -> 2.0418222e+08 | D76: =C76/$C$30 -> 0.57693362 | E76: =IF(D76<=0.8,"A",IF(D76<=0.95,"B","C")) -> A | I76: PRN-5753 | J76: 2822288.3 | K76: =SUM($J$34:J76) -> 2.0248878e+08 | L76: =(K76/$K$31) -> 0.55656575 | M76: =IF(L76<=0.8,"A",IF(L76<=0.95,"B","C")) -> A | P76: NET-1645 | Q76: 3502818.3 | R76: =SUM($Q$33:Q76) -> 2.481217e+08 | S76: =(R76/$R$30) -> 0.46934527 | T76: =IF(S76<=0.8,"A",IF(S76<=0.95,"B","C")) -> A | V76: Grand Total | W76: 0.24670298 | X76: 0.18634497 | Y76: 0.18768193 | Z76: 0.19296737 | AA76: 0.17710896 | AB76: 0.0091937973 | AC76: 1 | AI76: K. Singh | AJ76: 1 | AK76: 7 | AL76: =AJ76/AK76 -> 0.14285714
A77: PHN-8891 | B77: 2724900 | C77: =SUM($B$33:B77) -> 2.0690712e+08 | D77: =C77/$C$30 -> 0.58463305 | E77: =IF(D77<=0.8,"A",IF(D77<=0.95,"B","C")) -> A | I77: MON-2828 | J77: 2746246.8 | K77: =SUM($J$34:J77) -> 2.0523503e+08 | L77: =(K77/$K$31) -> 0.56411415 | M77: =IF(L77<=0.8,"A",IF(L77<=0.95,"B","C")) -> A | P77: ACC-4631 | Q77: 3480696 | R77: =SUM($Q$33:Q77) -> 2.5160239e+08 | S77: =(R77/$R$30) -> 0.47592934 | T77: =IF(S77<=0.8,"A",IF(S77<=0.95,"B","C")) -> A | AI77: G. Dubois | AJ77: 1 | AK77: 11 | AL77: =AJ77/AK77 -> 0.090909091
A78: LAP-2806 | B78: 2718887.3 | C78: =SUM($B$33:B78) -> 2.0962601e+08 | D78: =C78/$C$30 -> 0.59231549 | E78: =IF(D78<=0.8,"A",IF(D78<=0.95,"B","C")) -> A | I78: MON-4959 | J78: 2702616.7 | K78: =SUM($J$34:J78) -> 2.0793764e+08 | L78: =(K78/$K$31) -> 0.57154263 | M78: =IF(L78<=0.8,"A",IF(L78<=0.95,"B","C")) -> A | P78: NET-9177 | Q78: 3430716 | R78: =SUM($Q$33:Q78) -> 2.5503311e+08 | S78: =(R78/$R$30) -> 0.48241885 | T78: =IF(S78<=0.8,"A",IF(S78<=0.95,"B","C")) -> A | AI78: I. Johnson | AJ78: 1 | AK78: 8 | AL78: =AJ78/AK78 -> 0.125
A79: PHN-2341 | B79: 2697649.8 | C79: =SUM($B$33:B79) -> 2.1232366e+08 | D79: =C79/$C$30 -> 0.59993792 | E79: =IF(D79<=0.8,"A",IF(D79<=0.95,"B","C")) -> A | I79: MON-1663 | J79: 2690435.5 | K79: =SUM($J$34:J79) -> 2.1062808e+08 | L79: =(K79/$K$31) -> 0.57893763 | M79: =IF(L79<=0.8,"A",IF(L79<=0.95,"B","C")) -> A | P79: NET-5482 | Q79: 3428658.5 | R79: =SUM($Q$33:Q79) -> 2.5846177e+08 | S79: =(R79/$R$30) -> 0.48890448 | T79: =IF(S79<=0.8,"A",IF(S79<=0.95,"B","C")) -> A | AI79: D. Smith | AJ79: 1 | AK79: 9 | AL79: =AJ79/AK79 -> 0.11111111
A80: PHN-9789 | B80: 2655170.8 | C80: =SUM($B$33:B80) -> 2.1497883e+08 | D80: =C80/$C$30 -> 0.60744032 | E80: =IF(D80<=0.8,"A",IF(D80<=0.95,"B","C")) -> A | I80: PRN-1786 | J80: 2629526.2 | K80: =SUM($J$34:J80) -> 2.1325761e+08 | L80: =(K80/$K$31) -> 0.58616521 | M80: =IF(L80<=0.8,"A",IF(L80<=0.95,"B","C")) -> A | P80: ACC-5177 | Q80: 3413916 | R80: =SUM($Q$33:Q80) -> 2.6187568e+08 | S80: =(R80/$R$30) -> 0.49536222 | T80: =IF(S80<=0.8,"A",IF(S80<=0.95,"B","C")) -> A | AI80: Unidentified sales person | AJ80: 0 | AK80: 2 | AL80: =AJ80/AK80 -> 0
